Workbook

Sheet Delivery Plan
A1: Delivery Plan ID | B1: Campaign | C1: Planning Date | D1: LBA Code | E1: Supplier Name | F1: Expected Origin | G1: Destination Warehouse | H1: Expected Delivery Start | I1: Expected Delivery End | J1: Expected Quantity (kg) | K1: Expected Trucks | L1: Purchase / Funding Reference | M1: Plan Status | N1: Actual Received Quantity (kg) | O1: Actual Arrivals | P1: Accepted Trucks | Q1: Remaining Quantity (kg) | R1: Quantity Variance (kg) | S1: Planning Scenario | T1: Planning Basis
A2: DP-BKE-2026-001 | B2: 2026 | C2: 46069 | D2: LBA-002-SCA | E2: SCAAMT COOP CA | F2: VAVOUA | G2: BKE-003 | H2: 46071 | I2: 46149 | J2: 142424 | K2: 4 | L2: Not available in 2026 source | M2: DELIVERED | N2: =SUMIFS('Truck Reception'!$AD$2:$AD$500,'Truck Reception'!$AJ$2:$AJ$500,A2) -> 142424 | O2: =COUNTIF('Truck Reception'!$AJ$2:$AJ$500,A2) -> 4 | P2: =COUNTIFS('Truck Reception'!$AJ$2:$AJ$500,A2,'Truck Reception'!$AO$2:$AO$500,"STOCKED") -> 3 | Q2: =J2-N2 -> 0 | R2: =N2-J2 -> 0 | S2: NORMAL | T2: Reconstructed from 2026 actual receipts; Delivery Plan did not exist as a structured legacy field.
A3: DP-BKE-2026-002 | B3: 2026 | C3: 46068 | D3: LBA-011-ASR | E3: SCOOP ASER | F3: MANKONO | G3: BKE-001 | H3: 46071 | I3: 46146 | J3: 149036 | K3: 4 | L3: Not available in 2026 source | M3: DELIVERED | N3: =SUMIFS('Truck Reception'!$AD$2:$AD$500,'Truck Reception'!$AJ$2:$AJ$500,A3) -> 149036 | O3: =COUNTIF('Truck Reception'!$AJ$2:$AJ$500,A3) -> 4 | P3: =COUNTIFS('Truck Reception'!$AJ$2:$AJ$500,A3,'Truck Reception'!$AO$2:$AO$500,"STOCKED") -> 3 | Q3: =J3-N3 -> 0 | R3: =N3-J3 -> 0 | S3: EARLY DELIVERY | T3: Reconstructed from 2026 actual receipts; Delivery Plan did not exist as a structured legacy field.
A4: DP-BKE-2026-003 | B4: 2026 | C4: 46075 | D4: LBA-018-COP | E4: SCOOPS COOPRAKA | F4: KATIOLA | G4: BKE-003 | H4: 46077 | I4: 46145 | J4: 116106 | K4: 4 | L4: Not available in 2026 source | M4: DELIVERED | N4: =SUMIFS('Truck Reception'!$AD$2:$AD$500,'Truck Reception'!$AJ$2:$AJ$500,A4) -> 116106 | O4: =COUNTIF('Truck Reception'!$AJ$2:$AJ$500,A4) -> 4 | P4: =COUNTIFS('Truck Reception'!$AJ$2:$AJ$500,A4,'Truck Reception'!$AO$2:$AO$500,"STOCKED") -> 3 | Q4: =J4-N4 -> 0 | R4: =N4-J4 -> 0 | S4: LATE DELIVERY | T4: Reconstructed from 2026 actual receipts; Delivery Plan did not exist as a structured legacy field.
A5: DP-BKE-2026-004 | B5: 2026 | C5: 46120 | D5: LBA-021-SAN | E5: SANOGO SINDOU | F5: MANKONO | H5: 46122 | I5: 46146 | J5: 134389 | K5: 4 | L5: Not available in 2026 source | M5: DELIVERED | N5: =SUMIFS('Truck Reception'!$AD$2:$AD$500,'Truck Reception'!$AJ$2:$AJ$500,A5) -> 134389 | O5: =COUNTIF('Truck Reception'!$AJ$2:$AJ$500,A5) -> 4 | P5: =COUNTIFS('Truck Reception'!$AJ$2:$AJ$500,A5,'Truck Reception'!$AO$2:$AO$500,"STOCKED") -> 3 | Q5: =J5-N5 -> 0 | R5: =N5-J5 -> 0 | S5: ORIGIN MISMATCH | T5: Reconstructed from 2026 actual receipts; Delivery Plan did not exist as a structured legacy field.
A6: DP-BKE-2026-005 | B6: 2026 | C6: 46069 | D6: LBA-004-WEB | E6: SCOOPS WEBE | F6: DABAKALA | G6: BKE-003 | H6: 46071 | I6: 46146 | J6: 126434 | K6: 4 | L6: Not available in 2026 source | M6: DELIVERED | N6: =SUMIFS('Truck Reception'!$AD$2:$AD$500,'Truck Reception'!$AJ$2:$AJ$500,A6) -> 126434 | O6: =COUNTIF('Truck Reception'!$AJ$2:$AJ$500,A6) -> 4 | P6: =COUNTIFS('Truck Reception'!$AJ$2:$AJ$500,A6,'Truck Reception'!$AO$2:$AO$500,"STOCKED") -> 3 | Q6: =J6-N6 -> 0 | R6: =N6-J6 -> 0 | S6: WAREHOUSE CHANGE | T6: Reconstructed from 2026 actual receipts; Delivery Plan did not exist as a structured legacy field.
A7: DP-BKE-2026-006 | B7: 2026 | C7: 46069 | D7: LBA-010-CAP | E7: CAPCD-SCOOPS | F7: BOUAKE | G7: BKE-002 | H7: 46071 | I7: 46145 | J7: 78715 | K7: 3 | L7: Not available in 2026 source | M7: DELIVERED | N7: =SUMIFS('Truck Reception'!$AD$2:$AD$500,'Truck Reception'!$AJ$2:$AJ$500,A7) -> 92606 | O7: =COUNTIF('Truck Reception'!$AJ$2:$AJ$500,A7) -> 3 | P7: =COUNTIFS('Truck Reception'!$AJ$2:$AJ$500,A7,'Truck Reception'!$AO$2:$AO$500,"STOCKED") -> 3 | Q7: =J7-N7 -> -13891 | R7: =N7-J7 -> 13891 | S7: PLAN EXCESS | T7: Reconstructed from 2026 actual receipts; Delivery Plan did not exist as a structured legacy field.
A8: DP-BKE-2026-007 | B8: 2026 | C8: 46068 | D8: LBA-003-HER | E8: SCOOPS HERE B | F8: NIAKARA | G8: BKE-001 | H8: 46070 | I8: 46144 | J8: 135594 | K8: 3 | L8: Not available in 2026 source | M8: CANCELLED | N8: =SUMIFS('Truck Reception'!$AD$2:$AD$500,'Truck Reception'!$AJ$2:$AJ$500,A8) -> 135594 | O8: =COUNTIF('Truck Reception'!$AJ$2:$AJ$500,A8) -> 3 | P8: =COUNTIFS('Truck Reception'!$AJ$2:$AJ$500,A8,'Truck Reception'!$AO$2:$AO$500,"STOCKED") -> 3 | Q8: =J8-N8 -> 0 | R8: =N8-J8 -> 0 | S8: CANCELLED PLAN ARRIVAL | T8: Reconstructed from 2026 actual receipts; Delivery Plan did not exist as a structured legacy field.
A9: DP-BKE-2026-008 | B9: 2026 | C9: 46068 | D9: LBA-015-OUM | E9: SCOOPS-OUMI/KONE SIDY | F9: BOUAKE | G9: BKE-001 | H9: 46070 | I9: 46146 | J9: 141898 | K9: 3 | L9: Not available in 2026 source | M9: DELIVERED | N9: =SUMIFS('Truck Reception'!$AD$2:$AD$500,'Truck Reception'!$AJ$2:$AJ$500,A9) -> 141898 | O9: =COUNTIF('Truck Reception'!$AJ$2:$AJ$500,A9) -> 3 | P9: =COUNTIFS('Truck Reception'!$AJ$2:$AJ$500,A9,'Truck Reception'!$AO$2:$AO$500,"STOCKED") -> 3 | Q9: =J9-N9 -> 0 | R9: =N9-J9 -> 0 | S9: MULTI-TRUCK NORMAL | T9: Reconstructed from 2026 actual receipts; Delivery Plan did not exist as a structured legacy field.
A10: DP-BKE-2026-009 | B10: 2026 | C10: 46072 | D10: LBA-016-NOU | E10: SCOOPS AH AL NOUR | F10: KATIOLA | G10: BKE-001 | H10: 46074 | I10: 46146 | J10: 128412 | K10: 3 | L10: Not available in 2026 source | M10: DELIVERED | N10: =SUMIFS('Truck Reception'!$AD$2:$AD$500,'Truck Reception'!$AJ$2:$AJ$500,A10) -> 128412 | O10: =COUNTIF('Truck Reception'!$AJ$2:$AJ$500,A10) -> 3 | P10: =COUNTIFS('Truck Reception'!$AJ$2:$AJ$500,A10,'Truck Reception'!$AO$2:$AO$500,"STOCKED") -> 3 | Q10: =J10-N10 -> 0 | R10: =N10-J10 -> 0 | S10: MULTI-TRUCK NORMAL | T10: Reconstructed from 2026 actual receipts; Delivery Plan did not exist as a structured legacy field.
A11: DP-BKE-2026-010 | B11: 2026 | C11: 46070 | D11: LBA-005-JAV | E11: COP JAVA SCOOPS | F11: VAVOUA | G11: BKE-003 | H11: 46072 | I11: 46144 | J11: 141583 | K11: 3 | L11: Not available in 2026 source | M11: DELIVERED | N11: =SUMIFS('Truck Reception'!$AD$2:$AD$500,'Truck Reception'!$AJ$2:$AJ$500,A11) -> 141583 | O11: =COUNTIF('Truck Reception'!$AJ$2:$AJ$500,A11) -> 3 | P11: =COUNTIFS('Truck Reception'!$AJ$2:$AJ$500,A11,'Truck Reception'!$AO$2:$AO$500,"STOCKED") -> 3 | Q11: =J11-N11 -> 0 | R11: =N11-J11 -> 0 | S11: MULTI-TRUCK NORMAL | T11: Reconstructed from 2026 actual receipts; Delivery Plan did not exist as a structured legacy field.

Sheet Truck Reception
A1: Receipt ID | B1: Arrival Date | C1: Offloading Date | D1: Payment Type | E1: Warehouse Location | F1: Warehouse Code | G1: Supplier Name | H1: Supplier Code | I1: Truck No | J1: Fiche Code | K1: Fiche No | L1: Origin | M1: Moisture (%) | N1: Nut Count | O1: KOR | P1: Final KOR | Q1: Quality Result | R1: Rejection Reason | S1: Gross Weight (kg) | T1: Tare Weight (kg) | U1: Net Weight (kg) | V1: Paid Weight (kg) | W1: Bags Count | X1: Good Bags | Y1: Humid Bags | Z1: Torn Bags | AA1: Refraction (kg) | AB1: Price (CFA/kg) | AC1: Amount (CFA) | AD1: GRN Quantity (kg) | AE1: Lot No | AF1: Bin No | AG1: Remarks | AH1: Week | AI1: Planned Delivery? | AJ1: Delivery Plan ID | AK1: Reception Type | AL1: Planning / Exception Flag | AM1: Exception Approval Status | AN1: Plan Link Status | AO1: Receipt Status
A2: REC-BKE-2026-0001 | B2: 46069 | C2: 46069 | D2: CREDIT | E2: BOUAKE | F2: BKE-002 | G2: SCOOP IMANE | H2: LBA-006-IMA | I2: 827KT01 | J2: 0401-0007 | K2: 72515 | L2: DIANRA | M2: 10.2 | N2: 172 | O2: 47.69 | P2: 48.4 | Q2: ACCEPTED | S2: 41300 | U2: 40822 | V2: =IF(OR(U2="",AA2=""),"",U2-AA2) -> 40762 | W2: 478 | X2: 463 | Y2: 0 | Z2: 15 | AA2: 60 | AB2: 470 | AC2: =IF(OR(V2="",AB2=""),"",V2*AB2) -> 19158140 | AD2: 40822 | AE2: LOT-BKE-2026-0001 | AH2: W-8 Feb | AI2: NO | AK2: UNPLANNED | AL2: UNPLANNED - known LBA, no pre-alert | AM2: APPROVED | AN2: NOT PLANNED | AO2: STOCKED
A3: REC-BKE-2026-0002 | B3: 46069 | C3: 46069 | D3: CREDIT | E3: BOUAKE | F3: BKE-002 | G3: CASP-S SCOOPS | H3: LBA-007-CAS | I3: 793LT03 | J3: 0429-0040 | K3: 72533 | L3: MANKONO | M3: 9 | N3: 165 | O3: 48.41 | P3: 48.22 | Q3: ACCEPTED | S3: 50880 | U3: 50252 | V3: =IF(OR(U3="",AA3=""),"",U3-AA3) -> 49976 | W3: 628 | X3: 559 | Y3: 0 | Z3: 69 | AA3: 276 | AB3: 490 | AC3: =IF(OR(V3="",AB3=""),"",V3*AB3) -> 24488240 | AD3: 50252 | AE3: LOT-BKE-2026-0002 | AH3: W-8 Feb | AI3: NO | AK3: UNPLANNED | AL3: UNPLANNED - known LBA, no pre-alert | AM3: APPROVED | AN3: NOT PLANNED | AO3: STOCKED
A4: REC-BKE-2026-0003 | B4: 46069 | D4: CREDIT | E4: BOUAKE | G4: CASP-S SCOOPS | H4: LBA-007-CAS | I4: 524LS01 | L4: MANKONO | M4: 8.7 | N4: 164 | O4: 44.35 | Q4: REJECTED | R4: REJECT | S4: 0 | U4: 0 | V4: 0 | W4: 0 | AB4: 0 | AC4: 0 | AG4: REJECT | AI4: NO | AK4: UNPLANNED | AL4: UNPLANNED / QUALITY REJECTED | AM4: N/A - REJECTED | AN4: NOT PLANNED | AO4: REJECTED
A5: REC-BKE-2026-0004 | B5: 46070 | C5: 46070 | D5: CREDIT | E5: BOUAKE | F5: BKE-002 | G5: SCOOPS HERE B | H5: LBA-003-HER | I5: 8287GH03 | J5: 0426-0187 | K5: 72615 | L5: NIAKARA | M5: 11.4 | N5: 162 | O5: 46.11 | Q5: ACCEPTED | S5: 45420 | U5: 44908 | V5: =IF(OR(U5="",AA5=""),"",U5-AA5) -> 44876 | W5: 512 | X5: 504 | Y5: 0 | Z5: 8 | AA5: 32 | AB5: 470 | AC5: =IF(OR(V5="",AB5=""),"",V5*AB5) -> 21091720 | AD5: 44908 | AE5: LOT-BKE-2026-0003 | AF5: BKE-002-BIN-004 / BKE-002-BIN-006 | AH5: W-8 Feb | AI5: YES | AJ5: DP-BKE-2026-007 | AK5: PLANNED WITH EXCEPTION | AL5: PLAN CANCELLED - ARRIVAL RECORDED; WAREHOUSE CHANGE | AM5: APPROVED | AN5: PLANNED FROM START | AO5: STOCKED
A6: REC-BKE-2026-0005 | B6: 46070 | C6: 46070 | D6: CREDIT | E6: BOUAKE | F6: BKE-003 | G6: SCOPPAS SCOOPS | H6: LBA-009-SCO | I6: 338KX01 | J6: 0426-0203 | K6: 72540 | L6: BOUAKE | M6: 9.5 | N6: 166 | O6: 48.57 | P6: 48.04 | Q6: ACCEPTED | S6: 35320 | U6: 34895 | V6: =IF(OR(U6="",AA6=""),"",U6-AA6) -> 34795 | W6: 425 | X6: 400 | Y6: 0 | Z6: 25 | AA6: 100 | AB6: 470 | AC6: =IF(OR(V6="",AB6=""),"",V6*AB6) -> 16353650 | AD6: 34895 | AE6: LOT-BKE-2026-0004 | AH6: W-8 Feb | AI6: NO | AK6: UNPLANNED | AL6: UNPLANNED - known LBA, no pre-alert | AM6: APPROVED | AN6: NOT PLANNED | AO6: STOCKED
A7: REC-BKE-2026-0006 | B7: 46070 | C7: 46070 | D7: CREDIT | E7: BOUAKE | F7: BKE-002 | G7: DAGNOGO KARIM | H7: LBA-013-DAG | I7: 3633LZ04 | J7: 0425-0068 | K7: 72569 | L7: NIAKARA | M7: 11.5 | N7: 161 | O7: 47.87 | Q7: ACCEPTED | S7: 50760 | U7: 50174 | V7: =IF(OR(U7="",AA7=""),"",U7-AA7) -> 49622 | W7: 586 | X7: 556 | Y7: 12 | Z7: 18 | AA7: 552 | AB7: 470 | AC7: =IF(OR(V7="",AB7=""),"",V7*AB7) -> 23322340 | AD7: 50174 | AE7: LOT-BKE-2026-0005 | AF7: BKE-002-BIN-003 | AH7: W-8 Feb | AI7: NO | AK7: UNPLANNED | AL7: UNPLANNED - known LBA, no pre-alert | AM7: APPROVED | AN7: NOT PLANNED | AO7: STOCKED
A8: REC-BKE-2026-0007 | B8: 46070 | C8: 46070 | D8: CREDIT | E8: BOUAKE | F8: BKE-002 | G8: SCOOPS BAY SCOOPS | H8: LBA-014-BAY | I8: 3509KJ01 | J8: 0426-0194 | K8: 72607 | L8: MANKONO | M8: 9.1 | N8: 163 | O8: 47.08 | P8: 47.16 | Q8: ACCEPTED | S8: 39460 | U8: 39018 | V8: =IF(OR(U8="",AA8=""),"",U8-AA8) -> 38998 | W8: 442 | X8: 437 | Y8: 0 | Z8: 5 | AA8: 20 | AB8: 470 | AC8: =IF(OR(V8="",AB8=""),"",V8*AB8) -> 18329060 | AD8: 39018 | AE8: LOT-BKE-2026-0006 | AH8: W-8 Feb | AI8: NO | AK8: UNPLANNED | AL8: UNPLANNED - known LBA, no pre-alert | AM8: APPROVED | AN8: NOT PLANNED | AO8: STOCKED
A9: REC-BKE-2026-0008 | B9: 46070 | C9: 46070 | D9: CREDIT | E9: BOUAKE | F9: BKE-002 | G9: SCOOPS-OUMI/KONE SIDY | H9: LBA-015-OUM | I9: 28JZ01 | J9: 0426-0347 | K9: 72564 | L9: BOUAKE | M9: 9.2 | N9: 172 | O9: 48.04 | P9: 48.4 | Q9: ACCEPTED | S9: 49020 | U9: 48450 | V9: =IF(OR(U9="",AA9=""),"",U9-AA9) -> 48390 | W9: 570 | X9: 555 | Y9: 0 | Z9: 15 | AA9: 60 | AB9: 470 | AC9: =IF(OR(V9="",AB9=""),"",V9*AB9) -> 22743300 | AD9: 48450 | AE9: LOT-BKE-2026-0007 | AH9: W-8 Feb | AI9: YES | AJ9: DP-BKE-2026-008 | AK9: PLANNED WITH EXCEPTION | AL9: WAREHOUSE CHANGE | AM9: APPROVED | AN9: PLANNED FROM START | AO9: STOCKED
A10: REC-BKE-2026-0009 | B10: 46070 | D10: CREDIT | E10: BOUAKE | G10: SCOOP ASER | H10: LBA-011-ASR | I10: AA398TS04 | L10: BOUAKE | M10: 9.3 | N10: 185 | O10: 45.4 | Q10: REJECTED | R10: REJECT | S10: 0 | U10: 0 | V10: 0 | W10: 0 | AB10: 0 | AC10: 0 | AG10: REJECT | AI10: YES | AJ10: DP-BKE-2026-002 | AK10: PLANNED WITH EXCEPTION | AL10: EARLY DELIVERY; ORIGIN MISMATCH | AM10: N/A - REJECTED | AN10: PLANNED FROM START | AO10: REJECTED
A11: REC-BKE-2026-0010 | B11: 46071 | C11: 46071 | D11: CREDIT | E11: BOUAKE | F11: BKE-003 | G11: SCAAMT COOP CA | H11: LBA-002-SCA | I11: AA864JL01 | J11: 0419-0180 | K11: 72517 | L11: VAVOUA | M11: 9.5 | N11: 178 | O11: 46.81 | P11: 47.16 | Q11: ACCEPTED | S11: 52060 | U11: 51446 | V11: =IF(OR(U11="",AA11=""),"",U11-AA11) -> 51302 | W11: 614 | X11: 578 | Y11: 0 | Z11: 36 | AA11: 144 | AB11: 470 | AC11: =IF(OR(V11="",AB11=""),"",V11*AB11) -> 24111940 | AD11: 51446 | AE11: LOT-BKE-2026-0008 | AH11: W-8 Feb | AI11: YES | AJ11: DP-BKE-2026-001 | AK11: PLANNED | AL11: ON PLAN | AM11: NOT REQUIRED | AN11: PLANNED FROM START | AO11: STOCKED
A12: REC-BKE-2026-0011 | B12: 46071 | C12: 46071 | D12: CREDIT | E12: BOUAKE | F12: BKE-003 | G12: SCOOPS WEBE | H12: LBA-004-WEB | I12: 5176LG04 | J12: 0425-0212 | K12: 72568 | L12: DABAKALA | M12: 9.6 | N12: 182 | O12: 48.22 | P12: 48.4 | Q12: ACCEPTED | S12: 41540 | U12: 41087 | V12: =IF(OR(U12="",AA12=""),"",U12-AA12) -> 40915 | W12: 453 | X12: 410 | Y12: 0 | Z12: 43 | AA12: 172 | AB12: 475 | AC12: =IF(OR(V12="",AB12=""),"",V12*AB12) -> 19434625 | AD12: 41087 | AE12: LOT-BKE-2026-0009 | AH12: W-8 Feb | AI12: YES | AJ12: DP-BKE-2026-005 | AK12: PLANNED | AL12: ON PLAN | AM12: NOT REQUIRED | AN12: PLANNED FROM START | AO12: STOCKED
A13: REC-BKE-2026-0012 | B13: 46071 | C13: 46071 | D13: CREDIT | E13: BOUAKE | F13: BKE-002 | G13: CAPCD-SCOOPS | H13: LBA-010-CAP | I13: AA562YL04 | J13: 0431-0277 | K13: 72523 | L13: DIANRA | M13: 11.2 | N13: 168 | O13: 48.04 | Q13: ACCEPTED | S13: 40560 | U13: 40097 | V13: =IF(OR(U13="",AA13=""),"",U13-AA13) -> 40057 | W13: 463 | X13: 453 | Y13: 0 | Z13: 10 | AA13: 40 | AB13: 475 | AC13: =IF(OR(V13="",AB13=""),"",V13*AB13) -> 19027075 | AD13: 40097 | AE13: LOT-BKE-2026-0010 | AH13: W-8 Feb | AI13: YES | AJ13: DP-BKE-2026-006 | AK13: PLANNED WITH EXCEPTION | AL13: ORIGIN MISMATCH | AM13: APPROVED | AN13: PLANNED FROM START | AO13: STOCKED
A14: REC-BKE-2026-0013 | B14: 46071 | C14: 46071 | D14: CREDIT | E14: BOUAKE | F14: BKE-003 | G14: SCOOP ASER | H14: LBA-011-ASR | I14: 2138HC01 | J14: 0426-0340 | K14: 72501 | L14: MANKONO | M14: 8.6 | N14: 171 | O14: 47.6 | P14: 47.87 | Q14: ACCEPTED | S14: 46680 | U14: 46118 | V14: =IF(OR(U14="",AA14=""),"",U14-AA14) -> 45966 | W14: 562 | X14: 524 | Y14: 0 | Z14: 38 | AA14: 152 | AB14: 470 | AC14: =IF(OR(V14="",AB14=""),"",V14*AB14) -> 21604020 | AD14: 46118 | AE14: LOT-BKE-2026-0011 | AH14: W-8 Feb | AI14: YES | AJ14: DP-BKE-2026-002 | AK14: PLANNED WITH EXCEPTION | AL14: WAREHOUSE CHANGE | AM14: APPROVED | AN14: PLANNED FROM START | AO14: STOCKED
A15: REC-BKE-2026-0014 | B15: 46071 | D15: CREDIT | E15: BOUAKE | G15: SCOOPS WEBE | H15: LBA-004-WEB | I15: AA533NN | L15: KORHOGO | M15: 8.1 | N15: 178 | O15: 44.35 | Q15: REJECTED | R15: REJECT | S15: 0 | V15: 0 | W15: 0 | AC15: 0 | AG15: REJECT | AI15: YES | AJ15: DP-BKE-2026-005 | AK15: PLANNED WITH EXCEPTION | AL15: ORIGIN MISMATCH | AM15: N/A - REJECTED | AN15: PLANNED FROM START | AO15: REJECTED
A16: REC-BKE-2026-0015 | B16: 46071 | D16: CREDIT | E16: BOUAKE | G16: SCOPPAS SCOOPS | H16: LBA-009-SCO | I16: 913HB04 | L16: KOUTO | M16: 7.5 | N16: 170 | O16: 44.7 | Q16: REJECTED | R16: REJECT | S16: 0 | V16: 0 | W16: 0 | AC16: 0 | AG16: REJECT | AI16: NO | AK16: UNPLANNED | AL16: UNPLANNED / QUALITY REJECTED | AM16: N/A - REJECTED | AN16: NOT PLANNED | AO16: REJECTED
A17: REC-BKE-2026-0016 | B17: 46072 | C17: 46072 | D17: CREDIT | E17: BOUAKE | F17: BKE-003 | G17: COP JAVA SCOOPS | H17: LBA-005-JAV | I17: 285LA01 | J17: 0429-0005 | K17: 72553 | L17: VAVOUA | M17: 8.2 | N17: 178 | O17: 47.52 | P17: 48.04 | Q17: ACCEPTED | S17: 44040 | U17: 43478 | V17: =IF(OR(U17="",AA17=""),"",U17-AA17) -> 43402 | W17: 562 | X17: 543 | Y17: 0 | Z17: 19 | AA17: 76 | AB17: 475 | AC17: =IF(OR(V17="",AB17=""),"",V17*AB17) -> 20615950 | AD17: 43478 | AE17: LOT-BKE-2026-0012 | AH17: W-8 Feb | AI17: YES | AJ17: DP-BKE-2026-010 | AK17: PLANNED | AL17: ON PLAN | AM17: NOT REQUIRED | AN17: PLANNED FROM START | AO17: STOCKED
A18: REC-BKE-2026-0017 | B18: 46072 | C18: 46072 | D18: CREDIT | E18: BOUAKE | F18: BKE-003 | G18: SCOOPS KPESSO | H18: LBA-012-KPE | I18: AA057ER03 | J18: 0426-0365 | K18: 72549 | L18: DIANRA | M18: 8.7 | N18: 178 | O18: 46.99 | P18: 47.34 | Q18: ACCEPTED | S18: 43860 | U18: 43350 | V18: =IF(OR(U18="",AA18=""),"",U18-AA18) -> 43302 | W18: 510 | X18: 498 | Y18: 0 | Z18: 12 | AA18: 48 | AB18: 470 | AC18: =IF(OR(V18="",AB18=""),"",V18*AB18) -> 20351940 | AD18: 43350 | AE18: LOT-BKE-2026-0013 | AH18: W-8 Feb | AI18: NO | AK18: UNPLANNED | AL18: UNPLANNED - known LBA, no pre-alert | AM18: APPROVED | AN18: NOT PLANNED | AO18: STOCKED
A19: REC-BKE-2026-0018 | B19: 46073 | C19: 46073 | D19: CREDIT | E19: BOUAKE | F19: BKE-002 | G19: SCOOP-CA/COBAN | H19: LBA-008-COB | I19: 2415CV03 | J19: 0420-0149 | K19: 72529 | L19: DIANRA | M19: 8.5 | N19: 167 | O19: 46.64 | P19: 46.72 | Q19: ACCEPTED | S19: 51300 | U19: 50693 | V19: =IF(OR(U19="",AA19=""),"",U19-AA19) -> 50441 | W19: 607 | X19: 544 | Z19: 63 | AA19: 252 | AB19: 480 | AC19: =IF(OR(V19="",AB19=""),"",V19*AB19) -> 24211680 | AD19: 50693 | AE19: LOT-BKE-2026-0014 | AH19: W-8 Feb | AI19: NO | AK19: UNPLANNED | AL19: UNPLANNED - approval required at arrival | AM19: APPROVED | AN19: TO BE LINKED / REGULARIZED | AO19: STOCKED
A20: REC-BKE-2026-0019 | B20: 46073 | D20: CREDIT | E20: BOUAKE | G20: SCOOP-CA/COBAN | H20: LBA-008-COB | I20: 9719FC01 | L20: DIANRA | M20: 9.3 | N20: 165 | O20: 45.23 | Q20: REJECTED | R20: REJECT | S20: 0 | V20: 0 | W20: 0 | AC20: 0 | AG20: REJECT | AI20: NO | AK20: UNPLANNED | AL20: UNPLANNED / QUALITY REJECTED | AM20: N/A - REJECTED | AN20: NOT PLANNED | AO20: REJECTED
A21: REC-BKE-2026-0020 | B21: 46074 | C21: 46074 | D21: CREDIT | E21: BOUAKE | F21: BKE-003 | G21: SCOOPS AH AL NOUR | H21: LBA-016-NOU | I21: 838LX01 | J21: 0425-0055 | K21: 72593 | L21: KATIOLA | M21: 9 | N21: 165 | O21: 48.92 | Q21: ACCEPTED | S21: 46380 | U21: 45843 | V21: =IF(OR(U21="",AA21=""),"",U21-AA21) -> 45759 | W21: 537 | X21: 516 | Y21: 0 | Z21: 21 | AA21: 84 | AB21: 475 | AC21: =IF(OR(V21="",AB21=""),"",V21*AB21) -> 21735525 | AD21: 45843 | AE21: LOT-BKE-2026-0015 | AH21: W-8 Feb | AI21: YES | AJ21: DP-BKE-2026-009 | AK21: PLANNED WITH EXCEPTION | AL21: WAREHOUSE CHANGE | AM21: APPROVED | AN21: PLANNED FROM START | AO21: STOCKED
A22: REC-BKE-2026-0021 | B22: 46074 | C22: 46074 | D22: CREDIT | E22: BOUAKE | F22: BKE-002 | G22: SCOOPS DPVICA | H22: LBA-017-DPV | I22: 32LA01 | J22: 0420-0251 | K22: 68145 | L22: DIANRA | M22: 9.3 | N22: 166 | O22: 46.11 | Q22: ACCEPTED | S22: 40740 | U22: 40220 | V22: =IF(OR(U22="",AA22=""),"",U22-AA22) -> 40112 | W22: 520 | X22: 493 | Y22: 0 | Z22: 27 | AA22: 108 | AB22: 475 | AC22: =IF(OR(V22="",AB22=""),"",V22*AB22) -> 19053200 | AD22: 40220 | AE22: LOT-BKE-2026-0016 | AH22: W-8 Feb | AI22: NO | AK22: UNPLANNED | AL22: UNPLANNED - known LBA, no pre-alert | AM22: APPROVED | AN22: NOT PLANNED | AO22: STOCKED
A23: REC-BKE-2026-0022 | B23: 46075 | D23: CREDIT | E23: BOUAKE | G23: SCOOPS HERE B | H23: LBA-003-HER | I23: 6103GZ03 | L23: DIKODOUGOU | M23: 9.6 | N23: 170 | O23: 45.4 | Q23: REJECTED | R23: REJECT | S23: 0 | V23: 0 | W23: 0 | AC23: 0 | AG23: REJECT | AI23: NO | AK23: UNPLANNED | AL23: UNPLANNED / QUALITY REJECTED | AM23: N/A - REJECTED | AN23: NOT PLANNED | AO23: REJECTED
A24: REC-BKE-2026-0023 | B24: 46076 | D24: CREDIT | E24: BOUAKE | G24: SCOOPS-OUMI/KONE SIDY | H24: LBA-015-OUM | I24: 28JZ01 | L24: MANKONO | M24: 8.2 | N24: 174 | O24: 45.05 | Q24: REJECTED | R24: REJECT | S24: 0 | V24: 0 | W24: 0 | AA24: 0 | AC24: 0 | AG24: REJECT | AI24: NO | AK24: UNPLANNED | AL24: UNPLANNED / QUALITY REJECTED | AM24: N/A - REJECTED | AN24: NOT PLANNED | AO24: REJECTED
A25: REC-BKE-2026-0024 | B25: 46077 | C25: 46077 | D25: CREDIT | E25: BOUAKE | F25: BKE-003 | G25: SCOOPS COOPRAKA | H25: LBA-018-COP | I25: 2766HC01 | J25: 0425-0001 | K25: 72620 | L25: KATIOLA | M25: 9.4 | N25: 174 | O25: 47.87 | Q25: ACCEPTED | S25: 39020 | U25: 38569 | V25: =IF(OR(U25="",AA25=""),"",U25-AA25) -> 38529 | W25: 451 | X25: 441 | Y25: 0 | Z25: 10 | AA25: 40 | AB25: 475 | AC25: =IF(OR(V25="",AB25=""),"",V25*AB25) -> 18301275 | AD25: 38569 | AE25: LOT-BKE-2026-0017 | AH25: W-9 Feb | AI25: YES | AJ25: DP-BKE-2026-003 | AK25: PLANNED | AL25: ON PLAN | AM25: NOT REQUIRED | AN25: PLANNED FROM START | AO25: STOCKED
A26: REC-BKE-2026-0025 | B26: 46077 | D26: CREDIT | E26: BOUAKE | G26: DAGNOGO KARIM | H26: LBA-013-DAG | I26: 9149EL04 | L26: NIAKARA | M26: 11.7 | N26: 161 | O26: 45.05 | Q26: REJECTED | R26: REJECT | S26: 0 | U26: 0 | V26: 0 | W26: 0 | AC26: 0 | AG26: REJECT | AI26: NO | AK26: UNPLANNED | AL26: UNPLANNED / QUALITY REJECTED | AM26: N/A - REJECTED | AN26: NOT PLANNED | AO26: REJECTED
A27: REC-BKE-2026-0026 | B27: 46077 | D27: CREDIT | E27: BOUAKE | G27: SCOOPS AH AL NOUR | H27: LBA-016-NOU | I27: AA518FY01 | L27: KATIOLA | M27: 10.9 | N27: 174 | O27: 44.88 | Q27: REJECTED | R27: REJECT | S27: 0 | U27: 0 | V27: 0 | W27: 0 | AC27: 0 | AG27: REJECT | AI27: NO | AK27: UNPLANNED | AL27: UNPLANNED / QUALITY REJECTED | AM27: N/A - REJECTED | AN27: NOT PLANNED | AO27: REJECTED
A28: REC-BKE-2026-0027 | B28: 46078 | C28: 46078 | D28: CREDIT | E28: BOUAKE | F28: BKE-003 | G28: CASP-S SCOOPS | H28: LBA-007-CAS | I28: 3619 EJ 03 | J28: 0429-0040 | K28: 68659 | L28: BOUNDIALI | M28: 8 | N28: 175 | O28: 46.11 | Q28: ACCEPTED | S28: 51380 | U28: 50744 | V28: =IF(OR(U28="",AA28=""),"",U28-AA28) -> 50624 | W28: 636 | X28: 606 | Y28: 0 | Z28: 30 | AA28: 120 | AB28: 490 | AC28: =IF(OR(V28="",AB28=""),"",V28*AB28) -> 24805760 | AD28: 50744 | AE28: LOT-BKE-2026-0018 | AH28: W-9 Feb | AI28: NO | AK28: UNPLANNED | AL28: UNPLANNED - known LBA, no pre-alert | AM28: APPROVED | AN28: NOT PLANNED | AO28: STOCKED
A29: REC-BKE-2026-0028 | B29: 46079 | D29: CREDIT | E29: BOUAKE | G29: SCOOP IMANE | H29: LBA-006-IMA | I29: 1148CV03 | L29: KANI | M29: 8.3 | N29: 180 | O29: 41 | Q29: REJECTED | R29: REJECT | S29: 0 | V29: 0 | AB29: 0 | AC29: 0 | AG29: REJECT | AI29: NO | AK29: UNPLANNED | AL29: UNPLANNED / QUALITY REJECTED | AM29: N/A - REJECTED | AN29: NOT PLANNED | AO29: REJECTED
A30: REC-BKE-2026-0029 | B30: 46081 | D30: CREDIT | E30: YAKRO FACTORY | G30: SCAAMT COOP CA | H30: LBA-002-SCA | I30: AV2744KK0R | L30: VAVOUA | M30: 7.9 | N30: 183 | O30: 45.23 | Q30: REJECTED | R30: REJECT | S30: 0 | V30: 0 | AC30: 0 | AG30: REJECT | AI30: YES | AJ30: DP-BKE-2026-001 | AK30: PLANNED | AL30: ON PLAN | AM30: N/A - REJECTED | AN30: PLANNED FROM START | AO30: REJECTED
A31: REC-BKE-2026-0030 | B31: 46085 | D31: CREDIT | E31: BOUAKE | G31: SCOOPS BAY SCOOPS | H31: LBA-014-BAY | I31: 2023 HF 01 | L31: BOTRO | M31: 10 | N31: 170 | O31: 44.26 | Q31: REJECTED | R31: REJECT | S31: 0 | V31: 0 | AC31: 0 | AG31: REJECT | AI31: NO | AK31: UNPLANNED | AL31: UNPLANNED / QUALITY REJECTED | AM31: N/A - REJECTED | AN31: NOT PLANNED | AO31: REJECTED
A32: REC-BKE-2026-0031 | B32: 46085 | D32: CREDIT | E32: BOUAKE | G32: CAPCD-SCOOPS | H32: LBA-010-CAP | I32: AA 465 KK 01 | L32: SEGUELA | M32: 7.9 | N32: 178 | O32: 42.06 | Q32: REJECTED | R32: REJECT | S32: 0 | V32: 0 | AC32: 0 | AG32: REJECT | AI32: NO | AK32: UNPLANNED | AL32: UNPLANNED / QUALITY REJECTED | AM32: N/A - REJECTED | AN32: NOT PLANNED | AO32: REJECTED
A33: REC-BKE-2026-0032 | B33: 46086 | C33: 46086 | D33: CREDIT | E33: BOUAKE | F33: BKE-003 | G33: DAGNOGO KARIM | H33: LBA-013-DAG | I33: 374LK01 | J33: 0425-0068 | K33: 77662 | L33: NIAKARA | M33: 9.7 | N33: 160 | O33: 46.02 | Q33: ACCEPTED | S33: 46760 | U33: 46256 | V33: =IF(OR(U33="",AA33=""),"",U33-AA33) -> 46216 | W33: 504 | X33: 494 | Y33: 0 | Z33: 10 | AA33: 40 | AB33: 485 | AC33: =IF(OR(V33="",AB33=""),"",V33*AB33) -> 22414760 | AD33: 46256 | AE33: LOT-BKE-2026-0019 | AH33: W-10 Mar | AI33: NO | AK33: UNPLANNED | AL33: UNPLANNED - known LBA, no pre-alert | AM33: APPROVED | AN33: NOT PLANNED | AO33: STOCKED
A34: REC-BKE-2026-0033 | B34: 46087 | D34: CREDIT | E34: BOUAKE | G34: SCOOPS COOPRAKA | H34: LBA-018-COP | I34: 2766 HC 01 | L34: KATIOLA | M34: 9.6 | N34: 168 | O34: 44.44 | Q34: REJECTED | R34: REJECT | S34: 0 | V34: 0 | AC34: 0 | AG34: REJECT | AI34: YES | AJ34: DP-BKE-2026-003 | AK34: PLANNED | AL34: ON PLAN | AM34: N/A - REJECTED | AN34: PLANNED FROM START | AO34: REJECTED
A35: REC-BKE-2026-0034 | B35: 46088 | C35: 46088 | D35: CREDIT | E35: BOUAKE | F35: BKE-001 | G35: SCOOPS HERE B | H35: LBA-003-HER | I35: 6085HR03 | J35: 0426-0187 | K35: 77633 | L35: NIAKARA | M35: 9.8 | N35: 168 | O35: 46.11 | Q35: ACCEPTED | S35: 46040 | U35: 45492 | V35: =IF(OR(U35="",AA35=""),"",U35-AA35) -> 45460 | W35: 548 | X35: 540 | Y35: 0 | Z35: 8 | AA35: 32 | AB35: 485 | AC35: =IF(OR(V35="",AB35=""),"",V35*AB35) -> 22048100 | AD35: 45492 | AE35: LOT-BKE-2026-0020 | AH35: W-10 Mar | AI35: YES | AJ35: DP-BKE-2026-007 | AK35: PLANNED WITH EXCEPTION | AL35: PLAN CANCELLED - ARRIVAL RECORDED | AM35: APPROVED | AN35: PLANNED FROM START | AO35: STOCKED
A36: REC-BKE-2026-0035 | B36: 46090 | D36: CREDIT | E36: BOUAKE | G36: SCOOPS KPESSO | H36: LBA-012-KPE | I36: AA653PE03 | L36: DIANRA | M36: 9.1 | N36: 170 | O36: 44.35 | Q36: REJECTED | R36: REJECT | S36: 0 | V36: 0 | AC36: 0 | AG36: REJECT | AI36: NO | AK36: UNPLANNED | AL36: UNPLANNED / QUALITY REJECTED | AM36: N/A - REJECTED | AN36: NOT PLANNED | AO36: REJECTED
A37: REC-BKE-2026-0036 | B37: 46092 | C37: 46092 | D37: CREDIT | E37: BOUAKE | F37: BKE-001 | G37: SCOPPAS SCOOPS | H37: LBA-009-SCO | I37: 6690GB01 | J37: 0426-0203 | K37: 75589 | L37: VAVOUA | M37: 9.9 | N37: 185 | O37: 45.23 | Q37: ACCEPTED | S37: 48580 | U37: 47967 | V37: =IF(OR(U37="",AA37=""),"",U37-AA37) -> 47935 | W37: 613 | X37: 605 | Y37: 0 | Z37: 8 | AA37: 32 | AB37: 485 | AC37: =IF(OR(V37="",AB37=""),"",V37*AB37) -> 23248475 | AD37: 47967 | AE37: LOT-BKE-2026-0021 | AH37: W-11 Mar | AI37: NO | AK37: UNPLANNED | AL37: UNPLANNED - known LBA, no pre-alert | AM37: APPROVED | AN37: NOT PLANNED | AO37: STOCKED
A38: REC-BKE-2026-0037 | B38: 46093 | C38: 46093 | D38: CREDIT | E38: BOUAKE | F38: BKE-001 | G38: SCOOP-CA/COBAN | H38: LBA-008-COB | I38: 8573GA01 | J38: 0420-0149 | K38: 72647 | L38: SEGUELA | M38: 7.5 | N38: 166 | O38: 45.4 | Q38: ACCEPTED | S38: 40300 | U38: 39784 | V38: =IF(OR(U38="",AA38=""),"",U38-AA38) -> 39744 | W38: 516 | X38: 506 | Y38: 0 | Z38: 10 | AA38: 40 | AB38: 485 | AC38: =IF(OR(V38="",AB38=""),"",V38*AB38) -> 19275840 | AD38: 39784 | AE38: LOT-BKE-2026-0022 | AH38: W-11 Mar | AI38: NO | AK38: UNPLANNED | AL38: UNPLANNED - known LBA, no pre-alert | AM38: APPROVED | AN38: NOT PLANNED | AO38: STOCKED
A39: REC-BKE-2026-0038 | B39: 46095 | C39: 46095 | D39: CREDIT | E39: BOUAKE | F39: BKE-002 | G39: SCOOPS WEBE | H39: LBA-004-WEB | I39: AA869FY01 | J39: 0425-0212 | K39: 82147 | L39: DABAKALA | M39: 8.6 | N39: 166 | O39: 47.26 | Q39: ACCEPTED | S39: 44880 | U39: 44340 | V39: =IF(OR(U39="",AA39=""),"",U39-AA39) -> 44308 | W39: 540 | X39: 532 | Y39: 0 | Z39: 8 | AA39: 32 | AB39: 495 | AC39: =IF(OR(V39="",AB39=""),"",V39*AB39) -> 21932460 | AD39: 44340 | AE39: LOT-BKE-2026-0023 | AH39: W-11 Mar | AI39: YES | AJ39: DP-BKE-2026-005 | AK39: PLANNED WITH EXCEPTION | AL39: WAREHOUSE CHANGE | AM39: APPROVED | AN39: PLANNED FROM START | AO39: STOCKED
A40: REC-BKE-2026-0039 | B40: 46096 | C40: 46097 | D40: CREDIT | E40: BOUAKE | F40: BKE-001 | G40: SCOOPS HERE B | H40: LBA-003-HER | I40: 8287GH03 | J40: 0426-0187 | K40: 82869 | L40: DABAKALA | M40: 12.2 | N40: 189 | O40: 45.15 | Q40: ACCEPTED | S40: 39880 | U40: 39405 | V40: =IF(OR(U40="",AA40=""),"",U40-AA40) -> 39325 | W40: 475 | X40: 455 | Y40: 0 | Z40: 20 | AA40: 80 | AB40: 485 | AC40: =IF(OR(V40="",AB40=""),"",V40*AB40) -> 19072625 | AD40: 39405 | AE40: LOT-BKE-2026-0024 | AF40: BKE-001-BIN-015 | AH40: W-12 Mar | AI40: NO | AK40: UNPLANNED | AL40: UNPLANNED - known LBA, no pre-alert | AM40: APPROVED | AN40: NOT PLANNED | AO40: STOCKED
A41: REC-BKE-2026-0040 | B41: 46096 | C41: 46097 | D41: CREDIT | E41: BOUAKE | F41: BKE-001 | G41: SCOOPS AH AL NOUR | H41: LBA-016-NOU | I41: 4137LG04 | J41: 0425-0055 | K41: 82143 | L41: KATIOLA | M41: 11 | N41: 164 | O41: 46.03 | Q41: ACCEPTED | S41: 43640 | U41: 43128 | V41: =IF(OR(U41="",AA41=""),"",U41-AA41) -> 43088 | W41: 512 | X41: 502 | Y41: 0 | Z41: 10 | AA41: 40 | AB41: 490 | AC41: =IF(OR(V41="",AB41=""),"",V41*AB41) -> 21113120 | AD41: 43128 | AE41: LOT-BKE-2026-0025 | AF41: BKE-001-BIN-016 | AH41: W-12 Mar | AI41: NO | AK41: UNPLANNED | AL41: UNPLANNED - known LBA, no pre-alert | AM41: APPROVED | AN41: NOT PLANNED | AO41: STOCKED
A42: REC-BKE-2026-0041 | B42: 46098 | C42: 46098 | D42: CREDIT | E42: BOUAKE | F42: BKE-003 | G42: SCOOPS KPESSO | H42: LBA-012-KPE | I42: AA057ER03 | J42: 0426-0365 | K42: 82164 | L42: DIANRA | M42: 9.4 | N42: 162 | O42: 46.03 | Q42: ACCEPTED | S42: 39920 | U42: 39441 | V42: =IF(OR(U42="",AA42=""),"",U42-AA42) -> 39401 | W42: 479 | X42: 469 | Y42: 0 | Z42: 10 | AA42: 40 | AB42: 490 | AC42: =IF(OR(V42="",AB42=""),"",V42*AB42) -> 19306490 | AD42: 39441 | AE42: LOT-BKE-2026-0026 | AH42: W-12 Mar | AI42: NO | AK42: UNPLANNED | AL42: UNPLANNED - approval required at arrival | AM42: APPROVED | AN42: TO BE LINKED / REGULARIZED | AO42: STOCKED
A43: REC-BKE-2026-0042 | B43: 46100 | C43: 46103 | D43: CREDIT | E43: BOUAKE | F43: BKE-001 | G43: SCOOP IMANE | H43: LBA-006-IMA | I43: 616KY03 | J43: 0401-0007 | K43: 82151 | L43: BOTRO | M43: 10.3 | N43: 163 | O43: 44.44 | Q43: ACCEPTED | S43: 40740 | U43: 40276 | V43: =IF(OR(U43="",AA43=""),"",U43-AA43) -> 40236 | W43: 464 | X43: 454 | Y43: 0 | Z43: 10 | AA43: 40 | AB43: 485 | AC43: =IF(OR(V43="",AB43=""),"",V43*AB43) -> 19514460 | AD43: 40276 | AE43: LOT-BKE-2026-0027 | AH43: W-12 Mar | AI43: NO | AK43: UNPLANNED | AL43: UNPLANNED - known LBA, no pre-alert | AM43: APPROVED | AN43: NOT PLANNED | AO43: STOCKED
A44: REC-BKE-2026-0043 | B44: 46102 | C44: 46104 | D44: CREDIT | E44: BOUAKE | F44: BKE-001 | G44: SCOOP ASER | H44: LBA-011-ASR | I44: AA398TS04 | J44: 0426-0340 | K44: 82130 | L44: DUEKOUE | M44: 10.7 | N44: 181 | O44: 46.2 | Q44: ACCEPTED | S44: 55220 | U44: 54542 | V44: =IF(OR(U44="",AA44=""),"",U44-AA44) -> 54478 | W44: 678 | X44: 662 | Y44: 0 | Z44: 16 | AA44: 64 | AB44: 490 | AC44: =IF(OR(V44="",AB44=""),"",V44*AB44) -> 26694220 | AD44: 54542 | AE44: LOT-BKE-2026-0028 | AH44: W-13 Mar | AI44: YES | AJ44: DP-BKE-2026-002 | AK44: PLANNED WITH EXCEPTION | AL44: ORIGIN MISMATCH | AM44: APPROVED | AN44: PLANNED FROM START | AO44: STOCKED
A45: REC-BKE-2026-0044 | B45: 46104 | C45: 46104 | D45: CREDIT | E45: BOUAKE | F45: BKE-003 | G45: SCOOPS BAY SCOOPS | H45: LBA-014-BAY | I45: 2023HF01 | J45: 0426-0194 | K45: 78072 | L45: BOTRO | M45: 10.1 | N45: 163 | O45: 46.56 | Q45: ACCEPTED | S45: 18140 | U45: 17944 | V45: =IF(OR(U45="",AA45=""),"",U45-AA45) -> 17924 | W45: 196 | X45: 191 | Y45: 0 | Z45: 5 | AA45: 20 | AB45: 490 | AC45: =IF(OR(V45="",AB45=""),"",V45*AB45) -> 8782760 | AD45: 17944 | AE45: LOT-BKE-2026-0029 | AH45: W-13 Mar | AI45: NO | AK45: UNPLANNED | AL45: UNPLANNED - known LBA, no pre-alert | AM45: APPROVED | AN45: NOT PLANNED | AO45: STOCKED
A46: REC-BKE-2026-0045 | B46: 46107 | C46: 46107 | D46: CREDIT | E46: YAKRO FACTORY | G46: COP JAVA SCOOPS | H46: LBA-005-JAV | I46: 285LA01 | J46: 0429-0005 | K46: 83406 | L46: VAVOUA | M46: 9.6 | N46: 187 | O46: 44.17 | Q46: ACCEPTED | S46: 46300 | U46: 45728 | V46: =IF(OR(U46="",AA46=""),"",U46-AA46) -> 45692 | W46: 572 | X46: 563 | Y46: 0 | Z46: 9 | AA46: 36 | AB46: 485 | AC46: =IF(OR(V46="",AB46=""),"",V46*AB46) -> 22160620 | AD46: 45728 | AE46: LOT-BKE-2026-0030 | AH46: W-13 Mar | AI46: YES | AJ46: DP-BKE-2026-010 | AK46: PLANNED | AL46: ON PLAN | AM46: NOT REQUIRED | AN46: PLANNED FROM START | AO46: STOCKED
A47: REC-BKE-2026-0046 | B47: 46107 | C47: 46107 | D47: CREDIT | E47: BOUAKE | F47: BKE-001 | G47: SCOOPS-OUMI/KONE SIDY | H47: LBA-015-OUM | I47: 5012HJ01 | J47: 0426-0347 | K47: 88279 | L47: MANKONO | M47: 8.2 | N47: 178 | O47: 44.18 | Q47: ACCEPTED | S47: 45480 | U47: 44935 | V47: =IF(OR(U47="",AA47=""),"",U47-AA47) -> 44899 | W47: 545 | X47: 536 | Y47: 0 | Z47: 9 | AA47: 36 | AB47: 485 | AC47: =IF(OR(V47="",AB47=""),"",V47*AB47) -> 21776015 | AD47: 44935 | AE47: LOT-BKE-2026-0031 | AH47: W-13 Mar | AI47: YES | AJ47: DP-BKE-2026-008 | AK47: PLANNED WITH EXCEPTION | AL47: ORIGIN MISMATCH | AM47: APPROVED | AN47: PLANNED FROM START | AO47: STOCKED
A48: REC-BKE-2026-0047 | B48: 46113 | C48: 46114 | D48: CREDIT | E48: YAKRO FACTORY | G48: SCOOPS DPVICA | H48: LBA-017-DPV | I48: AA562YC04 | J48: 0420-0251 | K48: 82173 | L48: DIANRA | M48: 8.5 | N48: 168 | O48: 42.24 | Q48: ACCEPTED | S48: 40440 | U48: 39950 | V48: =IF(OR(U48="",AA48=""),"",U48-AA48) -> 39870 | W48: 490 | X48: 470 | Y48: 0 | Z48: 20 | AA48: 80 | AB48: 480 | AC48: =IF(OR(V48="",AB48=""),"",V48*AB48) -> 19137600 | AD48: 39950 | AE48: LOT-BKE-2026-0032 | AH48: W-14 Mar | AI48: NO | AK48: UNPLANNED | AL48: UNPLANNED - known LBA, no pre-alert | AM48: APPROVED | AN48: NOT PLANNED | AO48: STOCKED
A49: REC-BKE-2026-0048 | B49: 46118 | C49: 46119 | D49: CREDIT | E49: BOUAKE | F49: BKE-002 | G49: CAPCD-SCOOPS | H49: LBA-010-CAP | I49: AA343VP04 | J49: 0431-0277 | K49: 80522 | L49: BOUAKE | M49: 11.7 | N49: 160 | O49: 41.79 | Q49: ACCEPTED | S49: 12240 | U49: 12091 | V49: =IF(OR(U49="",AA49=""),"",U49-AA49) -> 12015 | W49: 149 | X49: 130 | Y49: 0 | Z49: 19 | AA49: 76 | AB49: 485 | AC49: =IF(OR(V49="",AB49=""),"",V49*AB49) -> 5827275 | AD49: 12091 | AE49: LOT-BKE-2026-0033 | AH49: W-15 Mar | AI49: YES | AJ49: DP-BKE-2026-006 | AK49: PLANNED | AL49: ON PLAN | AM49: NOT REQUIRED | AN49: PLANNED FROM START | AO49: STOCKED
A50: REC-BKE-2026-0049 | B50: 46120 | E50: BOUAKE | G50: SCOOPS DPVICA | H50: LBA-017-DPV | I50: AA562YL04/354LH01 | L50: DIANRA | M50: 12.4 | N50: 160 | O50: 40.5651 | Q50: REJECTED | R50: REJECT | S50: 0 | V50: 0 | AC50: 0 | AG50: REJECT | AI50: NO | AK50: UNPLANNED | AL50: UNPLANNED / QUALITY REJECTED | AM50: N/A - REJECTED | AN50: NOT PLANNED | AO50: REJECTED
A51: REC-BKE-2026-0050 | B51: 46122 | C51: 46122 | D51: CREDIT | E51: YAKRO FACTORY | G51: SCAAMT COOP CA | H51: LBA-002-SCA | I51: AA721PZ01 | J51: 0419-0180 | K51: 78912 | L51: VAVOUA | M51: 10.8 | N51: 189 | O51: 44.26 | Q51: ACCEPTED | S51: 51020 | U51: 50362 | V51: =IF(OR(U51="",AA51=""),"",U51-AA51) -> 50178 | W51: 658 | X51: 612 | Y51: 0 | Z51: 46 | AA51: 184 | AB51: 515 | AC51: =IF(OR(V51="",AB51=""),"",V51*AB51) -> 25841670 | AD51: 50362 | AE51: LOT-BKE-2026-0034 | AH51: W-15 Mar | AI51: YES | AJ51: DP-BKE-2026-001 | AK51: PLANNED | AL51: ON PLAN | AM51: NOT REQUIRED | AN51: PLANNED FROM START | AO51: STOCKED
A52: REC-BKE-2026-0051 | B52: 46122 | C52: 46122 | D52: CREDIT | E52: YAKRO FACTORY | G52: SANOGO SINDOU | H52: LBA-021-SAN | I52: 8454CF04 | K52: 37970 | L52: MANKONO | M52: 13.7 | N52: 166 | O52: 43.38 | Q52: ACCEPTED | S52: 42110 | U52: 41622 | V52: =IF(OR(U52="",AA52=""),"",U52-AA52) -> 41526 | W52: 488 | X52: 464 | Y52: 0 | Z52: 24 | AA52: 96 | AB52: 500 | AC52: =IF(OR(V52="",AB52=""),"",V52*AB52) -> 20763000 | AD52: 41622 | AE52: LOT-BKE-2026-0035 | AG52: SCOOP BENKADY_CDAG | AH52: W-15 Mar | AI52: YES | AJ52: DP-BKE-2026-004 | AK52: PLANNED | AL52: ON PLAN | AM52: NOT REQUIRED | AN52: PLANNED FROM START | AO52: STOCKED
A53: REC-BKE-2026-0052 | B53: 46122 | C53: 46123 | D53: CREDIT | E53: BOUAKE | F53: BKE-001 | G53: SCOOPS AH AL NOUR | H53: LBA-016-NOU | I53: 953LU01 | J53: 0425-0055 | K53: 18448 | L53: NIAKARA | M53: 12.1 | N53: 159 | O53: 41.53 | Q53: ACCEPTED | S53: 41680 | U53: 41234 | V53: =IF(OR(U53="",AA53=""),"",U53-AA53) -> 41082 | W53: 446 | X53: 427 | Y53: 19 | Z53: 0 | AA53: 152 | AB53: 490 | AC53: =IF(OR(V53="",AB53=""),"",V53*AB53) -> 20130180 | AD53: 41234 | AE53: LOT-BKE-2026-0036 | AH53: W-15 Mar | AI53: YES | AJ53: DP-BKE-2026-009 | AK53: PLANNED WITH EXCEPTION | AL53: ORIGIN MISMATCH | AM53: APPROVED | AN53: PLANNED FROM START | AO53: STOCKED
A54: REC-BKE-2026-0053 | B54: 46127 | E54: YAKRO FACTORY | G54: SANOGO SINDOU | H54: LBA-021-SAN | I54: 6238JL01/4363HU01 | L54: BOUAKE | M54: 13.2 | N54: 161 | O54: 40.03 | Q54: REJECTED | R54: REJECT | S54: 0 | V54: 0 | AC54: 0 | AG54: REJECT | AI54: YES | AJ54: DP-BKE-2026-004 | AK54: PLANNED WITH EXCEPTION | AL54: ORIGIN MISMATCH | AM54: N/A - REJECTED | AN54: PLANNED FROM START | AO54: REJECTED
A55: REC-BKE-2026-0054 | B55: 46128 | C55: 46128 | D55: CREDIT | E55: BOUAKE | F55: BKE-002 | G55: SCOOPS COOPRAKA | H55: LBA-018-COP | I55: 4669CP03 | J55: 0425-0001 | K55: 19865 | L55: KATIOLA | M55: 9.4 | N55: 160 | O55: 42.32 | Q55: ACCEPTED | S55: 39680 | U55: 39212 | V55: =IF(OR(U55="",AA55=""),"",U55-AA55) -> 39144 | W55: 468 | X55: 451 | Y55: 0 | Z55: 17 | AA55: 68 | AB55: 510 | AC55: =IF(OR(V55="",AB55=""),"",V55*AB55) -> 19963440 | AD55: 39212 | AE55: LOT-BKE-2026-0037 | AH55: W-16 Mar | AI55: YES | AJ55: DP-BKE-2026-003 | AK55: PLANNED WITH EXCEPTION | AL55: WAREHOUSE CHANGE | AM55: APPROVED | AN55: PLANNED FROM START | AO55: STOCKED
A56: REC-BKE-2026-0055 | B56: 46130 | C56: 46131 | D56: CREDIT | E56: BOUAKE | F56: BKE-002 | G56: CAPCD-SCOOPS | H56: LBA-010-CAP | I56: 6305EP01 | J56: 0431-0277 | K56: 87092 | L56: KOUASSI | M56: 9.7 | N56: 160 | O56: 41.27 | Q56: ACCEPTED | S56: 25360 | U56: 25013 | V56: =IF(OR(U56="",AA56=""),"",U56-AA56) -> 24969 | W56: 347 | X56: 336 | Y56: 0 | Z56: 11 | AA56: 44 | AB56: 500 | AC56: =IF(OR(V56="",AB56=""),"",V56*AB56) -> 12484500 | AD56: 25013 | AE56: LOT-BKE-2026-0038 | AF56: BKE-002-BIN-031 | AH56: W-17 Mar | AI56: NO | AK56: UNPLANNED | AL56: UNPLANNED - known LBA, no pre-alert | AM56: APPROVED | AN56: NOT PLANNED | AO56: STOCKED
A57: REC-BKE-2026-0056 | B57: 46133 | E57: YAKRO FACTORY | G57: COP JAVA SCOOPS | H57: LBA-005-JAV | I57: 8229FV02/9908BG01 | L57: VAVOUA | M57: 12.7 | N57: 184 | O57: 39.85 | Q57: REJECTED | R57: REJECT | S57: 0 | V57: 0 | AC57: 0 | AG57: REJECT | AI57: NO | AK57: UNPLANNED | AL57: UNPLANNED / QUALITY REJECTED | AM57: N/A - REJECTED | AN57: NOT PLANNED | AO57: REJECTED
A58: REC-BKE-2026-0057 | B58: 46133 | C58: 46134 | D58: CREDIT | E58: BOUAKE | F58: BKE-002 | G58: SCOOP-CA/COBAN | H58: LBA-008-COB | I58: 4852HV03 | J58: 0420-0149 | K58: 67796 | L58: DIANRA | M58: 9.2 | N58: 159 | O58: 41.44 | Q58: ACCEPTED | S58: 41660 | U58: 41196 | V58: =IF(OR(U58="",AA58=""),"",U58-AA58) -> 41144 | W58: 464 | X58: 451 | Y58: 0 | Z58: 13 | AA58: 52 | AB58: 500 | AC58: =IF(OR(V58="",AB58=""),"",V58*AB58) -> 20572000 | AD58: 41196 | AE58: LOT-BKE-2026-0039 | AH58: W-17 Mar | AI58: NO | AK58: UNPLANNED | AL58: UNPLANNED - known LBA, no pre-alert | AM58: APPROVED | AN58: NOT PLANNED | AO58: STOCKED
A59: REC-BKE-2026-0058 | B59: 46134 | C59: 46134 | D59: CREDIT | E59: BOUAKE | F59: BKE-002 | G59: SCOOPS COOPRAKA | H59: LBA-018-COP | I59: AA245YN03 | J59: 0425-0001 | K59: 19859 | L59: KORHOGO | M59: 9.1 | N59: 168 | O59: 41.09 | Q59: ACCEPTED | S59: 39560 | U59: 39099 | V59: =IF(OR(U59="",AA59=""),"",U59-AA59) -> 39051 | W59: 461 | X59: 449 | Y59: 0 | Z59: 12 | AA59: 48 | AB59: 500 | AC59: =IF(OR(V59="",AB59=""),"",V59*AB59) -> 19525500 | AD59: 39099 | AE59: LOT-BKE-2026-0040 | AF59: BKE-002-BIN-031 | AH59: W-17 Mar | AI59: NO | AK59: UNPLANNED | AL59: UNPLANNED - known LBA, no pre-alert | AM59: APPROVED | AN59: NOT PLANNED | AO59: STOCKED
A60: REC-BKE-2026-0059 | B60: 46134 | C60: 46135 | D60: CREDIT | E60: BOUAKE | F60: BKE-001 | G60: CASP-S SCOOPS | H60: LBA-007-CAS | I60: AA231VP04 | J60: 0429-0040 | K60: 38397 | L60: MANKONO | M60: 11.9 | N60: 166 | O60: 41.09 | Q60: ACCEPTED | S60: 41220 | U60: 40749 | V60: =IF(OR(U60="",AA60=""),"",U60-AA60) -> 40549 | W60: 471 | X60: 446 | Y60: 25 | Z60: 0 | AA60: 200 | AB60: 490 | AC60: =IF(OR(V60="",AB60=""),"",V60*AB60) -> 19869010 | AD60: 40749 | AE60: LOT-BKE-2026-0041 | AH60: W-17 Mar | AI60: NO | AK60: UNPLANNED | AL60: UNPLANNED - known LBA, no pre-alert | AM60: APPROVED | AN60: NOT PLANNED | AO60: STOCKED
A61: REC-BKE-2026-0060 | B61: 46135 | C61: 46136 | D61: CREDIT | E61: BOUAKE | F61: BKE-001 | G61: SCOPPAS SCOOPS | H61: LBA-009-SCO | I61: 2563GY01 | J61: 0426-0203 | K61: 31708 | L61: DABAKALA | M61: 11.7 | N61: 184 | O61: 41.79 | Q61: ACCEPTED | S61: 40400 | U61: 39890 | V61: =IF(OR(U61="",AA61=""),"",U61-AA61) -> 39730 | W61: 510 | X61: 490 | Y61: 20 | Z61: 0 | AA61: 160 | AB61: 485 | AC61: =IF(OR(V61="",AB61=""),"",V61*AB61) -> 19269050 | AD61: 39890 | AE61: LOT-BKE-2026-0042 | AI61: NO | AK61: UNPLANNED | AL61: UNPLANNED - approval required at arrival | AM61: APPROVED | AN61: TO BE LINKED / REGULARIZED | AO61: STOCKED
A62: REC-BKE-2026-0061 | B62: 46136 | C62: 46137 | D62: CREDIT | E62: BOUAKE | F62: BKE-001 | G62: DAGNOGO KARIM | H62: LBA-013-DAG | I62: 7242JS01 | J62: 0425-0068 | K62: 18679 | L62: NIAKARA | M62: 11 | N62: 160 | O62: 44.09 | Q62: ACCEPTED | S62: 46840 | U62: 46305 | V62: =IF(OR(U62="",AA62=""),"",U62-AA62) -> 46145 | W62: 535 | X62: 515 | Y62: 20 | Z62: 0 | AA62: 160 | AB62: 510 | AC62: =IF(OR(V62="",AB62=""),"",V62*AB62) -> 23533950 | AD62: 46305 | AE62: LOT-BKE-2026-0043 | AI62: NO | AK62: UNPLANNED | AL62: UNPLANNED - known LBA, no pre-alert | AM62: APPROVED | AN62: NOT PLANNED | AO62: STOCKED
A63: REC-BKE-2026-0062 | B63: 46136 | C63: 46137 | D63: CREDIT | E63: YAKRO FACTORY | G63: SANOGO SINDOU | H63: LBA-021-SAN | I63: 9970HE07 | K63: 32358 | L63: BROBO | M63: 14.2 | N63: 160 | O63: 42.76 | Q63: ACCEPTED | S63: 46090 | U63: 45557 | V63: =IF(OR(U63="",AA63=""),"",U63-AA63) -> 45317 | W63: 533 | X63: 503 | Y63: 30 | Z63: 0 | AA63: 240 | AB63: 515 | AC63: =IF(OR(V63="",AB63=""),"",V63*AB63) -> 23338255 | AD63: 45557 | AE63: LOT-BKE-2026-0044 | AG63: SCOOPS PS | AI63: YES | AJ63: DP-BKE-2026-004 | AK63: PLANNED WITH EXCEPTION | AL63: ORIGIN MISMATCH | AM63: APPROVED | AN63: PLANNED FROM START | AO63: STOCKED
A64: REC-BKE-2026-0063 | B64: 46144 | C64: 46144 | D64: CREDIT | E64: BOUAKE | F64: BKE-001 | G64: SCOOPS HERE B | H64: LBA-003-HER | I64: 9900KU03 | J64: 0426-0187 | K64: 18615 | L64: NIAKARA | M64: 11.4 | N64: 169 | O64: 40.38 | Q64: ACCEPTED | S64: 45740 | U64: 45194 | V64: =IF(OR(U64="",AA64=""),"",U64-AA64) -> 44914 | W64: 546 | X64: 511 | Y64: 35 | Z64: 0 | AA64: 280 | AB64: 460 | AC64: =IF(OR(V64="",AB64=""),"",V64*AB64) -> 20660440 | AD64: 45194 | AE64: LOT-BKE-2026-0045 | AI64: YES | AJ64: DP-BKE-2026-007 | AK64: PLANNED WITH EXCEPTION | AL64: PLAN CANCELLED - ARRIVAL RECORDED | AM64: APPROVED | AN64: PLANNED FROM START | AO64: STOCKED
A65: REC-BKE-2026-0064 | B65: 46144 | C65: 46145 | D65: CREDIT | E65: YAKRO FACTORY | G65: COP JAVA SCOOPS | H65: LBA-005-JAV | I65: 2596FZ03 | J65: 0429-0005 | K65: 87106 | L65: VAVOUA | M65: 10.6 | N65: 176 | O65: 42.59 | Q65: ACCEPTED | S65: 53020 | U65: 52377 | V65: =IF(OR(U65="",AA65=""),"",U65-AA65) -> 52217 | W65: 643 | X65: 623 | Y65: 20 | Z65: 0 | AA65: 160 | AB65: 475 | AC65: =IF(OR(V65="",AB65=""),"",V65*AB65) -> 24803075 | AD65: 52377 | AE65: LOT-BKE-2026-0046 | AI65: YES | AJ65: DP-BKE-2026-010 | AK65: PLANNED | AL65: ON PLAN | AM65: NOT REQUIRED | AN65: PLANNED FROM START | AO65: STOCKED
A66: REC-BKE-2026-0065 | B66: 46144 | C66: 46147 | D66: CREDIT | E66: YAKRO FACTORY | G66: SCOOPS DPVICA | H66: LBA-017-DPV | I66: AA141VT01 | J66: 0420-0251 | K66: 37590 | L66: DIANRA | M66: 12.7 | N66: 162 | O66: 42.85 | Q66: ACCEPTED | S66: 45610 | U66: 45125 | V66: =IF(OR(U66="",AA66=""),"",U66-AA66) -> 44805 | W66: 485 | X66: 445 | Y66: 40 | Z66: 0 | AA66: 320 | AB66: 465 | AC66: =IF(OR(V66="",AB66=""),"",V66*AB66) -> 20834325 | AD66: 45125 | AE66: LOT-BKE-2026-0047 | AI66: NO | AK66: UNPLANNED | AL66: UNPLANNED - known LBA, no pre-alert | AM66: APPROVED | AN66: NOT PLANNED | AO66: STOCKED
A67: REC-BKE-2026-0066 | B67: 46145 | C67: 46146 | D67: CREDIT | E67: BOUAKE | F67: BKE-001 | G67: CAPCD-SCOOPS | H67: LBA-010-CAP | I67: 9640GEE04 | J67: 0431-0277 | K67: 87046 | L67: BOUAKE | M67: 9.3 | N67: 158 | O67: 42.32 | Q67: ACCEPTED | S67: 40900 | U67: 40418 | V67: =IF(OR(U67="",AA67=""),"",U67-AA67) -> 40366 | W67: 482 | X67: 469 | Y67: 0 | Z67: 13 | AA67: 52 | AB67: 465 | AC67: =IF(OR(V67="",AB67=""),"",V67*AB67) -> 18770190 | AD67: 40418 | AE67: LOT-BKE-2026-0048 | AI67: YES | AJ67: DP-BKE-2026-006 | AK67: PLANNED WITH EXCEPTION | AL67: WAREHOUSE CHANGE; PLAN EXCESS | AM67: APPROVED | AN67: PLANNED FROM START | AO67: STOCKED
A68: REC-BKE-2026-0067 | B68: 46145 | C68: 46146 | D68: CREDIT | E68: BOUAKE | F68: BKE-001 | G68: SCOOPS KPESSO | H68: LBA-012-KPE | I68: 2318JK01 | J68: 0426-0365 | K68: 32757 | L68: BOTRO | M68: 9.8 | N68: 158 | O68: 41.62 | Q68: ACCEPTED | S68: 41020 | U68: 40532 | V68: =IF(OR(U68="",AA68=""),"",U68-AA68) -> 40484 | W68: 488 | X68: 476 | Y68: 0 | Z68: 12 | AA68: 48 | AB68: 460 | AC68: =IF(OR(V68="",AB68=""),"",V68*AB68) -> 18622640 | AD68: 40532 | AE68: LOT-BKE-2026-0049 | AI68: NO | AK68: UNPLANNED | AL68: UNPLANNED - known LBA, no pre-alert | AM68: APPROVED | AN68: NOT PLANNED | AO68: STOCKED
A69: REC-BKE-2026-0068 | B69: 46146 | C69: 46146 | D69: CREDIT | E69: BOUAKE | F69: BKE-001 | G69: SCOOPS BAY SCOOPS | H69: LBA-014-BAY | I69: 2023HF01 | J69: 0426-0194 | K69: 32834 | L69: BEOUMI | M69: 10.4 | N69: 157 | O69: 42.32 | Q69: ACCEPTED | S69: 13180 | U69: 13025 | V69: =IF(OR(U69="",AA69=""),"",U69-AA69) -> 12993 | W69: 155 | X69: 147 | Y69: 0 | Z69: 8 | AA69: 32 | AB69: 470 | AC69: =IF(OR(V69="",AB69=""),"",V69*AB69) -> 6106710 | AD69: 13025 | AE69: LOT-BKE-2026-0050 | AI69: NO | AK69: UNPLANNED | AL69: UNPLANNED - known LBA, no pre-alert | AM69: APPROVED | AN69: NOT PLANNED | AO69: STOCKED
A70: REC-BKE-2026-0069 | B70: 46146 | C70: 46146 | D70: CREDIT | E70: BOUAKE | F70: BKE-001 | G70: SCOOPS COOPRAKA | H70: LBA-018-COP | I70: 2766HC01 | J70: 0425-0001 | K70: 18794 | L70: KATIOLA | M70: 8 | N70: 167 | O70: 42.32 | Q70: ACCEPTED | S70: 38800 | U70: 38325 | V70: =IF(OR(U70="",AA70=""),"",U70-AA70) -> 38277 | W70: 475 | X70: 463 | Y70: 0 | Z70: 12 | AA70: 48 | AB70: 470 | AC70: =IF(OR(V70="",AB70=""),"",V70*AB70) -> 17990190 | AD70: 38325 | AE70: LOT-BKE-2026-0051 | AI70: YES | AJ70: DP-BKE-2026-003 | AK70: PLANNED WITH EXCEPTION | AL70: LATE DELIVERY; WAREHOUSE CHANGE | AM70: APPROVED | AN70: PLANNED FROM START | AO70: STOCKED
A71: REC-BKE-2026-0070 | B71: 46146 | C71: 46147 | D71: CREDIT | E71: BOUAKE | F71: BKE-001 | G71: SCOOP ASER | H71: LBA-011-ASR | I71: A044CA | J71: 0426-0340 | K71: 32069 | L71: BOUNDIALI | M71: 10.6 | N71: 173 | O71: 41.97 | Q71: ACCEPTED | S71: 48960 | U71: 48376 | V71: =IF(OR(U71="",AA71=""),"",U71-AA71) -> 48316 | W71: 584 | X71: 569 | Y71: 0 | Z71: 15 | AA71: 60 | AB71: 470 | AC71: =IF(OR(V71="",AB71=""),"",V71*AB71) -> 22708520 | AD71: 48376 | AE71: LOT-BKE-2026-0052 | AI71: YES | AJ71: DP-BKE-2026-002 | AK71: PLANNED WITH EXCEPTION | AL71: ORIGIN MISMATCH | AM71: APPROVED | AN71: PLANNED FROM START | AO71: STOCKED
A72: REC-BKE-2026-0071 | B72: 46146 | C72: 46147 | D72: CREDIT | E72: BOUAKE | F72: BKE-001 | G72: SCOOPS AH AL NOUR | H72: LBA-016-NOU | I72: 953LU01 | J72: 0425-0055 | K72: 18783 | L72: KATIOLA | M72: 9.6 | N72: 162 | O72: 41.79 | Q72: ACCEPTED | S72: 41820 | U72: 41335 | V72: =IF(OR(U72="",AA72=""),"",U72-AA72) -> 41295 | W72: 485 | X72: 475 | Y72: 0 | Z72: 10 | AA72: 40 | AB72: 465 | AC72: =IF(OR(V72="",AB72=""),"",V72*AB72) -> 19202175 | AD72: 41335 | AE72: LOT-BKE-2026-0053 | AI72: YES | AJ72: DP-BKE-2026-009 | AK72: PLANNED | AL72: ON PLAN | AM72: NOT REQUIRED | AN72: PLANNED FROM START | AO72: STOCKED
A73: REC-BKE-2026-0072 | B73: 46146 | C73: 46147 | D73: CREDIT | E73: BOUAKE | F73: BKE-001 | G73: SCOOPS-OUMI/KONE SIDY | H73: LBA-015-OUM | I73: 9611CV03 | J73: 0426-0347 | K73: 31994 | L73: KORHOGO | M73: 11 | N73: 181 | O73: 42.15 | Q73: ACCEPTED | S73: 49100 | U73: 48513 | V73: =IF(OR(U73="",AA73=""),"",U73-AA73) -> 48353 | W73: 587 | X73: 567 | Y73: 20 | Z73: 0 | AA73: 160 | AB73: 465 | AC73: =IF(OR(V73="",AB73=""),"",V73*AB73) -> 22484145 | AD73: 48513 | AE73: LOT-BKE-2026-0054 | AF73: BKE-001-BIN-023 | AI73: YES | AJ73: DP-BKE-2026-008 | AK73: PLANNED WITH EXCEPTION | AL73: ORIGIN MISMATCH | AM73: APPROVED | AN73: PLANNED FROM START | AO73: STOCKED
A74: REC-BKE-2026-0073 | B74: 46146 | C74: 46147 | D74: CREDIT | E74: BOUAKE | F74: BKE-001 | G74: SCOOP IMANE | H74: LBA-006-IMA | I74: 5012HJ01 | J74: 0401-0007 | K74: 13117 | L74: BOUAKE | M74: 8 | N74: 177 | O74: 41.62 | Q74: ACCEPTED | S74: 45540 | U74: 44964 | V74: =IF(OR(U74="",AA74=""),"",U74-AA74) -> 44932 | W74: 576 | X74: 568 | Y74: 0 | Z74: 8 | AA74: 32 | AB74: 460 | AC74: =IF(OR(V74="",AB74=""),"",V74*AB74) -> 20668720 | AD74: 44964 | AE74: LOT-BKE-2026-0055 | AI74: NO | AK74: UNPLANNED | AL74: UNPLANNED - known LBA, no pre-alert | AM74: APPROVED | AN74: NOT PLANNED | AO74: STOCKED
A75: REC-BKE-2026-0074 | B75: 46146 | C75: 46147 | D75: CREDIT | E75: YAKRO FACTORY | G75: SCOOPS WEBE | H75: LBA-004-WEB | I75: 4981JR04 | J75: 0425-0212 | K75: 18946 | L75: DABAKALA | M75: 12.6 | N75: 173 | O75: 43.91 | Q75: ACCEPTED | S75: 41510 | U75: 41007 | V75: =IF(OR(U75="",AA75=""),"",U75-AA75) -> 40567 | W75: 503 | X75: 448 | Y75: 55 | Z75: 0 | AA75: 440 | AB75: 465 | AC75: =IF(OR(V75="",AB75=""),"",V75*AB75) -> 18863655 | AD75: 41007 | AE75: LOT-BKE-2026-0056 | AI75: YES | AJ75: DP-BKE-2026-005 | AK75: PLANNED | AL75: ON PLAN | AM75: NOT REQUIRED | AN75: PLANNED FROM START | AO75: STOCKED
A76: REC-BKE-2026-0075 | B76: 46146 | C76: 46150 | D76: CREDIT | E76: YAKRO FACTORY | G76: SANOGO SINDOU | H76: LBA-021-SAN | I76: 8188KU03 | K76: 89077 | L76: SAMATIGUILA | M76: 8.5 | N76: 183 | O76: 43.65 | Q76: ACCEPTED | S76: 47800 | U76: 47210 | V76: =IF(OR(U76="",AA76=""),"",U76-AA76) -> 47170 | W76: 590 | X76: 580 | Y76: 0 | Z76: 10 | AA76: 40 | AB76: 495 | AC76: =IF(OR(V76="",AB76=""),"",V76*AB76) -> 23349150 | AD76: 47210 | AE76: LOT-BKE-2026-0057 | AG76: KONE ADAMA | AI76: YES | AJ76: DP-BKE-2026-004 | AK76: PLANNED WITH EXCEPTION | AL76: ORIGIN MISMATCH | AM76: APPROVED | AN76: PLANNED FROM START | AO76: STOCKED
A77: REC-BKE-2026-0076 | B77: 46149 | C77: 46150 | D77: CREDIT | E77: YAKRO FACTORY | G77: SCAAMT COOP CA | H77: LBA-002-SCA | I77: 5116HF01 | J77: 0429-0180 | K77: 78898 | L77: VAVOUA | M77: 9.8 | N77: 180 | O77: 42.15 | Q77: ACCEPTED | S77: 41140 | U77: 40616 | V77: =IF(OR(U77="",AA77=""),"",U77-AA77) -> 40560 | W77: 524 | X77: 514 | Y77: 0 | Z77: 14 | AA77: 56 | AB77: 454 | AC77: =IF(OR(V77="",AB77=""),"",V77*AB77) -> 18414240 | AD77: 40616 | AE77: LOT-BKE-2026-0058 | AI77: YES | AJ77: DP-BKE-2026-001 | AK77: PLANNED | AL77: ON PLAN | AM77: NOT REQUIRED | AN77: PLANNED FROM START | AO77: STOCKED

Sheet Warehouse Receiving
A1: Row ID | B1: No | C1: Warehouse | D1: Unloading Bin | E1: After Drying Bin | F1: Lot No | G1: Scale Location | H1: Warehouse Receipt No | I1: Fiche CCA No | J1: Truck No | K1: Arrival Date | L1: Arrival Date (as written) | M1: Discharge Date | N1: Discharge Date (as written) | O1: Origin | P1: Supplier Name | Q1: Supplier Code | R1: Good Bags | S1: Humid Bags | T1: Torn Bags | U1: Recondition Bags | V1: Total Bags in Lot | W1: Export Bags | X1: Bio Bags | Y1: Brousse Bags | Z1: Total Bags Received | AA1: Gross Weight Received (kg) | AB1: Total Refraction (kg) | AC1: GRN Quantity (kg) | AD1: Paid Weight (kg) | AE1: Net Weight (kg) | AF1: GRN Fresh Quantity (kg) | AG1: GRN Dried Quantity (kg) | AH1: Sample – Rejection (g) | AI1: Sample – Void (g) | AJ1: Sample – Oil (g) | AK1: Sample – Total Defect (g) | AL1: Sample – Good Kernel (g) | AM1: Sample – Immature (g) | AN1: Sample – Spotted (g) | AO1: Sample – Total Kernels (g) | AP1: Sample – KOR | AQ1: Sample – Shot | AR1: Sample – FOT | AS1: Sample – Useful Kernels Yield (%) | AT1: Sample – Total Yield (%) | AU1: Sample – Moisture (%) | AV1: Sample – Nut Count | AW1: Sample – Shell (g) | AX1: Final – Rejection (g) | AY1: Final – Void (g) | AZ1: Final – Oil (g) | BA1: Final – Total Defect (g) | BB1: Final – Good Kernel (g) | BC1: Final – Immature (g) | BD1: Final – Spotted (g) | BE1: Final – Total Kernels (g) | BF1: Final – KOR | BG1: Final – Shot | BH1: Final – FOT | BI1: Final – Useful Kernels Yield (%) | BJ1: Final – Total Yield (%) | BK1: Final – Moisture (%) | BL1: Final – Nut Count | BM1: Final – Shell (g)
A2: RCV-BKE-2026-0001 | B2: 1 | C2: BKE-002 | F2: LOT-BKE-2026-0001 | G2: INSIDE | H2: 801 | I2: 72515 | J2: 827KT01 | K2: 46069 | L2: 16-Feb | M2: 46069 | N2: 16-Feb | O2: DIANRA | P2: SCOOP IMANE | Q2: LBA-006-IMA | R2: 463 | S2: 0 | T2: 15 | V2: 478 | Z2: =SUM(R2:U2) -> 478 | AA2: 41300 | AB2: 60 | AC2: 40822 | AD2: =IF(OR(AE2="",AB2=""),"",AE2-AB2) -> 40762 | AE2: 40822 | AF2: 40822 | AK2: =IF(COUNTA(AH2:AJ2)=0,"",SUM(AH2:AJ2)) | AO2: =IF(COUNTA(AL2:AN2)=0,"",SUM(AL2:AN2)) | AP2: =IF(COUNTA(AL2:AN2)<3,"",(AL2+0.5*(AM2+AN2))*0.17637) | AQ2: =IF(AO2="","",AO2*0.17637) | AR2: =IF(COUNTA(AJ2,AH2,AL2:AN2)=0,"",(AJ2+AH2+AL2+AM2+AN2)*0.17637) | AS2: =IF(AO2="","",AO2/1000) | AT2: =IF(COUNTA(AH2,AJ2,AL2:AN2)=0,"",SUM(AH2,AJ2,AL2:AN2)/1000) | AU2: 10.2 | AV2: 172 | BA2: =IF(COUNTA(AX2:AZ2)=0,"",SUM(AX2:AZ2)) | BE2: =IF(COUNTA(BB2:BD2)=0,"",SUM(BB2:BD2)) | BF2: =IF(COUNTA(BB2:BD2)<3,"",(BB2+0.5*(BC2+BD2))*0.17637) | BG2: =IF(BE2="","",BE2*0.17637) | BH2: =IF(COUNTA(AZ2,AX2,BB2:BD2)=0,"",(AZ2+AX2+BB2+BC2+BD2)*0.17637) | BI2: =IF(BE2="","",BE2/1000) | BJ2: =IF(COUNTA(AX2,AZ2,BB2:BD2)=0,"",SUM(AX2,AZ2,BB2:BD2)/1000) | BK2: 10.2 | BL2: 172
A3: RCV-BKE-2026-0002 | B3: 2 | C3: BKE-002 | F3: LOT-BKE-2026-0002 | G3: INSIDE | H3: 802 | I3: 72533 | J3: 793LT03 | K3: 46069 | L3: 16-Feb | M3: 46069 | N3: 16-Feb | O3: MANKONO | P3: CASP-S SCOOPS | Q3: LBA-007-CAS | R3: 559 | S3: 0 | T3: 69 | V3: 628 | Z3: =SUM(R3:U3) -> 628 | AA3: 50880 | AB3: 276 | AC3: 50252 | AD3: =IF(OR(AE3="",AB3=""),"",AE3-AB3) -> 49976 | AE3: 50252 | AF3: 50252 | AK3: =IF(COUNTA(AH3:AJ3)=0,"",SUM(AH3:AJ3)) | AO3: =IF(COUNTA(AL3:AN3)=0,"",SUM(AL3:AN3)) | AP3: =IF(COUNTA(AL3:AN3)<3,"",(AL3+0.5*(AM3+AN3))*0.17637) | AQ3: =IF(AO3="","",AO3*0.17637) | AR3: =IF(COUNTA(AJ3,AH3,AL3:AN3)=0,"",(AJ3+AH3+AL3+AM3+AN3)*0.17637) | AS3: =IF(AO3="","",AO3/1000) | AT3: =IF(COUNTA(AH3,AJ3,AL3:AN3)=0,"",SUM(AH3,AJ3,AL3:AN3)/1000) | AU3: 9 | AV3: 165 | BA3: =IF(COUNTA(AX3:AZ3)=0,"",SUM(AX3:AZ3)) | BE3: =IF(COUNTA(BB3:BD3)=0,"",SUM(BB3:BD3)) | BF3: =IF(COUNTA(BB3:BD3)<3,"",(BB3+0.5*(BC3+BD3))*0.17637) | BG3: =IF(BE3="","",BE3*0.17637) | BH3: =IF(COUNTA(AZ3,AX3,BB3:BD3)=0,"",(AZ3+AX3+BB3+BC3+BD3)*0.17637) | BI3: =IF(BE3="","",BE3/1000) | BJ3: =IF(COUNTA(AX3,AZ3,BB3:BD3)=0,"",SUM(AX3,AZ3,BB3:BD3)/1000) | BK3: 9 | BL3: 165
A4: RCV-BKE-2026-0003 | B4: 3 | C4: BKE-002 | D4: BKE-002-BIN-004 / BKE-002-BIN-006 | F4: LOT-BKE-2026-0003 | G4: INSIDE | H4: 809 | I4: 72615 | J4: 8287GH03 | K4: 46070 | L4: 17-Feb | M4: 46070 | N4: 17-Feb | O4: NIAKARA | P4: SCOOPS HERE B | Q4: LBA-003-HER | R4: 504 | S4: 0 | T4: 8 | V4: 512 | Z4: =SUM(R4:U4) -> 512 | AA4: 45420 | AB4: 32 | AC4: 44908 | AD4: =IF(OR(AE4="",AB4=""),"",AE4-AB4) -> 44876 | AE4: 44908 | AF4: 44908 | AK4: =IF(COUNTA(AH4:AJ4)=0,"",SUM(AH4:AJ4)) | AO4: =IF(COUNTA(AL4:AN4)=0,"",SUM(AL4:AN4)) | AP4: =IF(COUNTA(AL4:AN4)<3,"",(AL4+0.5*(AM4+AN4))*0.17637) | AQ4: =IF(AO4="","",AO4*0.17637) | AR4: =IF(COUNTA(AJ4,AH4,AL4:AN4)=0,"",(AJ4+AH4+AL4+AM4+AN4)*0.17637) | AS4: =IF(AO4="","",AO4/1000) | AT4: =IF(COUNTA(AH4,AJ4,AL4:AN4)=0,"",SUM(AH4,AJ4,AL4:AN4)/1000) | AU4: 11.4 | AV4: 162 | BA4: =IF(COUNTA(AX4:AZ4)=0,"",SUM(AX4:AZ4)) | BE4: =IF(COUNTA(BB4:BD4)=0,"",SUM(BB4:BD4)) | BF4: =IF(COUNTA(BB4:BD4)<3,"",(BB4+0.5*(BC4+BD4))*0.17637) | BG4: =IF(BE4="","",BE4*0.17637) | BH4: =IF(COUNTA(AZ4,AX4,BB4:BD4)=0,"",(AZ4+AX4+BB4+BC4+BD4)*0.17637) | BI4: =IF(BE4="","",BE4/1000) | BJ4: =IF(COUNTA(AX4,AZ4,BB4:BD4)=0,"",SUM(AX4,AZ4,BB4:BD4)/1000) | BK4: 11.4 | BL4: 162
A5: RCV-BKE-2026-0004 | B5: 4 | C5: BKE-003 | F5: LOT-BKE-2026-0004 | G5: INSIDE | H5: 811 | I5: 72540 | J5: 338KX01 | K5: 46070 | L5: 17-Feb | M5: 46070 | N5: 17-Feb | O5: BOUAKE | P5: SCOPPAS SCOOPS | Q5: LBA-009-SCO | R5: 400 | S5: 0 | T5: 25 | V5: 425 | Z5: =SUM(R5:U5) -> 425 | AA5: 35320 | AB5: 100 | AC5: 34895 | AD5: =IF(OR(AE5="",AB5=""),"",AE5-AB5) -> 34795 | AE5: 34895 | AF5: 34895 | AK5: =IF(COUNTA(AH5:AJ5)=0,"",SUM(AH5:AJ5)) | AO5: =IF(COUNTA(AL5:AN5)=0,"",SUM(AL5:AN5)) | AP5: =IF(COUNTA(AL5:AN5)<3,"",(AL5+0.5*(AM5+AN5))*0.17637) | AQ5: =IF(AO5="","",AO5*0.17637) | AR5: =IF(COUNTA(AJ5,AH5,AL5:AN5)=0,"",(AJ5+AH5+AL5+AM5+AN5)*0.17637) | AS5: =IF(AO5="","",AO5/1000) | AT5: =IF(COUNTA(AH5,AJ5,AL5:AN5)=0,"",SUM(AH5,AJ5,AL5:AN5)/1000) | AU5: 9.5 | AV5: 166 | BA5: =IF(COUNTA(AX5:AZ5)=0,"",SUM(AX5:AZ5)) | BE5: =IF(COUNTA(BB5:BD5)=0,"",SUM(BB5:BD5)) | BF5: =IF(COUNTA(BB5:BD5)<3,"",(BB5+0.5*(BC5+BD5))*0.17637) | BG5: =IF(BE5="","",BE5*0.17637) | BH5: =IF(COUNTA(AZ5,AX5,BB5:BD5)=0,"",(AZ5+AX5+BB5+BC5+BD5)*0.17637) | BI5: =IF(BE5="","",BE5/1000) | BJ5: =IF(COUNTA(AX5,AZ5,BB5:BD5)=0,"",SUM(AX5,AZ5,BB5:BD5)/1000) | BK5: 9.5 | BL5: 166
A6: RCV-BKE-2026-0005 | B6: 5 | C6: BKE-002 | D6: BKE-002-BIN-003 | F6: LOT-BKE-2026-0005 | G6: INSIDE | H6: 805 | I6: 72569 | J6: 3633LZ04 | K6: 46070 | L6: 17-Feb | M6: 46070 | N6: 17-Feb | O6: NIAKARA | P6: DAGNOGO KARIM | Q6: LBA-013-DAG | R6: 556 | S6: 12 | T6: 18 | V6: 586 | Z6: =SUM(R6:U6) -> 586 | AA6: 50760 | AB6: 552 | AC6: 50174 | AD6: =IF(OR(AE6="",AB6=""),"",AE6-AB6) -> 49622 | AE6: 50174 | AF6: 50174 | AK6: =IF(COUNTA(AH6:AJ6)=0,"",SUM(AH6:AJ6)) | AO6: =IF(COUNTA(AL6:AN6)=0,"",SUM(AL6:AN6)) | AP6: =IF(COUNTA(AL6:AN6)<3,"",(AL6+0.5*(AM6+AN6))*0.17637) | AQ6: =IF(AO6="","",AO6*0.17637) | AR6: =IF(COUNTA(AJ6,AH6,AL6:AN6)=0,"",(AJ6+AH6+AL6+AM6+AN6)*0.17637) | AS6: =IF(AO6="","",AO6/1000) | AT6: =IF(COUNTA(AH6,AJ6,AL6:AN6)=0,"",SUM(AH6,AJ6,AL6:AN6)/1000) | AU6: 11.5 | AV6: 161 | BA6: =IF(COUNTA(AX6:AZ6)=0,"",SUM(AX6:AZ6)) | BE6: =IF(COUNTA(BB6:BD6)=0,"",SUM(BB6:BD6)) | BF6: =IF(COUNTA(BB6:BD6)<3,"",(BB6+0.5*(BC6+BD6))*0.17637) | BG6: =IF(BE6="","",BE6*0.17637) | BH6: =IF(COUNTA(AZ6,AX6,BB6:BD6)=0,"",(AZ6+AX6+BB6+BC6+BD6)*0.17637) | BI6: =IF(BE6="","",BE6/1000) | BJ6: =IF(COUNTA(AX6,AZ6,BB6:BD6)=0,"",SUM(AX6,AZ6,BB6:BD6)/1000) | BK6: 11.5 | BL6: 161
A7: RCV-BKE-2026-0006 | B7: 6 | C7: BKE-002 | F7: LOT-BKE-2026-0006 | G7: INSIDE | H7: 804 | I7: 72607 | J7: 3509KJ01 | K7: 46070 | L7: 17-Feb | M7: 46070 | N7: 17-Feb | O7: MANKONO | P7: SCOOPS BAY SCOOPS | Q7: LBA-014-BAY | R7: 437 | S7: 0 | T7: 5 | V7: 442 | Z7: =SUM(R7:U7) -> 442 | AA7: 39460 | AB7: 20 | AC7: 39018 | AD7: =IF(OR(AE7="",AB7=""),"",AE7-AB7) -> 38998 | AE7: 39018 | AF7: 39018 | AK7: =IF(COUNTA(AH7:AJ7)=0,"",SUM(AH7:AJ7)) | AO7: =IF(COUNTA(AL7:AN7)=0,"",SUM(AL7:AN7)) | AP7: =IF(COUNTA(AL7:AN7)<3,"",(AL7+0.5*(AM7+AN7))*0.17637) | AQ7: =IF(AO7="","",AO7*0.17637) | AR7: =IF(COUNTA(AJ7,AH7,AL7:AN7)=0,"",(AJ7+AH7+AL7+AM7+AN7)*0.17637) | AS7: =IF(AO7="","",AO7/1000) | AT7: =IF(COUNTA(AH7,AJ7,AL7:AN7)=0,"",SUM(AH7,AJ7,AL7:AN7)/1000) | AU7: 9.1 | AV7: 163 | BA7: =IF(COUNTA(AX7:AZ7)=0,"",SUM(AX7:AZ7)) | BE7: =IF(COUNTA(BB7:BD7)=0,"",SUM(BB7:BD7)) | BF7: =IF(COUNTA(BB7:BD7)<3,"",(BB7+0.5*(BC7+BD7))*0.17637) | BG7: =IF(BE7="","",BE7*0.17637) | BH7: =IF(COUNTA(AZ7,AX7,BB7:BD7)=0,"",(AZ7+AX7+BB7+BC7+BD7)*0.17637) | BI7: =IF(BE7="","",BE7/1000) | BJ7: =IF(COUNTA(AX7,AZ7,BB7:BD7)=0,"",SUM(AX7,AZ7,BB7:BD7)/1000) | BK7: 9.1 | BL7: 163
A8: RCV-BKE-2026-0007 | B8: 7 | C8: BKE-002 | F8: LOT-BKE-2026-0007 | G8: INSIDE | H8: 808 | I8: 72564 | J8: 28JZ01 | K8: 46070 | L8: 17-Feb | M8: 46070 | N8: 17-Feb | O8: BOUAKE | P8: SCOOPS-OUMI/KONE SIDY | Q8: LBA-015-OUM | R8: 555 | S8: 0 | T8: 15 | V8: 570 | Z8: =SUM(R8:U8) -> 570 | AA8: 49020 | AB8: 60 | AC8: 48450 | AD8: =IF(OR(AE8="",AB8=""),"",AE8-AB8) -> 48390 | AE8: 48450 | AF8: 48450 | AK8: =IF(COUNTA(AH8:AJ8)=0,"",SUM(AH8:AJ8)) | AO8: =IF(COUNTA(AL8:AN8)=0,"",SUM(AL8:AN8)) | AP8: =IF(COUNTA(AL8:AN8)<3,"",(AL8+0.5*(AM8+AN8))*0.17637) | AQ8: =IF(AO8="","",AO8*0.17637) | AR8: =IF(COUNTA(AJ8,AH8,AL8:AN8)=0,"",(AJ8+AH8+AL8+AM8+AN8)*0.17637) | AS8: =IF(AO8="","",AO8/1000) | AT8: =IF(COUNTA(AH8,AJ8,AL8:AN8)=0,"",SUM(AH8,AJ8,AL8:AN8)/1000) | AU8: 9.2 | AV8: 172 | BA8: =IF(COUNTA(AX8:AZ8)=0,"",SUM(AX8:AZ8)) | BE8: =IF(COUNTA(BB8:BD8)=0,"",SUM(BB8:BD8)) | BF8: =IF(COUNTA(BB8:BD8)<3,"",(BB8+0.5*(BC8+BD8))*0.17637) | BG8: =IF(BE8="","",BE8*0.17637) | BH8: =IF(COUNTA(AZ8,AX8,BB8:BD8)=0,"",(AZ8+AX8+BB8+BC8+BD8)*0.17637) | BI8: =IF(BE8="","",BE8/1000) | BJ8: =IF(COUNTA(AX8,AZ8,BB8:BD8)=0,"",SUM(AX8,AZ8,BB8:BD8)/1000) | BK8: 9.2 | BL8: 172
A9: RCV-BKE-2026-0008 | B9: 8 | C9: BKE-003 | F9: LOT-BKE-2026-0008 | G9: INSIDE | H9: 815 | I9: 72517 | J9: AA864JL01 | K9: 46071 | L9: 18-Feb | M9: 46071 | N9: 18-Feb | O9: VAVOUA | P9: SCAAMT COOP CA | Q9: LBA-002-SCA | R9: 578 | S9: 0 | T9: 36 | V9: 614 | Z9: =SUM(R9:U9) -> 614 | AA9: 52060 | AB9: 144 | AC9: 51446 | AD9: =IF(OR(AE9="",AB9=""),"",AE9-AB9) -> 51302 | AE9: 51446 | AF9: 51446 | AK9: =IF(COUNTA(AH9:AJ9)=0,"",SUM(AH9:AJ9)) | AO9: =IF(COUNTA(AL9:AN9)=0,"",SUM(AL9:AN9)) | AP9: =IF(COUNTA(AL9:AN9)<3,"",(AL9+0.5*(AM9+AN9))*0.17637) | AQ9: =IF(AO9="","",AO9*0.17637) | AR9: =IF(COUNTA(AJ9,AH9,AL9:AN9)=0,"",(AJ9+AH9+AL9+AM9+AN9)*0.17637) | AS9: =IF(AO9="","",AO9/1000) | AT9: =IF(COUNTA(AH9,AJ9,AL9:AN9)=0,"",SUM(AH9,AJ9,AL9:AN9)/1000) | AU9: 9.5 | AV9: 178 | BA9: =IF(COUNTA(AX9:AZ9)=0,"",SUM(AX9:AZ9)) | BE9: =IF(COUNTA(BB9:BD9)=0,"",SUM(BB9:BD9)) | BF9: =IF(COUNTA(BB9:BD9)<3,"",(BB9+0.5*(BC9+BD9))*0.17637) | BG9: =IF(BE9="","",BE9*0.17637) | BH9: =IF(COUNTA(AZ9,AX9,BB9:BD9)=0,"",(AZ9+AX9+BB9+BC9+BD9)*0.17637) | BI9: =IF(BE9="","",BE9/1000) | BJ9: =IF(COUNTA(AX9,AZ9,BB9:BD9)=0,"",SUM(AX9,AZ9,BB9:BD9)/1000) | BK9: 9.5 | BL9: 178
A10: RCV-BKE-2026-0009 | B10: 9 | C10: BKE-003 | F10: LOT-BKE-2026-0009 | G10: INSIDE | H10: 817 | I10: 72568 | J10: 5176LG04 | K10: 46071 | L10: 18-Feb | M10: 46071 | N10: 18-Feb | O10: DABAKALA | P10: SCOOPS WEBE | Q10: LBA-004-WEB | R10: 410 | S10: 0 | T10: 43 | V10: 453 | Z10: =SUM(R10:U10) -> 453 | AA10: 41540 | AB10: 172 | AC10: 41087 | AD10: =IF(OR(AE10="",AB10=""),"",AE10-AB10) -> 40915 | AE10: 41087 | AF10: 41087 | AK10: =IF(COUNTA(AH10:AJ10)=0,"",SUM(AH10:AJ10)) | AO10: =IF(COUNTA(AL10:AN10)=0,"",SUM(AL10:AN10)) | AP10: =IF(COUNTA(AL10:AN10)<3,"",(AL10+0.5*(AM10+AN10))*0.17637) | AQ10: =IF(AO10="","",AO10*0.17637) | AR10: =IF(COUNTA(AJ10,AH10,AL10:AN10)=0,"",(AJ10+AH10+AL10+AM10+AN10)*0.17637) | AS10: =IF(AO10="","",AO10/1000) | AT10: =IF(COUNTA(AH10,AJ10,AL10:AN10)=0,"",SUM(AH10,AJ10,AL10:AN10)/1000) | AU10: 9.6 | AV10: 182 | BA10: =IF(COUNTA(AX10:AZ10)=0,"",SUM(AX10:AZ10)) | BE10: =IF(COUNTA(BB10:BD10)=0,"",SUM(BB10:BD10)) | BF10: =IF(COUNTA(BB10:BD10)<3,"",(BB10+0.5*(BC10+BD10))*0.17637) | BG10: =IF(BE10="","",BE10*0.17637) | BH10: =IF(COUNTA(AZ10,AX10,BB10:BD10)=0,"",(AZ10+AX10+BB10+BC10+BD10)*0.17637) | BI10: =IF(BE10="","",BE10/1000) | BJ10: =IF(COUNTA(AX10,AZ10,BB10:BD10)=0,"",SUM(AX10,AZ10,BB10:BD10)/1000) | BK10: 9.6 | BL10: 182
A11: RCV-BKE-2026-0010 | B11: 10 | C11: BKE-002 | F11: LOT-BKE-2026-0010 | G11: INSIDE | H11: 812 | I11: 72523 | J11: AA562YL04 | K11: 46071 | L11: 18-Feb | M11: 46071 | N11: 18-Feb | O11: DIANRA | P11: CAPCD-SCOOPS | Q11: LBA-010-CAP | R11: 453 | S11: 0 | T11: 10 | V11: 463 | Z11: =SUM(R11:U11) -> 463 | AA11: 40560 | AB11: 40 | AC11: 40097 | AD11: =IF(OR(AE11="",AB11=""),"",AE11-AB11) -> 40057 | AE11: 40097 | AF11: 40097 | AK11: =IF(COUNTA(AH11:AJ11)=0,"",SUM(AH11:AJ11)) | AO11: =IF(COUNTA(AL11:AN11)=0,"",SUM(AL11:AN11)) | AP11: =IF(COUNTA(AL11:AN11)<3,"",(AL11+0.5*(AM11+AN11))*0.17637) | AQ11: =IF(AO11="","",AO11*0.17637) | AR11: =IF(COUNTA(AJ11,AH11,AL11:AN11)=0,"",(AJ11+AH11+AL11+AM11+AN11)*0.17637) | AS11: =IF(AO11="","",AO11/1000) | AT11: =IF(COUNTA(AH11,AJ11,AL11:AN11)=0,"",SUM(AH11,AJ11,AL11:AN11)/1000) | AU11: 11.2 | AV11: 168 | BA11: =IF(COUNTA(AX11:AZ11)=0,"",SUM(AX11:AZ11)) | BE11: =IF(COUNTA(BB11:BD11)=0,"",SUM(BB11:BD11)) | BF11: =IF(COUNTA(BB11:BD11)<3,"",(BB11+0.5*(BC11+BD11))*0.17637) | BG11: =IF(BE11="","",BE11*0.17637) | BH11: =IF(COUNTA(AZ11,AX11,BB11:BD11)=0,"",(AZ11+AX11+BB11+BC11+BD11)*0.17637) | BI11: =IF(BE11="","",BE11/1000) | BJ11: =IF(COUNTA(AX11,AZ11,BB11:BD11)=0,"",SUM(AX11,AZ11,BB11:BD11)/1000) | BK11: 11.2 | BL11: 168
A12: RCV-BKE-2026-0011 | B12: 11 | C12: BKE-003 | F12: LOT-BKE-2026-0011 | G12: INSIDE | H12: 814 | I12: 72501 | J12: 2138HC01 | K12: 46071 | L12: 18-Feb | M12: 46071 | N12: 18-Feb | O12: MANKONO | P12: SCOOP ASER | Q12: LBA-011-ASR | R12: 524 | S12: 0 | T12: 38 | V12: 562 | Z12: =SUM(R12:U12) -> 562 | AA12: 46680 | AB12: 152 | AC12: 46118 | AD12: =IF(OR(AE12="",AB12=""),"",AE12-AB12) -> 45966 | AE12: 46118 | AF12: 46118 | AK12: =IF(COUNTA(AH12:AJ12)=0,"",SUM(AH12:AJ12)) | AO12: =IF(COUNTA(AL12:AN12)=0,"",SUM(AL12:AN12)) | AP12: =IF(COUNTA(AL12:AN12)<3,"",(AL12+0.5*(AM12+AN12))*0.17637) | AQ12: =IF(AO12="","",AO12*0.17637) | AR12: =IF(COUNTA(AJ12,AH12,AL12:AN12)=0,"",(AJ12+AH12+AL12+AM12+AN12)*0.17637) | AS12: =IF(AO12="","",AO12/1000) | AT12: =IF(COUNTA(AH12,AJ12,AL12:AN12)=0,"",SUM(AH12,AJ12,AL12:AN12)/1000) | AU12: 8.6 | AV12: 171 | BA12: =IF(COUNTA(AX12:AZ12)=0,"",SUM(AX12:AZ12)) | BE12: =IF(COUNTA(BB12:BD12)=0,"",SUM(BB12:BD12)) | BF12: =IF(COUNTA(BB12:BD12)<3,"",(BB12+0.5*(BC12+BD12))*0.17637) | BG12: =IF(BE12="","",BE12*0.17637) | BH12: =IF(COUNTA(AZ12,AX12,BB12:BD12)=0,"",(AZ12+AX12+BB12+BC12+BD12)*0.17637) | BI12: =IF(BE12="","",BE12/1000) | BJ12: =IF(COUNTA(AX12,AZ12,BB12:BD12)=0,"",SUM(AX12,AZ12,BB12:BD12)/1000) | BK12: 8.6 | BL12: 171
A13: RCV-BKE-2026-0012 | B13: 12 | C13: BKE-003 | F13: LOT-BKE-2026-0012 | G13: INSIDE | H13: 823 | I13: 72553 | J13: 285LA01 | K13: 46072 | L13: 19-Feb | M13: 46072 | N13: 19-Feb | O13: VAVOUA | P13: COP JAVA SCOOPS | Q13: LBA-005-JAV | R13: 543 | S13: 0 | T13: 19 | V13: 562 | Z13: =SUM(R13:U13) -> 562 | AA13: 44040 | AB13: 76 | AC13: 43478 | AD13: =IF(OR(AE13="",AB13=""),"",AE13-AB13) -> 43402 | AE13: 43478 | AF13: 43478 | AK13: =IF(COUNTA(AH13:AJ13)=0,"",SUM(AH13:AJ13)) | AO13: =IF(COUNTA(AL13:AN13)=0,"",SUM(AL13:AN13)) | AP13: =IF(COUNTA(AL13:AN13)<3,"",(AL13+0.5*(AM13+AN13))*0.17637) | AQ13: =IF(AO13="","",AO13*0.17637) | AR13: =IF(COUNTA(AJ13,AH13,AL13:AN13)=0,"",(AJ13+AH13+AL13+AM13+AN13)*0.17637) | AS13: =IF(AO13="","",AO13/1000) | AT13: =IF(COUNTA(AH13,AJ13,AL13:AN13)=0,"",SUM(AH13,AJ13,AL13:AN13)/1000) | AU13: 8.2 | AV13: 178 | BA13: =IF(COUNTA(AX13:AZ13)=0,"",SUM(AX13:AZ13)) | BE13: =IF(COUNTA(BB13:BD13)=0,"",SUM(BB13:BD13)) | BF13: =IF(COUNTA(BB13:BD13)<3,"",(BB13+0.5*(BC13+BD13))*0.17637) | BG13: =IF(BE13="","",BE13*0.17637) | BH13: =IF(COUNTA(AZ13,AX13,BB13:BD13)=0,"",(AZ13+AX13+BB13+BC13+BD13)*0.17637) | BI13: =IF(BE13="","",BE13/1000) | BJ13: =IF(COUNTA(AX13,AZ13,BB13:BD13)=0,"",SUM(AX13,AZ13,BB13:BD13)/1000) | BK13: 8.2 | BL13: 178
A14: RCV-BKE-2026-0013 | B14: 13 | C14: BKE-003 | F14: LOT-BKE-2026-0013 | G14: INSIDE | H14: 825 | I14: 72549 | J14: AA057ER03 | K14: 46072 | L14: 19-Feb | M14: 46072 | N14: 19-Feb | O14: DIANRA | P14: SCOOPS KPESSO | Q14: LBA-012-KPE | R14: 498 | S14: 0 | T14: 12 | V14: 510 | Z14: =SUM(R14:U14) -> 510 | AA14: 43860 | AB14: 48 | AC14: 43350 | AD14: =IF(OR(AE14="",AB14=""),"",AE14-AB14) -> 43302 | AE14: 43350 | AF14: 43350 | AK14: =IF(COUNTA(AH14:AJ14)=0,"",SUM(AH14:AJ14)) | AO14: =IF(COUNTA(AL14:AN14)=0,"",SUM(AL14:AN14)) | AP14: =IF(COUNTA(AL14:AN14)<3,"",(AL14+0.5*(AM14+AN14))*0.17637) | AQ14: =IF(AO14="","",AO14*0.17637) | AR14: =IF(COUNTA(AJ14,AH14,AL14:AN14)=0,"",(AJ14+AH14+AL14+AM14+AN14)*0.17637) | AS14: =IF(AO14="","",AO14/1000) | AT14: =IF(COUNTA(AH14,AJ14,AL14:AN14)=0,"",SUM(AH14,AJ14,AL14:AN14)/1000) | AU14: 8.7 | AV14: 178 | BA14: =IF(COUNTA(AX14:AZ14)=0,"",SUM(AX14:AZ14)) | BE14: =IF(COUNTA(BB14:BD14)=0,"",SUM(BB14:BD14)) | BF14: =IF(COUNTA(BB14:BD14)<3,"",(BB14+0.5*(BC14+BD14))*0.17637) | BG14: =IF(BE14="","",BE14*0.17637) | BH14: =IF(COUNTA(AZ14,AX14,BB14:BD14)=0,"",(AZ14+AX14+BB14+BC14+BD14)*0.17637) | BI14: =IF(BE14="","",BE14/1000) | BJ14: =IF(COUNTA(AX14,AZ14,BB14:BD14)=0,"",SUM(AX14,AZ14,BB14:BD14)/1000) | BK14: 8.7 | BL14: 178
A15: RCV-BKE-2026-0014 | B15: 14 | C15: BKE-002 | F15: LOT-BKE-2026-0014 | G15: INSIDE | H15: 836 | I15: 72529 | J15: 2415CV03 | K15: 46073 | L15: 20-Feb | M15: 46073 | N15: 20-Feb | O15: DIANRA | P15: SCOOP-CA/COBAN | Q15: LBA-008-COB | R15: 544 | T15: 63 | V15: 607 | Z15: =SUM(R15:U15) -> 607 | AA15: 51300 | AB15: 252 | AC15: 50693 | AD15: =IF(OR(AE15="",AB15=""),"",AE15-AB15) -> 50441 | AE15: 50693 | AF15: 50693 | AK15: =IF(COUNTA(AH15:AJ15)=0,"",SUM(AH15:AJ15)) | AO15: =IF(COUNTA(AL15:AN15)=0,"",SUM(AL15:AN15)) | AP15: =IF(COUNTA(AL15:AN15)<3,"",(AL15+0.5*(AM15+AN15))*0.17637) | AQ15: =IF(AO15="","",AO15*0.17637) | AR15: =IF(COUNTA(AJ15,AH15,AL15:AN15)=0,"",(AJ15+AH15+AL15+AM15+AN15)*0.17637) | AS15: =IF(AO15="","",AO15/1000) | AT15: =IF(COUNTA(AH15,AJ15,AL15:AN15)=0,"",SUM(AH15,AJ15,AL15:AN15)/1000) | AU15: 8.5 | AV15: 167 | BA15: =IF(COUNTA(AX15:AZ15)=0,"",SUM(AX15:AZ15)) | BE15: =IF(COUNTA(BB15:BD15)=0,"",SUM(BB15:BD15)) | BF15: =IF(COUNTA(BB15:BD15)<3,"",(BB15+0.5*(BC15+BD15))*0.17637) | BG15: =IF(BE15="","",BE15*0.17637) | BH15: =IF(COUNTA(AZ15,AX15,BB15:BD15)=0,"",(AZ15+AX15+BB15+BC15+BD15)*0.17637) | BI15: =IF(BE15="","",BE15/1000) | BJ15: =IF(COUNTA(AX15,AZ15,BB15:BD15)=0,"",SUM(AX15,AZ15,BB15:BD15)/1000) | BK15: 8.5 | BL15: 167
A16: RCV-BKE-2026-0015 | B16: 15 | C16: BKE-003 | F16: LOT-BKE-2026-0015 | G16: INSIDE | H16: 842 | I16: 72593 | J16: 838LX01 | K16: 46074 | L16: 21-Feb | M16: 46074 | N16: 21-Feb | O16: KATIOLA | P16: SCOOPS AH AL NOUR | Q16: LBA-016-NOU | R16: 516 | S16: 0 | T16: 21 | V16: 537 | Z16: =SUM(R16:U16) -> 537 | AA16: 46380 | AB16: 84 | AC16: 45843 | AD16: =IF(OR(AE16="",AB16=""),"",AE16-AB16) -> 45759 | AE16: 45843 | AF16: 45843 | AK16: =IF(COUNTA(AH16:AJ16)=0,"",SUM(AH16:AJ16)) | AO16: =IF(COUNTA(AL16:AN16)=0,"",SUM(AL16:AN16)) | AP16: =IF(COUNTA(AL16:AN16)<3,"",(AL16+0.5*(AM16+AN16))*0.17637) | AQ16: =IF(AO16="","",AO16*0.17637) | AR16: =IF(COUNTA(AJ16,AH16,AL16:AN16)=0,"",(AJ16+AH16+AL16+AM16+AN16)*0.17637) | AS16: =IF(AO16="","",AO16/1000) | AT16: =IF(COUNTA(AH16,AJ16,AL16:AN16)=0,"",SUM(AH16,AJ16,AL16:AN16)/1000) | AU16: 9 | AV16: 165 | BA16: =IF(COUNTA(AX16:AZ16)=0,"",SUM(AX16:AZ16)) | BE16: =IF(COUNTA(BB16:BD16)=0,"",SUM(BB16:BD16)) | BF16: =IF(COUNTA(BB16:BD16)<3,"",(BB16+0.5*(BC16+BD16))*0.17637) | BG16: =IF(BE16="","",BE16*0.17637) | BH16: =IF(COUNTA(AZ16,AX16,BB16:BD16)=0,"",(AZ16+AX16+BB16+BC16+BD16)*0.17637) | BI16: =IF(BE16="","",BE16/1000) | BJ16: =IF(COUNTA(AX16,AZ16,BB16:BD16)=0,"",SUM(AX16,AZ16,BB16:BD16)/1000) | BK16: 9 | BL16: 165
A17: RCV-BKE-2026-0016 | B17: 16 | C17: BKE-002 | F17: LOT-BKE-2026-0016 | G17: INSIDE | H17: 844 | I17: 68145 | J17: 32LA01 | K17: 46074 | L17: 21-Feb | M17: 46074 | N17: 21-Feb | O17: DIANRA | P17: SCOOPS DPVICA | Q17: LBA-017-DPV | R17: 493 | S17: 0 | T17: 27 | V17: 520 | Z17: =SUM(R17:U17) -> 520 | AA17: 40740 | AB17: 108 | AC17: 40220 | AD17: =IF(OR(AE17="",AB17=""),"",AE17-AB17) -> 40112 | AE17: 40220 | AF17: 40220 | AK17: =IF(COUNTA(AH17:AJ17)=0,"",SUM(AH17:AJ17)) | AO17: =IF(COUNTA(AL17:AN17)=0,"",SUM(AL17:AN17)) | AP17: =IF(COUNTA(AL17:AN17)<3,"",(AL17+0.5*(AM17+AN17))*0.17637) | AQ17: =IF(AO17="","",AO17*0.17637) | AR17: =IF(COUNTA(AJ17,AH17,AL17:AN17)=0,"",(AJ17+AH17+AL17+AM17+AN17)*0.17637) | AS17: =IF(AO17="","",AO17/1000) | AT17: =IF(COUNTA(AH17,AJ17,AL17:AN17)=0,"",SUM(AH17,AJ17,AL17:AN17)/1000) | AU17: 9.3 | AV17: 166 | BA17: =IF(COUNTA(AX17:AZ17)=0,"",SUM(AX17:AZ17)) | BE17: =IF(COUNTA(BB17:BD17)=0,"",SUM(BB17:BD17)) | BF17: =IF(COUNTA(BB17:BD17)<3,"",(BB17+0.5*(BC17+BD17))*0.17637) | BG17: =IF(BE17="","",BE17*0.17637) | BH17: =IF(COUNTA(AZ17,AX17,BB17:BD17)=0,"",(AZ17+AX17+BB17+BC17+BD17)*0.17637) | BI17: =IF(BE17="","",BE17/1000) | BJ17: =IF(COUNTA(AX17,AZ17,BB17:BD17)=0,"",SUM(AX17,AZ17,BB17:BD17)/1000) | BK17: 9.3 | BL17: 166
A18: RCV-BKE-2026-0017 | B18: 17 | C18: BKE-003 | F18: LOT-BKE-2026-0017 | G18: INSIDE | H18: 768 | I18: 72620 | J18: 2766HC01 | K18: 46077 | L18: 24-Feb | M18: 46077 | N18: 24-Feb | O18: KATIOLA | P18: SCOOPS COOPRAKA | Q18: LBA-018-COP | R18: 441 | S18: 0 | T18: 10 | V18: 451 | Z18: =SUM(R18:U18) -> 451 | AA18: 39020 | AB18: 40 | AC18: 38569 | AD18: =IF(OR(AE18="",AB18=""),"",AE18-AB18) -> 38529 | AE18: 38569 | AF18: 38569 | AK18: =IF(COUNTA(AH18:AJ18)=0,"",SUM(AH18:AJ18)) | AO18: =IF(COUNTA(AL18:AN18)=0,"",SUM(AL18:AN18)) | AP18: =IF(COUNTA(AL18:AN18)<3,"",(AL18+0.5*(AM18+AN18))*0.17637) | AQ18: =IF(AO18="","",AO18*0.17637) | AR18: =IF(COUNTA(AJ18,AH18,AL18:AN18)=0,"",(AJ18+AH18+AL18+AM18+AN18)*0.17637) | AS18: =IF(AO18="","",AO18/1000) | AT18: =IF(COUNTA(AH18,AJ18,AL18:AN18)=0,"",SUM(AH18,AJ18,AL18:AN18)/1000) | AU18: 9.4 | AV18: 174 | BA18: =IF(COUNTA(AX18:AZ18)=0,"",SUM(AX18:AZ18)) | BE18: =IF(COUNTA(BB18:BD18)=0,"",SUM(BB18:BD18)) | BF18: =IF(COUNTA(BB18:BD18)<3,"",(BB18+0.5*(BC18+BD18))*0.17637) | BG18: =IF(BE18="","",BE18*0.17637) | BH18: =IF(COUNTA(AZ18,AX18,BB18:BD18)=0,"",(AZ18+AX18+BB18+BC18+BD18)*0.17637) | BI18: =IF(BE18="","",BE18/1000) | BJ18: =IF(COUNTA(AX18,AZ18,BB18:BD18)=0,"",SUM(AX18,AZ18,BB18:BD18)/1000) | BK18: 9.4 | BL18: 174
A19: RCV-BKE-2026-0018 | B19: 18 | C19: BKE-003 | F19: LOT-BKE-2026-0018 | G19: INSIDE | H19: 778 | I19: 68659 | J19: 3619 EJ 03 | K19: 46078 | L19: 25-Feb | M19: 46078 | N19: 25-Feb | O19: BOUNDIALI | P19: CASP-S SCOOPS | Q19: LBA-007-CAS | R19: 606 | S19: 0 | T19: 30 | V19: 636 | Z19: =SUM(R19:U19) -> 636 | AA19: 51380 | AB19: 120 | AC19: 50744 | AD19: =IF(OR(AE19="",AB19=""),"",AE19-AB19) -> 50624 | AE19: 50744 | AF19: 50744 | AK19: =IF(COUNTA(AH19:AJ19)=0,"",SUM(AH19:AJ19)) | AO19: =IF(COUNTA(AL19:AN19)=0,"",SUM(AL19:AN19)) | AP19: =IF(COUNTA(AL19:AN19)<3,"",(AL19+0.5*(AM19+AN19))*0.17637) | AQ19: =IF(AO19="","",AO19*0.17637) | AR19: =IF(COUNTA(AJ19,AH19,AL19:AN19)=0,"",(AJ19+AH19+AL19+AM19+AN19)*0.17637) | AS19: =IF(AO19="","",AO19/1000) | AT19: =IF(COUNTA(AH19,AJ19,AL19:AN19)=0,"",SUM(AH19,AJ19,AL19:AN19)/1000) | AU19: 8 | AV19: 175 | BA19: =IF(COUNTA(AX19:AZ19)=0,"",SUM(AX19:AZ19)) | BE19: =IF(COUNTA(BB19:BD19)=0,"",SUM(BB19:BD19)) | BF19: =IF(COUNTA(BB19:BD19)<3,"",(BB19+0.5*(BC19+BD19))*0.17637) | BG19: =IF(BE19="","",BE19*0.17637) | BH19: =IF(COUNTA(AZ19,AX19,BB19:BD19)=0,"",(AZ19+AX19+BB19+BC19+BD19)*0.17637) | BI19: =IF(BE19="","",BE19/1000) | BJ19: =IF(COUNTA(AX19,AZ19,BB19:BD19)=0,"",SUM(AX19,AZ19,BB19:BD19)/1000) | BK19: 8 | BL19: 175
A20: RCV-BKE-2026-0019 | B20: 19 | C20: BKE-003 | F20: LOT-BKE-2026-0019 | G20: INSIDE | H20: 1238 | I20: 77662 | J20: 374LK01 | K20: 46086 | L20: 05-Mar | M20: 46086 | N20: 05-Mar | O20: NIAKARA | P20: DAGNOGO KARIM | Q20: LBA-013-DAG | R20: 494 | S20: 0 | T20: 10 | V20: 504 | Z20: =SUM(R20:U20) -> 504 | AA20: 46760 | AB20: 40 | AC20: 46256 | AD20: =IF(OR(AE20="",AB20=""),"",AE20-AB20) -> 46216 | AE20: 46256 | AF20: 46256 | AK20: =IF(COUNTA(AH20:AJ20)=0,"",SUM(AH20:AJ20)) | AO20: =IF(COUNTA(AL20:AN20)=0,"",SUM(AL20:AN20)) | AP20: =IF(COUNTA(AL20:AN20)<3,"",(AL20+0.5*(AM20+AN20))*0.17637) | AQ20: =IF(AO20="","",AO20*0.17637) | AR20: =IF(COUNTA(AJ20,AH20,AL20:AN20)=0,"",(AJ20+AH20+AL20+AM20+AN20)*0.17637) | AS20: =IF(AO20="","",AO20/1000) | AT20: =IF(COUNTA(AH20,AJ20,AL20:AN20)=0,"",SUM(AH20,AJ20,AL20:AN20)/1000) | AU20: 9.7 | AV20: 160 | BA20: =IF(COUNTA(AX20:AZ20)=0,"",SUM(AX20:AZ20)) | BE20: =IF(COUNTA(BB20:BD20)=0,"",SUM(BB20:BD20)) | BF20: =IF(COUNTA(BB20:BD20)<3,"",(BB20+0.5*(BC20+BD20))*0.17637) | BG20: =IF(BE20="","",BE20*0.17637) | BH20: =IF(COUNTA(AZ20,AX20,BB20:BD20)=0,"",(AZ20+AX20+BB20+BC20+BD20)*0.17637) | BI20: =IF(BE20="","",BE20/1000) | BJ20: =IF(COUNTA(AX20,AZ20,BB20:BD20)=0,"",SUM(AX20,AZ20,BB20:BD20)/1000) | BK20: 9.7 | BL20: 160
A21: RCV-BKE-2026-0020 | B21: 20 | C21: BKE-001 | F21: LOT-BKE-2026-0020 | G21: INSIDE | H21: 202 | I21: 77633 | J21: 6085HR03 | K21: 46088 | L21: 07-Mar | M21: 46088 | N21: 07-Mar | O21: NIAKARA | P21: SCOOPS HERE B | Q21: LBA-003-HER | R21: 540 | S21: 0 | T21: 8 | V21: 548 | Z21: =SUM(R21:U21) -> 548 | AA21: 46040 | AB21: 32 | AC21: 45492 | AD21: =IF(OR(AE21="",AB21=""),"",AE21-AB21) -> 45460 | AE21: 45492 | AF21: 45492 | AK21: =IF(COUNTA(AH21:AJ21)=0,"",SUM(AH21:AJ21)) | AO21: =IF(COUNTA(AL21:AN21)=0,"",SUM(AL21:AN21)) | AP21: =IF(COUNTA(AL21:AN21)<3,"",(AL21+0.5*(AM21+AN21))*0.17637) | AQ21: =IF(AO21="","",AO21*0.17637) | AR21: =IF(COUNTA(AJ21,AH21,AL21:AN21)=0,"",(AJ21+AH21+AL21+AM21+AN21)*0.17637) | AS21: =IF(AO21="","",AO21/1000) | AT21: =IF(COUNTA(AH21,AJ21,AL21:AN21)=0,"",SUM(AH21,AJ21,AL21:AN21)/1000) | AU21: 9.8 | AV21: 168 | BA21: =IF(COUNTA(AX21:AZ21)=0,"",SUM(AX21:AZ21)) | BE21: =IF(COUNTA(BB21:BD21)=0,"",SUM(BB21:BD21)) | BF21: =IF(COUNTA(BB21:BD21)<3,"",(BB21+0.5*(BC21+BD21))*0.17637) | BG21: =IF(BE21="","",BE21*0.17637) | BH21: =IF(COUNTA(AZ21,AX21,BB21:BD21)=0,"",(AZ21+AX21+BB21+BC21+BD21)*0.17637) | BI21: =IF(BE21="","",BE21/1000) | BJ21: =IF(COUNTA(AX21,AZ21,BB21:BD21)=0,"",SUM(AX21,AZ21,BB21:BD21)/1000) | BK21: 9.8 | BL21: 168
A22: RCV-BKE-2026-0021 | B22: 21 | C22: BKE-001 | F22: LOT-BKE-2026-0021 | G22: INSIDE | H22: 225 | I22: 75589 | J22: 6690GB01 | K22: 46092 | L22: 11-Mar | M22: 46092 | N22: 11-Mar | O22: VAVOUA | P22: SCOPPAS SCOOPS | Q22: LBA-009-SCO | R22: 605 | S22: 0 | T22: 8 | V22: 613 | Z22: =SUM(R22:U22) -> 613 | AA22: 48580 | AB22: 32 | AC22: 47967 | AD22: =IF(OR(AE22="",AB22=""),"",AE22-AB22) -> 47935 | AE22: 47967 | AF22: 47967 | AK22: =IF(COUNTA(AH22:AJ22)=0,"",SUM(AH22:AJ22)) | AO22: =IF(COUNTA(AL22:AN22)=0,"",SUM(AL22:AN22)) | AP22: =IF(COUNTA(AL22:AN22)<3,"",(AL22+0.5*(AM22+AN22))*0.17637) | AQ22: =IF(AO22="","",AO22*0.17637) | AR22: =IF(COUNTA(AJ22,AH22,AL22:AN22)=0,"",(AJ22+AH22+AL22+AM22+AN22)*0.17637) | AS22: =IF(AO22="","",AO22/1000) | AT22: =IF(COUNTA(AH22,AJ22,AL22:AN22)=0,"",SUM(AH22,AJ22,AL22:AN22)/1000) | AU22: 9.9 | AV22: 185 | BA22: =IF(COUNTA(AX22:AZ22)=0,"",SUM(AX22:AZ22)) | BE22: =IF(COUNTA(BB22:BD22)=0,"",SUM(BB22:BD22)) | BF22: =IF(COUNTA(BB22:BD22)<3,"",(BB22+0.5*(BC22+BD22))*0.17637) | BG22: =IF(BE22="","",BE22*0.17637) | BH22: =IF(COUNTA(AZ22,AX22,BB22:BD22)=0,"",(AZ22+AX22+BB22+BC22+BD22)*0.17637) | BI22: =IF(BE22="","",BE22/1000) | BJ22: =IF(COUNTA(AX22,AZ22,BB22:BD22)=0,"",SUM(AX22,AZ22,BB22:BD22)/1000) | BK22: 9.9 | BL22: 185
A23: RCV-BKE-2026-0022 | B23: 22 | C23: BKE-001 | F23: LOT-BKE-2026-0022 | G23: INSIDE | H23: 237 | I23: 72647 | J23: 8573GA01 | K23: 46093 | L23: 12-Mar | M23: 46093 | N23: 12-Mar | O23: SEGUELA | P23: SCOOP-CA/COBAN | Q23: LBA-008-COB | R23: 506 | S23: 0 | T23: 10 | V23: 516 | Z23: =SUM(R23:U23) -> 516 | AA23: 40300 | AB23: 40 | AC23: 39784 | AD23: =IF(OR(AE23="",AB23=""),"",AE23-AB23) -> 39744 | AE23: 39784 | AF23: 39784 | AK23: =IF(COUNTA(AH23:AJ23)=0,"",SUM(AH23:AJ23)) | AO23: =IF(COUNTA(AL23:AN23)=0,"",SUM(AL23:AN23)) | AP23: =IF(COUNTA(AL23:AN23)<3,"",(AL23+0.5*(AM23+AN23))*0.17637) | AQ23: =IF(AO23="","",AO23*0.17637) | AR23: =IF(COUNTA(AJ23,AH23,AL23:AN23)=0,"",(AJ23+AH23+AL23+AM23+AN23)*0.17637) | AS23: =IF(AO23="","",AO23/1000) | AT23: =IF(COUNTA(AH23,AJ23,AL23:AN23)=0,"",SUM(AH23,AJ23,AL23:AN23)/1000) | AU23: 7.5 | AV23: 166 | BA23: =IF(COUNTA(AX23:AZ23)=0,"",SUM(AX23:AZ23)) | BE23: =IF(COUNTA(BB23:BD23)=0,"",SUM(BB23:BD23)) | BF23: =IF(COUNTA(BB23:BD23)<3,"",(BB23+0.5*(BC23+BD23))*0.17637) | BG23: =IF(BE23="","",BE23*0.17637) | BH23: =IF(COUNTA(AZ23,AX23,BB23:BD23)=0,"",(AZ23+AX23+BB23+BC23+BD23)*0.17637) | BI23: =IF(BE23="","",BE23/1000) | BJ23: =IF(COUNTA(AX23,AZ23,BB23:BD23)=0,"",SUM(AX23,AZ23,BB23:BD23)/1000) | BK23: 7.5 | BL23: 166
A24: RCV-BKE-2026-0023 | B24: 23 | C24: BKE-002 | F24: LOT-BKE-2026-0023 | G24: INSIDE | H24: 246 | I24: 82147 | J24: AA869FY01 | K24: 46095 | L24: 14-Mar | M24: 46095 | N24: 14-Mar | O24: DABAKALA | P24: SCOOPS WEBE | Q24: LBA-004-WEB | R24: 532 | S24: 0 | T24: 8 | V24: 540 | Z24: =SUM(R24:U24) -> 540 | AA24: 44880 | AB24: 32 | AC24: 44340 | AD24: =IF(OR(AE24="",AB24=""),"",AE24-AB24) -> 44308 | AE24: 44340 | AF24: 44340 | AK24: =IF(COUNTA(AH24:AJ24)=0,"",SUM(AH24:AJ24)) | AO24: =IF(COUNTA(AL24:AN24)=0,"",SUM(AL24:AN24)) | AP24: =IF(COUNTA(AL24:AN24)<3,"",(AL24+0.5*(AM24+AN24))*0.17637) | AQ24: =IF(AO24="","",AO24*0.17637) | AR24: =IF(COUNTA(AJ24,AH24,AL24:AN24)=0,"",(AJ24+AH24+AL24+AM24+AN24)*0.17637) | AS24: =IF(AO24="","",AO24/1000) | AT24: =IF(COUNTA(AH24,AJ24,AL24:AN24)=0,"",SUM(AH24,AJ24,AL24:AN24)/1000) | AU24: 8.6 | AV24: 166 | BA24: =IF(COUNTA(AX24:AZ24)=0,"",SUM(AX24:AZ24)) | BE24: =IF(COUNTA(BB24:BD24)=0,"",SUM(BB24:BD24)) | BF24: =IF(COUNTA(BB24:BD24)<3,"",(BB24+0.5*(BC24+BD24))*0.17637) | BG24: =IF(BE24="","",BE24*0.17637) | BH24: =IF(COUNTA(AZ24,AX24,BB24:BD24)=0,"",(AZ24+AX24+BB24+BC24+BD24)*0.17637) | BI24: =IF(BE24="","",BE24/1000) | BJ24: =IF(COUNTA(AX24,AZ24,BB24:BD24)=0,"",SUM(AX24,AZ24,BB24:BD24)/1000) | BK24: 8.6 | BL24: 166
A25: RCV-BKE-2026-0024 | B25: 24 | C25: BKE-001 | D25: BKE-001-BIN-015 | F25: LOT-BKE-2026-0024 | G25: INSIDE | H25: 108 | I25: 82869 | J25: 8287GH03 | K25: 46096 | L25: 15-Mar | M25: 46097 | N25: 16-Mar | O25: DABAKALA | P25: SCOOPS HERE B | Q25: LBA-003-HER | R25: 455 | S25: 0 | T25: 20 | V25: 475 | Z25: =SUM(R25:U25) -> 475 | AA25: 39880 | AB25: 80 | AC25: 39405 | AD25: =IF(OR(AE25="",AB25=""),"",AE25-AB25) -> 39325 | AE25: 39405 | AF25: 39405 | AK25: =IF(COUNTA(AH25:AJ25)=0,"",SUM(AH25:AJ25)) | AO25: =IF(COUNTA(AL25:AN25)=0,"",SUM(AL25:AN25)) | AP25: =IF(COUNTA(AL25:AN25)<3,"",(AL25+0.5*(AM25+AN25))*0.17637) | AQ25: =IF(AO25="","",AO25*0.17637) | AR25: =IF(COUNTA(AJ25,AH25,AL25:AN25)=0,"",(AJ25+AH25+AL25+AM25+AN25)*0.17637) | AS25: =IF(AO25="","",AO25/1000) | AT25: =IF(COUNTA(AH25,AJ25,AL25:AN25)=0,"",SUM(AH25,AJ25,AL25:AN25)/1000) | AU25: 12.2 | AV25: 189 | BA25: =IF(COUNTA(AX25:AZ25)=0,"",SUM(AX25:AZ25)) | BE25: =IF(COUNTA(BB25:BD25)=0,"",SUM(BB25:BD25)) | BF25: =IF(COUNTA(BB25:BD25)<3,"",(BB25+0.5*(BC25+BD25))*0.17637) | BG25: =IF(BE25="","",BE25*0.17637) | BH25: =IF(COUNTA(AZ25,AX25,BB25:BD25)=0,"",(AZ25+AX25+BB25+BC25+BD25)*0.17637) | BI25: =IF(BE25="","",BE25/1000) | BJ25: =IF(COUNTA(AX25,AZ25,BB25:BD25)=0,"",SUM(AX25,AZ25,BB25:BD25)/1000) | BK25: 12.2 | BL25: 189
A26: RCV-BKE-2026-0025 | B26: 25 | C26: BKE-001 | D26: BKE-001-BIN-016 | F26: LOT-BKE-2026-0025 | G26: INSIDE | H26: 109 | I26: 82143 | J26: 4137LG04 | K26: 46096 | L26: 15-Mar | M26: 46097 | N26: 16-Mar | O26: KATIOLA | P26: SCOOPS AH AL NOUR | Q26: LBA-016-NOU | R26: 502 | S26: 0 | T26: 10 | V26: 512 | Z26: =SUM(R26:U26) -> 512 | AA26: 43640 | AB26: 40 | AC26: 43128 | AD26: =IF(OR(AE26="",AB26=""),"",AE26-AB26) -> 43088 | AE26: 43128 | AF26: 43128 | AK26: =IF(COUNTA(AH26:AJ26)=0,"",SUM(AH26:AJ26)) | AO26: =IF(COUNTA(AL26:AN26)=0,"",SUM(AL26:AN26)) | AP26: =IF(COUNTA(AL26:AN26)<3,"",(AL26+0.5*(AM26+AN26))*0.17637) | AQ26: =IF(AO26="","",AO26*0.17637) | AR26: =IF(COUNTA(AJ26,AH26,AL26:AN26)=0,"",(AJ26+AH26+AL26+AM26+AN26)*0.17637) | AS26: =IF(AO26="","",AO26/1000) | AT26: =IF(COUNTA(AH26,AJ26,AL26:AN26)=0,"",SUM(AH26,AJ26,AL26:AN26)/1000) | AU26: 11 | AV26: 164 | BA26: =IF(COUNTA(AX26:AZ26)=0,"",SUM(AX26:AZ26)) | BE26: =IF(COUNTA(BB26:BD26)=0,"",SUM(BB26:BD26)) | BF26: =IF(COUNTA(BB26:BD26)<3,"",(BB26+0.5*(BC26+BD26))*0.17637) | BG26: =IF(BE26="","",BE26*0.17637) | BH26: =IF(COUNTA(AZ26,AX26,BB26:BD26)=0,"",(AZ26+AX26+BB26+BC26+BD26)*0.17637) | BI26: =IF(BE26="","",BE26/1000) | BJ26: =IF(COUNTA(AX26,AZ26,BB26:BD26)=0,"",SUM(AX26,AZ26,BB26:BD26)/1000) | BK26: 11 | BL26: 164
A27: RCV-BKE-2026-0026 | B27: 26 | C27: BKE-003 | F27: LOT-BKE-2026-0026 | G27: INSIDE | H27: 117 | I27: 82164 | J27: AA057ER03 | K27: 46098 | L27: 17-Mar | M27: 46098 | N27: 17-Mar | O27: DIANRA | P27: SCOOPS KPESSO | Q27: LBA-012-KPE | R27: 469 | S27: 0 | T27: 10 | V27: 479 | Z27: =SUM(R27:U27) -> 479 | AA27: 39920 | AB27: 40 | AC27: 39441 | AD27: =IF(OR(AE27="",AB27=""),"",AE27-AB27) -> 39401 | AE27: 39441 | AF27: 39441 | AK27: =IF(COUNTA(AH27:AJ27)=0,"",SUM(AH27:AJ27)) | AO27: =IF(COUNTA(AL27:AN27)=0,"",SUM(AL27:AN27)) | AP27: =IF(COUNTA(AL27:AN27)<3,"",(AL27+0.5*(AM27+AN27))*0.17637) | AQ27: =IF(AO27="","",AO27*0.17637) | AR27: =IF(COUNTA(AJ27,AH27,AL27:AN27)=0,"",(AJ27+AH27+AL27+AM27+AN27)*0.17637) | AS27: =IF(AO27="","",AO27/1000) | AT27: =IF(COUNTA(AH27,AJ27,AL27:AN27)=0,"",SUM(AH27,AJ27,AL27:AN27)/1000) | AU27: 9.4 | AV27: 162 | BA27: =IF(COUNTA(AX27:AZ27)=0,"",SUM(AX27:AZ27)) | BE27: =IF(COUNTA(BB27:BD27)=0,"",SUM(BB27:BD27)) | BF27: =IF(COUNTA(BB27:BD27)<3,"",(BB27+0.5*(BC27+BD27))*0.17637) | BG27: =IF(BE27="","",BE27*0.17637) | BH27: =IF(COUNTA(AZ27,AX27,BB27:BD27)=0,"",(AZ27+AX27+BB27+BC27+BD27)*0.17637) | BI27: =IF(BE27="","",BE27/1000) | BJ27: =IF(COUNTA(AX27,AZ27,BB27:BD27)=0,"",SUM(AX27,AZ27,BB27:BD27)/1000) | BK27: 9.4 | BL27: 162
A28: RCV-BKE-2026-0027 | B28: 27 | C28: BKE-001 | F28: LOT-BKE-2026-0027 | G28: INSIDE | H28: 130 | I28: 82151 | J28: 616KY03 | K28: 46100 | L28: 19-Mar | M28: 46103 | N28: 22-Mar | O28: BOTRO | P28: SCOOP IMANE | Q28: LBA-006-IMA | R28: 454 | S28: 0 | T28: 10 | V28: 464 | Z28: =SUM(R28:U28) -> 464 | AA28: 40740 | AB28: 40 | AC28: 40276 | AD28: =IF(OR(AE28="",AB28=""),"",AE28-AB28) -> 40236 | AE28: 40276 | AF28: 40276 | AK28: =IF(COUNTA(AH28:AJ28)=0,"",SUM(AH28:AJ28)) | AO28: =IF(COUNTA(AL28:AN28)=0,"",SUM(AL28:AN28)) | AP28: =IF(COUNTA(AL28:AN28)<3,"",(AL28+0.5*(AM28+AN28))*0.17637) | AQ28: =IF(AO28="","",AO28*0.17637) | AR28: =IF(COUNTA(AJ28,AH28,AL28:AN28)=0,"",(AJ28+AH28+AL28+AM28+AN28)*0.17637) | AS28: =IF(AO28="","",AO28/1000) | AT28: =IF(COUNTA(AH28,AJ28,AL28:AN28)=0,"",SUM(AH28,AJ28,AL28:AN28)/1000) | AU28: 10.3 | AV28: 163 | BA28: =IF(COUNTA(AX28:AZ28)=0,"",SUM(AX28:AZ28)) | BE28: =IF(COUNTA(BB28:BD28)=0,"",SUM(BB28:BD28)) | BF28: =IF(COUNTA(BB28:BD28)<3,"",(BB28+0.5*(BC28+BD28))*0.17637) | BG28: =IF(BE28="","",BE28*0.17637) | BH28: =IF(COUNTA(AZ28,AX28,BB28:BD28)=0,"",(AZ28+AX28+BB28+BC28+BD28)*0.17637) | BI28: =IF(BE28="","",BE28/1000) | BJ28: =IF(COUNTA(AX28,AZ28,BB28:BD28)=0,"",SUM(AX28,AZ28,BB28:BD28)/1000) | BK28: 10.3 | BL28: 163
A29: RCV-BKE-2026-0028 | B29: 28 | C29: BKE-001 | F29: LOT-BKE-2026-0028 | G29: INSIDE | H29: 131 | I29: 82130 | J29: AA398TS04 | K29: 46102 | L29: 21-Mar | M29: 46104 | N29: 23-Mar | O29: DUEKOUE | P29: SCOOP ASER | Q29: LBA-011-ASR | R29: 662 | S29: 0 | T29: 16 | V29: 678 | Z29: =SUM(R29:U29) -> 678 | AA29: 55220 | AB29: 64 | AC29: 54542 | AD29: =IF(OR(AE29="",AB29=""),"",AE29-AB29) -> 54478 | AE29: 54542 | AF29: 54542 | AK29: =IF(COUNTA(AH29:AJ29)=0,"",SUM(AH29:AJ29)) | AO29: =IF(COUNTA(AL29:AN29)=0,"",SUM(AL29:AN29)) | AP29: =IF(COUNTA(AL29:AN29)<3,"",(AL29+0.5*(AM29+AN29))*0.17637) | AQ29: =IF(AO29="","",AO29*0.17637) | AR29: =IF(COUNTA(AJ29,AH29,AL29:AN29)=0,"",(AJ29+AH29+AL29+AM29+AN29)*0.17637) | AS29: =IF(AO29="","",AO29/1000) | AT29: =IF(COUNTA(AH29,AJ29,AL29:AN29)=0,"",SUM(AH29,AJ29,AL29:AN29)/1000) | AU29: 10.7 | AV29: 181 | BA29: =IF(COUNTA(AX29:AZ29)=0,"",SUM(AX29:AZ29)) | BE29: =IF(COUNTA(BB29:BD29)=0,"",SUM(BB29:BD29)) | BF29: =IF(COUNTA(BB29:BD29)<3,"",(BB29+0.5*(BC29+BD29))*0.17637) | BG29: =IF(BE29="","",BE29*0.17637) | BH29: =IF(COUNTA(AZ29,AX29,BB29:BD29)=0,"",(AZ29+AX29+BB29+BC29+BD29)*0.17637) | BI29: =IF(BE29="","",BE29/1000) | BJ29: =IF(COUNTA(AX29,AZ29,BB29:BD29)=0,"",SUM(AX29,AZ29,BB29:BD29)/1000) | BK29: 10.7 | BL29: 181
A30: RCV-BKE-2026-0029 | B30: 29 | C30: BKE-003 | F30: LOT-BKE-2026-0029 | G30: INSIDE | H30: 133 | I30: 78072 | J30: 2023HF01 | K30: 46104 | L30: 23-Mar | M30: 46104 | N30: 23-Mar | O30: BOTRO | P30: SCOOPS BAY SCOOPS | Q30: LBA-014-BAY | R30: 191 | S30: 0 | T30: 5 | V30: 196 | Z30: =SUM(R30:U30) -> 196 | AA30: 18140 | AB30: 20 | AC30: 17944 | AD30: =IF(OR(AE30="",AB30=""),"",AE30-AB30) -> 17924 | AE30: 17944 | AF30: 17944 | AK30: =IF(COUNTA(AH30:AJ30)=0,"",SUM(AH30:AJ30)) | AO30: =IF(COUNTA(AL30:AN30)=0,"",SUM(AL30:AN30)) | AP30: =IF(COUNTA(AL30:AN30)<3,"",(AL30+0.5*(AM30+AN30))*0.17637) | AQ30: =IF(AO30="","",AO30*0.17637) | AR30: =IF(COUNTA(AJ30,AH30,AL30:AN30)=0,"",(AJ30+AH30+AL30+AM30+AN30)*0.17637) | AS30: =IF(AO30="","",AO30/1000) | AT30: =IF(COUNTA(AH30,AJ30,AL30:AN30)=0,"",SUM(AH30,AJ30,AL30:AN30)/1000) | AU30: 10.1 | AV30: 163 | BA30: =IF(COUNTA(AX30:AZ30)=0,"",SUM(AX30:AZ30)) | BE30: =IF(COUNTA(BB30:BD30)=0,"",SUM(BB30:BD30)) | BF30: =IF(COUNTA(BB30:BD30)<3,"",(BB30+0.5*(BC30+BD30))*0.17637) | BG30: =IF(BE30="","",BE30*0.17637) | BH30: =IF(COUNTA(AZ30,AX30,BB30:BD30)=0,"",(AZ30+AX30+BB30+BC30+BD30)*0.17637) | BI30: =IF(BE30="","",BE30/1000) | BJ30: =IF(COUNTA(AX30,AZ30,BB30:BD30)=0,"",SUM(AX30,AZ30,BB30:BD30)/1000) | BK30: 10.1 | BL30: 163
A31: RCV-BKE-2026-0030 | B31: 30 | F31: LOT-BKE-2026-0030 | G31: INSIDE | H31: 654 | I31: 83406 | J31: 285LA01 | K31: 46107 | L31: 26-Mar | M31: 46107 | N31: 26-Mar | O31: VAVOUA | P31: COP JAVA SCOOPS | Q31: LBA-005-JAV | R31: 563 | S31: 0 | T31: 9 | V31: 572 | Z31: =SUM(R31:U31) -> 572 | AA31: 46300 | AB31: 36 | AC31: 45728 | AD31: =IF(OR(AE31="",AB31=""),"",AE31-AB31) -> 45692 | AE31: 45728 | AF31: 45728 | AK31: =IF(COUNTA(AH31:AJ31)=0,"",SUM(AH31:AJ31)) | AO31: =IF(COUNTA(AL31:AN31)=0,"",SUM(AL31:AN31)) | AP31: =IF(COUNTA(AL31:AN31)<3,"",(AL31+0.5*(AM31+AN31))*0.17637) | AQ31: =IF(AO31="","",AO31*0.17637) | AR31: =IF(COUNTA(AJ31,AH31,AL31:AN31)=0,"",(AJ31+AH31+AL31+AM31+AN31)*0.17637) | AS31: =IF(AO31="","",AO31/1000) | AT31: =IF(COUNTA(AH31,AJ31,AL31:AN31)=0,"",SUM(AH31,AJ31,AL31:AN31)/1000) | AU31: 9.6 | AV31: 187 | BA31: =IF(COUNTA(AX31:AZ31)=0,"",SUM(AX31:AZ31)) | BE31: =IF(COUNTA(BB31:BD31)=0,"",SUM(BB31:BD31)) | BF31: =IF(COUNTA(BB31:BD31)<3,"",(BB31+0.5*(BC31+BD31))*0.17637) | BG31: =IF(BE31="","",BE31*0.17637) | BH31: =IF(COUNTA(AZ31,AX31,BB31:BD31)=0,"",(AZ31+AX31+BB31+BC31+BD31)*0.17637) | BI31: =IF(BE31="","",BE31/1000) | BJ31: =IF(COUNTA(AX31,AZ31,BB31:BD31)=0,"",SUM(AX31,AZ31,BB31:BD31)/1000) | BK31: 9.6 | BL31: 187
A32: RCV-BKE-2026-0031 | B32: 31 | C32: BKE-001 | F32: LOT-BKE-2026-0031 | G32: INSIDE | H32: 147 | I32: 88279 | J32: 5012HJ01 | K32: 46107 | L32: 26-Mar | M32: 46107 | N32: 26-Mar | O32: MANKONO | P32: SCOOPS-OUMI/KONE SIDY | Q32: LBA-015-OUM | R32: 536 | S32: 0 | T32: 9 | V32: 545 | Z32: =SUM(R32:U32) -> 545 | AA32: 45480 | AB32: 36 | AC32: 44935 | AD32: =IF(OR(AE32="",AB32=""),"",AE32-AB32) -> 44899 | AE32: 44935 | AF32: 44935 | AK32: =IF(COUNTA(AH32:AJ32)=0,"",SUM(AH32:AJ32)) | AO32: =IF(COUNTA(AL32:AN32)=0,"",SUM(AL32:AN32)) | AP32: =IF(COUNTA(AL32:AN32)<3,"",(AL32+0.5*(AM32+AN32))*0.17637) | AQ32: =IF(AO32="","",AO32*0.17637) | AR32: =IF(COUNTA(AJ32,AH32,AL32:AN32)=0,"",(AJ32+AH32+AL32+AM32+AN32)*0.17637) | AS32: =IF(AO32="","",AO32/1000) | AT32: =IF(COUNTA(AH32,AJ32,AL32:AN32)=0,"",SUM(AH32,AJ32,AL32:AN32)/1000) | AU32: 8.2 | AV32: 178 | BA32: =IF(COUNTA(AX32:AZ32)=0,"",SUM(AX32:AZ32)) | BE32: =IF(COUNTA(BB32:BD32)=0,"",SUM(BB32:BD32)) | BF32: =IF(COUNTA(BB32:BD32)<3,"",(BB32+0.5*(BC32+BD32))*0.17637) | BG32: =IF(BE32="","",BE32*0.17637) | BH32: =IF(COUNTA(AZ32,AX32,BB32:BD32)=0,"",(AZ32+AX32+BB32+BC32+BD32)*0.17637) | BI32: =IF(BE32="","",BE32/1000) | BJ32: =IF(COUNTA(AX32,AZ32,BB32:BD32)=0,"",SUM(AX32,AZ32,BB32:BD32)/1000) | BK32: 8.2 | BL32: 178
A33: RCV-BKE-2026-0032 | B33: 32 | F33: LOT-BKE-2026-0032 | G33: INSIDE | H33: 662 | I33: 82173 | J33: AA562YC04 | K33: 46113 | L33: 01-Apr | M33: 46114 | N33: 02-Apr | O33: DIANRA | P33: SCOOPS DPVICA | Q33: LBA-017-DPV | R33: 470 | S33: 0 | T33: 20 | V33: 490 | Z33: =SUM(R33:U33) -> 490 | AA33: 40440 | AB33: 80 | AC33: 39950 | AD33: =IF(OR(AE33="",AB33=""),"",AE33-AB33) -> 39870 | AE33: 39950 | AF33: 39950 | AK33: =IF(COUNTA(AH33:AJ33)=0,"",SUM(AH33:AJ33)) | AO33: =IF(COUNTA(AL33:AN33)=0,"",SUM(AL33:AN33)) | AP33: =IF(COUNTA(AL33:AN33)<3,"",(AL33+0.5*(AM33+AN33))*0.17637) | AQ33: =IF(AO33="","",AO33*0.17637) | AR33: =IF(COUNTA(AJ33,AH33,AL33:AN33)=0,"",(AJ33+AH33+AL33+AM33+AN33)*0.17637) | AS33: =IF(AO33="","",AO33/1000) | AT33: =IF(COUNTA(AH33,AJ33,AL33:AN33)=0,"",SUM(AH33,AJ33,AL33:AN33)/1000) | AU33: 8.5 | AV33: 168 | BA33: =IF(COUNTA(AX33:AZ33)=0,"",SUM(AX33:AZ33)) | BE33: =IF(COUNTA(BB33:BD33)=0,"",SUM(BB33:BD33)) | BF33: =IF(COUNTA(BB33:BD33)<3,"",(BB33+0.5*(BC33+BD33))*0.17637) | BG33: =IF(BE33="","",BE33*0.17637) | BH33: =IF(COUNTA(AZ33,AX33,BB33:BD33)=0,"",(AZ33+AX33+BB33+BC33+BD33)*0.17637) | BI33: =IF(BE33="","",BE33/1000) | BJ33: =IF(COUNTA(AX33,AZ33,BB33:BD33)=0,"",SUM(AX33,AZ33,BB33:BD33)/1000) | BK33: 8.5 | BL33: 168
A34: RCV-BKE-2026-0033 | B34: 33 | C34: BKE-002 | F34: LOT-BKE-2026-0033 | G34: INSIDE | H34: 1184 | I34: 80522 | J34: AA343VP04 | K34: 46118 | L34: 06-Apr | M34: 46119 | N34: 07-Apr | O34: BOUAKE | P34: CAPCD-SCOOPS | Q34: LBA-010-CAP | R34: 130 | S34: 0 | T34: 19 | V34: 149 | Z34: =SUM(R34:U34) -> 149 | AA34: 12240 | AB34: 76 | AC34: 12091 | AD34: =IF(OR(AE34="",AB34=""),"",AE34-AB34) -> 12015 | AE34: 12091 | AF34: 12091 | AK34: =IF(COUNTA(AH34:AJ34)=0,"",SUM(AH34:AJ34)) | AO34: =IF(COUNTA(AL34:AN34)=0,"",SUM(AL34:AN34)) | AP34: =IF(COUNTA(AL34:AN34)<3,"",(AL34+0.5*(AM34+AN34))*0.17637) | AQ34: =IF(AO34="","",AO34*0.17637) | AR34: =IF(COUNTA(AJ34,AH34,AL34:AN34)=0,"",(AJ34+AH34+AL34+AM34+AN34)*0.17637) | AS34: =IF(AO34="","",AO34/1000) | AT34: =IF(COUNTA(AH34,AJ34,AL34:AN34)=0,"",SUM(AH34,AJ34,AL34:AN34)/1000) | AU34: 11.7 | AV34: 160 | BA34: =IF(COUNTA(AX34:AZ34)=0,"",SUM(AX34:AZ34)) | BE34: =IF(COUNTA(BB34:BD34)=0,"",SUM(BB34:BD34)) | BF34: =IF(COUNTA(BB34:BD34)<3,"",(BB34+0.5*(BC34+BD34))*0.17637) | BG34: =IF(BE34="","",BE34*0.17637) | BH34: =IF(COUNTA(AZ34,AX34,BB34:BD34)=0,"",(AZ34+AX34+BB34+BC34+BD34)*0.17637) | BI34: =IF(BE34="","",BE34/1000) | BJ34: =IF(COUNTA(AX34,AZ34,BB34:BD34)=0,"",SUM(AX34,AZ34,BB34:BD34)/1000) | BK34: 11.7 | BL34: 160
A35: RCV-BKE-2026-0034 | B35: 34 | F35: LOT-BKE-2026-0034 | G35: INSIDE | H35: 675 | I35: 78912 | J35: AA721PZ01 | K35: 46122 | L35: 10-Apr | M35: 46122 | N35: 10-Apr | O35: VAVOUA | P35: SCAAMT COOP CA | Q35: LBA-002-SCA | R35: 612 | S35: 0 | T35: 46 | V35: 658 | Z35: =SUM(R35:U35) -> 658 | AA35: 51020 | AB35: 184 | AC35: 50362 | AD35: =IF(OR(AE35="",AB35=""),"",AE35-AB35) -> 50178 | AE35: 50362 | AF35: 50362 | AK35: =IF(COUNTA(AH35:AJ35)=0,"",SUM(AH35:AJ35)) | AO35: =IF(COUNTA(AL35:AN35)=0,"",SUM(AL35:AN35)) | AP35: =IF(COUNTA(AL35:AN35)<3,"",(AL35+0.5*(AM35+AN35))*0.17637) | AQ35: =IF(AO35="","",AO35*0.17637) | AR35: =IF(COUNTA(AJ35,AH35,AL35:AN35)=0,"",(AJ35+AH35+AL35+AM35+AN35)*0.17637) | AS35: =IF(AO35="","",AO35/1000) | AT35: =IF(COUNTA(AH35,AJ35,AL35:AN35)=0,"",SUM(AH35,AJ35,AL35:AN35)/1000) | AU35: 10.8 | AV35: 189 | BA35: =IF(COUNTA(AX35:AZ35)=0,"",SUM(AX35:AZ35)) | BE35: =IF(COUNTA(BB35:BD35)=0,"",SUM(BB35:BD35)) | BF35: =IF(COUNTA(BB35:BD35)<3,"",(BB35+0.5*(BC35+BD35))*0.17637) | BG35: =IF(BE35="","",BE35*0.17637) | BH35: =IF(COUNTA(AZ35,AX35,BB35:BD35)=0,"",(AZ35+AX35+BB35+BC35+BD35)*0.17637) | BI35: =IF(BE35="","",BE35/1000) | BJ35: =IF(COUNTA(AX35,AZ35,BB35:BD35)=0,"",SUM(AX35,AZ35,BB35:BD35)/1000) | BK35: 10.8 | BL35: 189
A36: RCV-BKE-2026-0035 | B36: 35 | F36: LOT-BKE-2026-0035 | G36: INSIDE | H36: 679 | I36: 37970 | J36: 8454CF04 | K36: 46122 | L36: 10-Apr | M36: 46122 | N36: 10-Apr | O36: MANKONO | P36: SANOGO SINDOU | Q36: LBA-021-SAN | R36: 464 | S36: 0 | T36: 24 | V36: 488 | Z36: =SUM(R36:U36) -> 488 | AA36: 42110 | AB36: 96 | AC36: 41622 | AD36: =IF(OR(AE36="",AB36=""),"",AE36-AB36) -> 41526 | AE36: 41622 | AF36: 41622 | AK36: =IF(COUNTA(AH36:AJ36)=0,"",SUM(AH36:AJ36)) | AO36: =IF(COUNTA(AL36:AN36)=0,"",SUM(AL36:AN36)) | AP36: =IF(COUNTA(AL36:AN36)<3,"",(AL36+0.5*(AM36+AN36))*0.17637) | AQ36: =IF(AO36="","",AO36*0.17637) | AR36: =IF(COUNTA(AJ36,AH36,AL36:AN36)=0,"",(AJ36+AH36+AL36+AM36+AN36)*0.17637) | AS36: =IF(AO36="","",AO36/1000) | AT36: =IF(COUNTA(AH36,AJ36,AL36:AN36)=0,"",SUM(AH36,AJ36,AL36:AN36)/1000) | AU36: 13.7 | AV36: 166 | BA36: =IF(COUNTA(AX36:AZ36)=0,"",SUM(AX36:AZ36)) | BE36: =IF(COUNTA(BB36:BD36)=0,"",SUM(BB36:BD36)) | BF36: =IF(COUNTA(BB36:BD36)<3,"",(BB36+0.5*(BC36+BD36))*0.17637) | BG36: =IF(BE36="","",BE36*0.17637) | BH36: =IF(COUNTA(AZ36,AX36,BB36:BD36)=0,"",(AZ36+AX36+BB36+BC36+BD36)*0.17637) | BI36: =IF(BE36="","",BE36/1000) | BJ36: =IF(COUNTA(AX36,AZ36,BB36:BD36)=0,"",SUM(AX36,AZ36,BB36:BD36)/1000) | BK36: 13.7 | BL36: 166
A37: RCV-BKE-2026-0036 | B37: 36 | C37: BKE-001 | F37: LOT-BKE-2026-0036 | G37: INSIDE | H37: 1109 | I37: 18448 | J37: 953LU01 | K37: 46122 | L37: 10-Apr | M37: 46123 | N37: 11-Apr | O37: NIAKARA | P37: SCOOPS AH AL NOUR | Q37: LBA-016-NOU | R37: 427 | S37: 19 | T37: 0 | V37: 446 | Z37: =SUM(R37:U37) -> 446 | AA37: 41680 | AB37: 152 | AC37: 41234 | AD37: =IF(OR(AE37="",AB37=""),"",AE37-AB37) -> 41082 | AE37: 41234 | AF37: 41234 | AK37: =IF(COUNTA(AH37:AJ37)=0,"",SUM(AH37:AJ37)) | AO37: =IF(COUNTA(AL37:AN37)=0,"",SUM(AL37:AN37)) | AP37: =IF(COUNTA(AL37:AN37)<3,"",(AL37+0.5*(AM37+AN37))*0.17637) | AQ37: =IF(AO37="","",AO37*0.17637) | AR37: =IF(COUNTA(AJ37,AH37,AL37:AN37)=0,"",(AJ37+AH37+AL37+AM37+AN37)*0.17637) | AS37: =IF(AO37="","",AO37/1000) | AT37: =IF(COUNTA(AH37,AJ37,AL37:AN37)=0,"",SUM(AH37,AJ37,AL37:AN37)/1000) | AU37: 12.1 | AV37: 159 | BA37: =IF(COUNTA(AX37:AZ37)=0,"",SUM(AX37:AZ37)) | BE37: =IF(COUNTA(BB37:BD37)=0,"",SUM(BB37:BD37)) | BF37: =IF(COUNTA(BB37:BD37)<3,"",(BB37+0.5*(BC37+BD37))*0.17637) | BG37: =IF(BE37="","",BE37*0.17637) | BH37: =IF(COUNTA(AZ37,AX37,BB37:BD37)=0,"",(AZ37+AX37+BB37+BC37+BD37)*0.17637) | BI37: =IF(BE37="","",BE37/1000) | BJ37: =IF(COUNTA(AX37,AZ37,BB37:BD37)=0,"",SUM(AX37,AZ37,BB37:BD37)/1000) | BK37: 12.1 | BL37: 159
A38: RCV-BKE-2026-0037 | B38: 37 | C38: BKE-002 | F38: LOT-BKE-2026-0037 | G38: INSIDE | H38: 1144 | I38: 19865 | J38: 4669CP03 | K38: 46128 | L38: 16-Apr | M38: 46128 | N38: 16-Apr | O38: KATIOLA | P38: SCOOPS COOPRAKA | Q38: LBA-018-COP | R38: 451 | S38: 0 | T38: 17 | V38: 468 | Z38: =SUM(R38:U38) -> 468 | AA38: 39680 | AB38: 68 | AC38: 39212 | AD38: =IF(OR(AE38="",AB38=""),"",AE38-AB38) -> 39144 | AE38: 39212 | AF38: 39212 | AK38: =IF(COUNTA(AH38:AJ38)=0,"",SUM(AH38:AJ38)) | AO38: =IF(COUNTA(AL38:AN38)=0,"",SUM(AL38:AN38)) | AP38: =IF(COUNTA(AL38:AN38)<3,"",(AL38+0.5*(AM38+AN38))*0.17637) | AQ38: =IF(AO38="","",AO38*0.17637) | AR38: =IF(COUNTA(AJ38,AH38,AL38:AN38)=0,"",(AJ38+AH38+AL38+AM38+AN38)*0.17637) | AS38: =IF(AO38="","",AO38/1000) | AT38: =IF(COUNTA(AH38,AJ38,AL38:AN38)=0,"",SUM(AH38,AJ38,AL38:AN38)/1000) | AU38: 9.4 | AV38: 160 | BA38: =IF(COUNTA(AX38:AZ38)=0,"",SUM(AX38:AZ38)) | BE38: =IF(COUNTA(BB38:BD38)=0,"",SUM(BB38:BD38)) | BF38: =IF(COUNTA(BB38:BD38)<3,"",(BB38+0.5*(BC38+BD38))*0.17637) | BG38: =IF(BE38="","",BE38*0.17637) | BH38: =IF(COUNTA(AZ38,AX38,BB38:BD38)=0,"",(AZ38+AX38+BB38+BC38+BD38)*0.17637) | BI38: =IF(BE38="","",BE38/1000) | BJ38: =IF(COUNTA(AX38,AZ38,BB38:BD38)=0,"",SUM(AX38,AZ38,BB38:BD38)/1000) | BK38: 9.4 | BL38: 160
A39: RCV-BKE-2026-0038 | B39: 38 | C39: BKE-002 | D39: BKE-002-BIN-031 | F39: LOT-BKE-2026-0038 | G39: INSIDE | H39: 263 | I39: 87092 | J39: 6305EP01 | K39: 46130 | L39: 18-Apr | M39: 46131 | N39: 19-Apr | O39: KOUASSI | P39: CAPCD-SCOOPS | Q39: LBA-010-CAP | R39: 336 | S39: 0 | T39: 11 | V39: 347 | Z39: =SUM(R39:U39) -> 347 | AA39: 25360 | AB39: 44 | AC39: 25013 | AD39: =IF(OR(AE39="",AB39=""),"",AE39-AB39) -> 24969 | AE39: 25013 | AF39: 25013 | AK39: =IF(COUNTA(AH39:AJ39)=0,"",SUM(AH39:AJ39)) | AO39: =IF(COUNTA(AL39:AN39)=0,"",SUM(AL39:AN39)) | AP39: =IF(COUNTA(AL39:AN39)<3,"",(AL39+0.5*(AM39+AN39))*0.17637) | AQ39: =IF(AO39="","",AO39*0.17637) | AR39: =IF(COUNTA(AJ39,AH39,AL39:AN39)=0,"",(AJ39+AH39+AL39+AM39+AN39)*0.17637) | AS39: =IF(AO39="","",AO39/1000) | AT39: =IF(COUNTA(AH39,AJ39,AL39:AN39)=0,"",SUM(AH39,AJ39,AL39:AN39)/1000) | AU39: 9.7 | AV39: 160 | BA39: =IF(COUNTA(AX39:AZ39)=0,"",SUM(AX39:AZ39)) | BE39: =IF(COUNTA(BB39:BD39)=0,"",SUM(BB39:BD39)) | BF39: =IF(COUNTA(BB39:BD39)<3,"",(BB39+0.5*(BC39+BD39))*0.17637) | BG39: =IF(BE39="","",BE39*0.17637) | BH39: =IF(COUNTA(AZ39,AX39,BB39:BD39)=0,"",(AZ39+AX39+BB39+BC39+BD39)*0.17637) | BI39: =IF(BE39="","",BE39/1000) | BJ39: =IF(COUNTA(AX39,AZ39,BB39:BD39)=0,"",SUM(AX39,AZ39,BB39:BD39)/1000) | BK39: 9.7 | BL39: 160
A40: RCV-BKE-2026-0039 | B40: 39 | C40: BKE-002 | F40: LOT-BKE-2026-0039 | G40: INSIDE | H40: 286 | I40: 67796 | J40: 4852HV03 | K40: 46133 | L40: 21-Apr | M40: 46134 | N40: 22-Apr | O40: DIANRA | P40: SCOOP-CA/COBAN | Q40: LBA-008-COB | R40: 451 | S40: 0 | T40: 13 | V40: 464 | Z40: =SUM(R40:U40) -> 464 | AA40: 41660 | AB40: 52 | AC40: 41196 | AD40: =IF(OR(AE40="",AB40=""),"",AE40-AB40) -> 41144 | AE40: 41196 | AF40: 41196 | AK40: =IF(COUNTA(AH40:AJ40)=0,"",SUM(AH40:AJ40)) | AO40: =IF(COUNTA(AL40:AN40)=0,"",SUM(AL40:AN40)) | AP40: =IF(COUNTA(AL40:AN40)<3,"",(AL40+0.5*(AM40+AN40))*0.17637) | AQ40: =IF(AO40="","",AO40*0.17637) | AR40: =IF(COUNTA(AJ40,AH40,AL40:AN40)=0,"",(AJ40+AH40+AL40+AM40+AN40)*0.17637) | AS40: =IF(AO40="","",AO40/1000) | AT40: =IF(COUNTA(AH40,AJ40,AL40:AN40)=0,"",SUM(AH40,AJ40,AL40:AN40)/1000) | AU40: 9.2 | AV40: 159 | BA40: =IF(COUNTA(AX40:AZ40)=0,"",SUM(AX40:AZ40)) | BE40: =IF(COUNTA(BB40:BD40)=0,"",SUM(BB40:BD40)) | BF40: =IF(COUNTA(BB40:BD40)<3,"",(BB40+0.5*(BC40+BD40))*0.17637) | BG40: =IF(BE40="","",BE40*0.17637) | BH40: =IF(COUNTA(AZ40,AX40,BB40:BD40)=0,"",(AZ40+AX40+BB40+BC40+BD40)*0.17637) | BI40: =IF(BE40="","",BE40/1000) | BJ40: =IF(COUNTA(AX40,AZ40,BB40:BD40)=0,"",SUM(AX40,AZ40,BB40:BD40)/1000) | BK40: 9.2 | BL40: 159
A41: RCV-BKE-2026-0040 | B41: 40 | C41: BKE-002 | D41: BKE-002-BIN-031 | F41: LOT-BKE-2026-0040 | G41: INSIDE | H41: 285 | I41: 19859 | J41: AA245YN03 | K41: 46134 | L41: 22-Apr | M41: 46134 | N41: 22-Apr | O41: KORHOGO | P41: SCOOPS COOPRAKA | Q41: LBA-018-COP | R41: 449 | S41: 0 | T41: 12 | V41: 461 | Z41: =SUM(R41:U41) -> 461 | AA41: 39560 | AB41: 48 | AC41: 39099 | AD41: =IF(OR(AE41="",AB41=""),"",AE41-AB41) -> 39051 | AE41: 39099 | AF41: 39099 | AK41: =IF(COUNTA(AH41:AJ41)=0,"",SUM(AH41:AJ41)) | AO41: =IF(COUNTA(AL41:AN41)=0,"",SUM(AL41:AN41)) | AP41: =IF(COUNTA(AL41:AN41)<3,"",(AL41+0.5*(AM41+AN41))*0.17637) | AQ41: =IF(AO41="","",AO41*0.17637) | AR41: =IF(COUNTA(AJ41,AH41,AL41:AN41)=0,"",(AJ41+AH41+AL41+AM41+AN41)*0.17637) | AS41: =IF(AO41="","",AO41/1000) | AT41: =IF(COUNTA(AH41,AJ41,AL41:AN41)=0,"",SUM(AH41,AJ41,AL41:AN41)/1000) | AU41: 9.1 | AV41: 168 | BA41: =IF(COUNTA(AX41:AZ41)=0,"",SUM(AX41:AZ41)) | BE41: =IF(COUNTA(BB41:BD41)=0,"",SUM(BB41:BD41)) | BF41: =IF(COUNTA(BB41:BD41)<3,"",(BB41+0.5*(BC41+BD41))*0.17637) | BG41: =IF(BE41="","",BE41*0.17637) | BH41: =IF(COUNTA(AZ41,AX41,BB41:BD41)=0,"",(AZ41+AX41+BB41+BC41+BD41)*0.17637) | BI41: =IF(BE41="","",BE41/1000) | BJ41: =IF(COUNTA(AX41,AZ41,BB41:BD41)=0,"",SUM(AX41,AZ41,BB41:BD41)/1000) | BK41: 9.1 | BL41: 168
A42: RCV-BKE-2026-0041 | B42: 41 | C42: BKE-001 | F42: LOT-BKE-2026-0041 | G42: INSIDE | H42: 289 | I42: 38397 | J42: AA231VP04 | K42: 46134 | L42: 22-Apr | M42: 46135 | N42: 23-Apr | O42: MANKONO | P42: CASP-S SCOOPS | Q42: LBA-007-CAS | R42: 446 | S42: 25 | T42: 0 | V42: 471 | Z42: =SUM(R42:U42) -> 471 | AA42: 41220 | AB42: 200 | AC42: 40749 | AD42: =IF(OR(AE42="",AB42=""),"",AE42-AB42) -> 40549 | AE42: 40749 | AF42: 40749 | AK42: =IF(COUNTA(AH42:AJ42)=0,"",SUM(AH42:AJ42)) | AO42: =IF(COUNTA(AL42:AN42)=0,"",SUM(AL42:AN42)) | AP42: =IF(COUNTA(AL42:AN42)<3,"",(AL42+0.5*(AM42+AN42))*0.17637) | AQ42: =IF(AO42="","",AO42*0.17637) | AR42: =IF(COUNTA(AJ42,AH42,AL42:AN42)=0,"",(AJ42+AH42+AL42+AM42+AN42)*0.17637) | AS42: =IF(AO42="","",AO42/1000) | AT42: =IF(COUNTA(AH42,AJ42,AL42:AN42)=0,"",SUM(AH42,AJ42,AL42:AN42)/1000) | AU42: 11.9 | AV42: 166 | BA42: =IF(COUNTA(AX42:AZ42)=0,"",SUM(AX42:AZ42)) | BE42: =IF(COUNTA(BB42:BD42)=0,"",SUM(BB42:BD42)) | BF42: =IF(COUNTA(BB42:BD42)<3,"",(BB42+0.5*(BC42+BD42))*0.17637) | BG42: =IF(BE42="","",BE42*0.17637) | BH42: =IF(COUNTA(AZ42,AX42,BB42:BD42)=0,"",(AZ42+AX42+BB42+BC42+BD42)*0.17637) | BI42: =IF(BE42="","",BE42/1000) | BJ42: =IF(COUNTA(AX42,AZ42,BB42:BD42)=0,"",SUM(AX42,AZ42,BB42:BD42)/1000) | BK42: 11.9 | BL42: 166
A43: RCV-BKE-2026-0042 | B43: 42 | C43: BKE-001 | F43: LOT-BKE-2026-0042 | G43: INSIDE | H43: 296 | I43: 31708 | J43: 2563GY01 | K43: 46135 | L43: 23-Apr | M43: 46136 | N43: 24-Apr | O43: DABAKALA | P43: SCOPPAS SCOOPS | Q43: LBA-009-SCO | R43: 490 | S43: 20 | T43: 0 | V43: 510 | Z43: =SUM(R43:U43) -> 510 | AA43: 40400 | AB43: 160 | AC43: 39890 | AD43: =IF(OR(AE43="",AB43=""),"",AE43-AB43) -> 39730 | AE43: 39890 | AF43: 39890 | AK43: =IF(COUNTA(AH43:AJ43)=0,"",SUM(AH43:AJ43)) | AO43: =IF(COUNTA(AL43:AN43)=0,"",SUM(AL43:AN43)) | AP43: =IF(COUNTA(AL43:AN43)<3,"",(AL43+0.5*(AM43+AN43))*0.17637) | AQ43: =IF(AO43="","",AO43*0.17637) | AR43: =IF(COUNTA(AJ43,AH43,AL43:AN43)=0,"",(AJ43+AH43+AL43+AM43+AN43)*0.17637) | AS43: =IF(AO43="","",AO43/1000) | AT43: =IF(COUNTA(AH43,AJ43,AL43:AN43)=0,"",SUM(AH43,AJ43,AL43:AN43)/1000) | AU43: 11.7 | AV43: 184 | BA43: =IF(COUNTA(AX43:AZ43)=0,"",SUM(AX43:AZ43)) | BE43: =IF(COUNTA(BB43:BD43)=0,"",SUM(BB43:BD43)) | BF43: =IF(COUNTA(BB43:BD43)<3,"",(BB43+0.5*(BC43+BD43))*0.17637) | BG43: =IF(BE43="","",BE43*0.17637) | BH43: =IF(COUNTA(AZ43,AX43,BB43:BD43)=0,"",(AZ43+AX43+BB43+BC43+BD43)*0.17637) | BI43: =IF(BE43="","",BE43/1000) | BJ43: =IF(COUNTA(AX43,AZ43,BB43:BD43)=0,"",SUM(AX43,AZ43,BB43:BD43)/1000) | BK43: 11.7 | BL43: 184
A44: RCV-BKE-2026-0043 | B44: 43 | C44: BKE-001 | F44: LOT-BKE-2026-0043 | G44: INSIDE | H44: 356 | I44: 18679 | J44: 7242JS01 | K44: 46136 | L44: 24-Apr | M44: 46137 | N44: 25-Apr | O44: NIAKARA | P44: DAGNOGO KARIM | Q44: LBA-013-DAG | R44: 515 | S44: 20 | T44: 0 | V44: 535 | Z44: =SUM(R44:U44) -> 535 | AA44: 46840 | AB44: 160 | AC44: 46305 | AD44: =IF(OR(AE44="",AB44=""),"",AE44-AB44) -> 46145 | AE44: 46305 | AF44: 46305 | AK44: =IF(COUNTA(AH44:AJ44)=0,"",SUM(AH44:AJ44)) | AO44: =IF(COUNTA(AL44:AN44)=0,"",SUM(AL44:AN44)) | AP44: =IF(COUNTA(AL44:AN44)<3,"",(AL44+0.5*(AM44+AN44))*0.17637) | AQ44: =IF(AO44="","",AO44*0.17637) | AR44: =IF(COUNTA(AJ44,AH44,AL44:AN44)=0,"",(AJ44+AH44+AL44+AM44+AN44)*0.17637) | AS44: =IF(AO44="","",AO44/1000) | AT44: =IF(COUNTA(AH44,AJ44,AL44:AN44)=0,"",SUM(AH44,AJ44,AL44:AN44)/1000) | AU44: 11 | AV44: 160 | BA44: =IF(COUNTA(AX44:AZ44)=0,"",SUM(AX44:AZ44)) | BE44: =IF(COUNTA(BB44:BD44)=0,"",SUM(BB44:BD44)) | BF44: =IF(COUNTA(BB44:BD44)<3,"",(BB44+0.5*(BC44+BD44))*0.17637) | BG44: =IF(BE44="","",BE44*0.17637) | BH44: =IF(COUNTA(AZ44,AX44,BB44:BD44)=0,"",(AZ44+AX44+BB44+BC44+BD44)*0.17637) | BI44: =IF(BE44="","",BE44/1000) | BJ44: =IF(COUNTA(AX44,AZ44,BB44:BD44)=0,"",SUM(AX44,AZ44,BB44:BD44)/1000) | BK44: 11 | BL44: 160
A45: RCV-BKE-2026-0044 | B45: 44 | F45: LOT-BKE-2026-0044 | G45: INSIDE | H45: 722 | I45: 32358 | J45: 9970HE07 | K45: 46136 | L45: 24-Apr | M45: 46137 | N45: 25-Apr | O45: BROBO | P45: SANOGO SINDOU | Q45: LBA-021-SAN | R45: 503 | S45: 30 | T45: 0 | V45: 533 | Z45: =SUM(R45:U45) -> 533 | AA45: 46090 | AB45: 240 | AC45: 45557 | AD45: =IF(OR(AE45="",AB45=""),"",AE45-AB45) -> 45317 | AE45: 45557 | AF45: 45557 | AK45: =IF(COUNTA(AH45:AJ45)=0,"",SUM(AH45:AJ45)) | AO45: =IF(COUNTA(AL45:AN45)=0,"",SUM(AL45:AN45)) | AP45: =IF(COUNTA(AL45:AN45)<3,"",(AL45+0.5*(AM45+AN45))*0.17637) | AQ45: =IF(AO45="","",AO45*0.17637) | AR45: =IF(COUNTA(AJ45,AH45,AL45:AN45)=0,"",(AJ45+AH45+AL45+AM45+AN45)*0.17637) | AS45: =IF(AO45="","",AO45/1000) | AT45: =IF(COUNTA(AH45,AJ45,AL45:AN45)=0,"",SUM(AH45,AJ45,AL45:AN45)/1000) | AU45: 14.2 | AV45: 160 | BA45: =IF(COUNTA(AX45:AZ45)=0,"",SUM(AX45:AZ45)) | BE45: =IF(COUNTA(BB45:BD45)=0,"",SUM(BB45:BD45)) | BF45: =IF(COUNTA(BB45:BD45)<3,"",(BB45+0.5*(BC45+BD45))*0.17637) | BG45: =IF(BE45="","",BE45*0.17637) | BH45: =IF(COUNTA(AZ45,AX45,BB45:BD45)=0,"",(AZ45+AX45+BB45+BC45+BD45)*0.17637) | BI45: =IF(BE45="","",BE45/1000) | BJ45: =IF(COUNTA(AX45,AZ45,BB45:BD45)=0,"",SUM(AX45,AZ45,BB45:BD45)/1000) | BK45: 14.2 | BL45: 160
A46: RCV-BKE-2026-0045 | B46: 45 | C46: BKE-001 | F46: LOT-BKE-2026-0045 | G46: INSIDE | H46: 386 | I46: 18615 | J46: 9900KU03 | K46: 46144 | L46: 02-May | M46: 46144 | N46: 02-May | O46: NIAKARA | P46: SCOOPS HERE B | Q46: LBA-003-HER | R46: 511 | S46: 35 | T46: 0 | V46: 546 | Z46: =SUM(R46:U46) -> 546 | AA46: 45740 | AB46: 280 | AC46: 45194 | AD46: =IF(OR(AE46="",AB46=""),"",AE46-AB46) -> 44914 | AE46: 45194 | AF46: 45194 | AK46: =IF(COUNTA(AH46:AJ46)=0,"",SUM(AH46:AJ46)) | AO46: =IF(COUNTA(AL46:AN46)=0,"",SUM(AL46:AN46)) | AP46: =IF(COUNTA(AL46:AN46)<3,"",(AL46+0.5*(AM46+AN46))*0.17637) | AQ46: =IF(AO46="","",AO46*0.17637) | AR46: =IF(COUNTA(AJ46,AH46,AL46:AN46)=0,"",(AJ46+AH46+AL46+AM46+AN46)*0.17637) | AS46: =IF(AO46="","",AO46/1000) | AT46: =IF(COUNTA(AH46,AJ46,AL46:AN46)=0,"",SUM(AH46,AJ46,AL46:AN46)/1000) | AU46: 11.4 | AV46: 169 | BA46: =IF(COUNTA(AX46:AZ46)=0,"",SUM(AX46:AZ46)) | BE46: =IF(COUNTA(BB46:BD46)=0,"",SUM(BB46:BD46)) | BF46: =IF(COUNTA(BB46:BD46)<3,"",(BB46+0.5*(BC46+BD46))*0.17637) | BG46: =IF(BE46="","",BE46*0.17637) | BH46: =IF(COUNTA(AZ46,AX46,BB46:BD46)=0,"",(AZ46+AX46+BB46+BC46+BD46)*0.17637) | BI46: =IF(BE46="","",BE46/1000) | BJ46: =IF(COUNTA(AX46,AZ46,BB46:BD46)=0,"",SUM(AX46,AZ46,BB46:BD46)/1000) | BK46: 11.4 | BL46: 169
A47: RCV-BKE-2026-0046 | B47: 46 | F47: LOT-BKE-2026-0046 | G47: INSIDE | H47: 418 | I47: 87106 | J47: 2596FZ03 | K47: 46144 | L47: 02-May | M47: 46145 | N47: 03-May | O47: VAVOUA | P47: COP JAVA SCOOPS | Q47: LBA-005-JAV | R47: 623 | S47: 20 | T47: 0 | V47: 643 | Z47: =SUM(R47:U47) -> 643 | AA47: 53020 | AB47: 160 | AC47: 52377 | AD47: =IF(OR(AE47="",AB47=""),"",AE47-AB47) -> 52217 | AE47: 52377 | AF47: 52377 | AK47: =IF(COUNTA(AH47:AJ47)=0,"",SUM(AH47:AJ47)) | AO47: =IF(COUNTA(AL47:AN47)=0,"",SUM(AL47:AN47)) | AP47: =IF(COUNTA(AL47:AN47)<3,"",(AL47+0.5*(AM47+AN47))*0.17637) | AQ47: =IF(AO47="","",AO47*0.17637) | AR47: =IF(COUNTA(AJ47,AH47,AL47:AN47)=0,"",(AJ47+AH47+AL47+AM47+AN47)*0.17637) | AS47: =IF(AO47="","",AO47/1000) | AT47: =IF(COUNTA(AH47,AJ47,AL47:AN47)=0,"",SUM(AH47,AJ47,AL47:AN47)/1000) | AU47: 10.6 | AV47: 176 | BA47: =IF(COUNTA(AX47:AZ47)=0,"",SUM(AX47:AZ47)) | BE47: =IF(COUNTA(BB47:BD47)=0,"",SUM(BB47:BD47)) | BF47: =IF(COUNTA(BB47:BD47)<3,"",(BB47+0.5*(BC47+BD47))*0.17637) | BG47: =IF(BE47="","",BE47*0.17637) | BH47: =IF(COUNTA(AZ47,AX47,BB47:BD47)=0,"",(AZ47+AX47+BB47+BC47+BD47)*0.17637) | BI47: =IF(BE47="","",BE47/1000) | BJ47: =IF(COUNTA(AX47,AZ47,BB47:BD47)=0,"",SUM(AX47,AZ47,BB47:BD47)/1000) | BK47: 10.6 | BL47: 176
A48: RCV-BKE-2026-0047 | B48: 47 | F48: LOT-BKE-2026-0047 | G48: INSIDE | H48: 425 | I48: 37590 | J48: AA141VT01 | K48: 46144 | L48: 02-May | M48: 46147 | N48: 05-May | O48: DIANRA | P48: SCOOPS DPVICA | Q48: LBA-017-DPV | R48: 445 | S48: 40 | T48: 0 | V48: 485 | Z48: =SUM(R48:U48) -> 485 | AA48: 45610 | AB48: 320 | AC48: 45125 | AD48: =IF(OR(AE48="",AB48=""),"",AE48-AB48) -> 44805 | AE48: 45125 | AF48: 45125 | AK48: =IF(COUNTA(AH48:AJ48)=0,"",SUM(AH48:AJ48)) | AO48: =IF(COUNTA(AL48:AN48)=0,"",SUM(AL48:AN48)) | AP48: =IF(COUNTA(AL48:AN48)<3,"",(AL48+0.5*(AM48+AN48))*0.17637) | AQ48: =IF(AO48="","",AO48*0.17637) | AR48: =IF(COUNTA(AJ48,AH48,AL48:AN48)=0,"",(AJ48+AH48+AL48+AM48+AN48)*0.17637) | AS48: =IF(AO48="","",AO48/1000) | AT48: =IF(COUNTA(AH48,AJ48,AL48:AN48)=0,"",SUM(AH48,AJ48,AL48:AN48)/1000) | AU48: 12.7 | AV48: 162 | BA48: =IF(COUNTA(AX48:AZ48)=0,"",SUM(AX48:AZ48)) | BE48: =IF(COUNTA(BB48:BD48)=0,"",SUM(BB48:BD48)) | BF48: =IF(COUNTA(BB48:BD48)<3,"",(BB48+0.5*(BC48+BD48))*0.17637) | BG48: =IF(BE48="","",BE48*0.17637) | BH48: =IF(COUNTA(AZ48,AX48,BB48:BD48)=0,"",(AZ48+AX48+BB48+BC48+BD48)*0.17637) | BI48: =IF(BE48="","",BE48/1000) | BJ48: =IF(COUNTA(AX48,AZ48,BB48:BD48)=0,"",SUM(AX48,AZ48,BB48:BD48)/1000) | BK48: 12.7 | BL48: 162
A49: RCV-BKE-2026-0048 | B49: 48 | C49: BKE-001 | F49: LOT-BKE-2026-0048 | G49: INSIDE | H49: 398 | I49: 87046 | J49: 9640GEE04 | K49: 46145 | L49: 03-May | M49: 46146 | N49: 04-May | O49: BOUAKE | P49: CAPCD-SCOOPS | Q49: LBA-010-CAP | R49: 469 | S49: 0 | T49: 13 | V49: 482 | Z49: =SUM(R49:U49) -> 482 | AA49: 40900 | AB49: 52 | AC49: 40418 | AD49: =IF(OR(AE49="",AB49=""),"",AE49-AB49) -> 40366 | AE49: 40418 | AF49: 40418 | AK49: =IF(COUNTA(AH49:AJ49)=0,"",SUM(AH49:AJ49)) | AO49: =IF(COUNTA(AL49:AN49)=0,"",SUM(AL49:AN49)) | AP49: =IF(COUNTA(AL49:AN49)<3,"",(AL49+0.5*(AM49+AN49))*0.17637) | AQ49: =IF(AO49="","",AO49*0.17637) | AR49: =IF(COUNTA(AJ49,AH49,AL49:AN49)=0,"",(AJ49+AH49+AL49+AM49+AN49)*0.17637) | AS49: =IF(AO49="","",AO49/1000) | AT49: =IF(COUNTA(AH49,AJ49,AL49:AN49)=0,"",SUM(AH49,AJ49,AL49:AN49)/1000) | AU49: 9.3 | AV49: 158 | BA49: =IF(COUNTA(AX49:AZ49)=0,"",SUM(AX49:AZ49)) | BE49: =IF(COUNTA(BB49:BD49)=0,"",SUM(BB49:BD49)) | BF49: =IF(COUNTA(BB49:BD49)<3,"",(BB49+0.5*(BC49+BD49))*0.17637) | BG49: =IF(BE49="","",BE49*0.17637) | BH49: =IF(COUNTA(AZ49,AX49,BB49:BD49)=0,"",(AZ49+AX49+BB49+BC49+BD49)*0.17637) | BI49: =IF(BE49="","",BE49/1000) | BJ49: =IF(COUNTA(AX49,AZ49,BB49:BD49)=0,"",SUM(AX49,AZ49,BB49:BD49)/1000) | BK49: 9.3 | BL49: 158
A50: RCV-BKE-2026-0049 | B50: 49 | C50: BKE-001 | F50: LOT-BKE-2026-0049 | G50: INSIDE | H50: 397 | I50: 32757 | J50: 2318JK01 | K50: 46145 | L50: 03-May | M50: 46146 | N50: 04-May | O50: BOTRO | P50: SCOOPS KPESSO | Q50: LBA-012-KPE | R50: 476 | S50: 0 | T50: 12 | V50: 488 | Z50: =SUM(R50:U50) -> 488 | AA50: 41020 | AB50: 48 | AC50: 40532 | AD50: =IF(OR(AE50="",AB50=""),"",AE50-AB50) -> 40484 | AE50: 40532 | AF50: 40532 | AK50: =IF(COUNTA(AH50:AJ50)=0,"",SUM(AH50:AJ50)) | AO50: =IF(COUNTA(AL50:AN50)=0,"",SUM(AL50:AN50)) | AP50: =IF(COUNTA(AL50:AN50)<3,"",(AL50+0.5*(AM50+AN50))*0.17637) | AQ50: =IF(AO50="","",AO50*0.17637) | AR50: =IF(COUNTA(AJ50,AH50,AL50:AN50)=0,"",(AJ50+AH50+AL50+AM50+AN50)*0.17637) | AS50: =IF(AO50="","",AO50/1000) | AT50: =IF(COUNTA(AH50,AJ50,AL50:AN50)=0,"",SUM(AH50,AJ50,AL50:AN50)/1000) | AU50: 9.8 | AV50: 158 | BA50: =IF(COUNTA(AX50:AZ50)=0,"",SUM(AX50:AZ50)) | BE50: =IF(COUNTA(BB50:BD50)=0,"",SUM(BB50:BD50)) | BF50: =IF(COUNTA(BB50:BD50)<3,"",(BB50+0.5*(BC50+BD50))*0.17637) | BG50: =IF(BE50="","",BE50*0.17637) | BH50: =IF(COUNTA(AZ50,AX50,BB50:BD50)=0,"",(AZ50+AX50+BB50+BC50+BD50)*0.17637) | BI50: =IF(BE50="","",BE50/1000) | BJ50: =IF(COUNTA(AX50,AZ50,BB50:BD50)=0,"",SUM(AX50,AZ50,BB50:BD50)/1000) | BK50: 9.8 | BL50: 158
A51: RCV-BKE-2026-0050 | B51: 50 | C51: BKE-001 | F51: LOT-BKE-2026-0050 | G51: INSIDE | H51: 301 | I51: 32834 | J51: 2023HF01 | K51: 46146 | L51: 04-May | M51: 46146 | N51: 04-May | O51: BEOUMI | P51: SCOOPS BAY SCOOPS | Q51: LBA-014-BAY | R51: 147 | S51: 0 | T51: 8 | V51: 155 | Z51: =SUM(R51:U51) -> 155 | AA51: 13180 | AB51: 32 | AC51: 13025 | AD51: =IF(OR(AE51="",AB51=""),"",AE51-AB51) -> 12993 | AE51: 13025 | AF51: 13025 | AK51: =IF(COUNTA(AH51:AJ51)=0,"",SUM(AH51:AJ51)) | AO51: =IF(COUNTA(AL51:AN51)=0,"",SUM(AL51:AN51)) | AP51: =IF(COUNTA(AL51:AN51)<3,"",(AL51+0.5*(AM51+AN51))*0.17637) | AQ51: =IF(AO51="","",AO51*0.17637) | AR51: =IF(COUNTA(AJ51,AH51,AL51:AN51)=0,"",(AJ51+AH51+AL51+AM51+AN51)*0.17637) | AS51: =IF(AO51="","",AO51/1000) | AT51: =IF(COUNTA(AH51,AJ51,AL51:AN51)=0,"",SUM(AH51,AJ51,AL51:AN51)/1000) | AU51: 10.4 | AV51: 157 | BA51: =IF(COUNTA(AX51:AZ51)=0,"",SUM(AX51:AZ51)) | BE51: =IF(COUNTA(BB51:BD51)=0,"",SUM(BB51:BD51)) | BF51: =IF(COUNTA(BB51:BD51)<3,"",(BB51+0.5*(BC51+BD51))*0.17637) | BG51: =IF(BE51="","",BE51*0.17637) | BH51: =IF(COUNTA(AZ51,AX51,BB51:BD51)=0,"",(AZ51+AX51+BB51+BC51+BD51)*0.17637) | BI51: =IF(BE51="","",BE51/1000) | BJ51: =IF(COUNTA(AX51,AZ51,BB51:BD51)=0,"",SUM(AX51,AZ51,BB51:BD51)/1000) | BK51: 10.4 | BL51: 157
A52: RCV-BKE-2026-0051 | B52: 51 | C52: BKE-001 | F52: LOT-BKE-2026-0051 | G52: INSIDE | H52: 302 | I52: 18794 | J52: 2766HC01 | K52: 46146 | L52: 04-May | M52: 46146 | N52: 04-May | O52: KATIOLA | P52: SCOOPS COOPRAKA | Q52: LBA-018-COP | R52: 463 | S52: 0 | T52: 12 | V52: 475 | Z52: =SUM(R52:U52) -> 475 | AA52: 38800 | AB52: 48 | AC52: 38325 | AD52: =IF(OR(AE52="",AB52=""),"",AE52-AB52) -> 38277 | AE52: 38325 | AF52: 38325 | AK52: =IF(COUNTA(AH52:AJ52)=0,"",SUM(AH52:AJ52)) | AO52: =IF(COUNTA(AL52:AN52)=0,"",SUM(AL52:AN52)) | AP52: =IF(COUNTA(AL52:AN52)<3,"",(AL52+0.5*(AM52+AN52))*0.17637) | AQ52: =IF(AO52="","",AO52*0.17637) | AR52: =IF(COUNTA(AJ52,AH52,AL52:AN52)=0,"",(AJ52+AH52+AL52+AM52+AN52)*0.17637) | AS52: =IF(AO52="","",AO52/1000) | AT52: =IF(COUNTA(AH52,AJ52,AL52:AN52)=0,"",SUM(AH52,AJ52,AL52:AN52)/1000) | AU52: 8 | AV52: 167 | BA52: =IF(COUNTA(AX52:AZ52)=0,"",SUM(AX52:AZ52)) | BE52: =IF(COUNTA(BB52:BD52)=0,"",SUM(BB52:BD52)) | BF52: =IF(COUNTA(BB52:BD52)<3,"",(BB52+0.5*(BC52+BD52))*0.17637) | BG52: =IF(BE52="","",BE52*0.17637) | BH52: =IF(COUNTA(AZ52,AX52,BB52:BD52)=0,"",(AZ52+AX52+BB52+BC52+BD52)*0.17637) | BI52: =IF(BE52="","",BE52/1000) | BJ52: =IF(COUNTA(AX52,AZ52,BB52:BD52)=0,"",SUM(AX52,AZ52,BB52:BD52)/1000) | BK52: 8 | BL52: 167
A53: RCV-BKE-2026-0052 | B53: 52 | C53: BKE-001 | F53: LOT-BKE-2026-0052 | G53: INSIDE | H53: 303 | I53: 32069 | J53: A044CA | K53: 46146 | L53: 04-May | M53: 46147 | N53: 05-May | O53: BOUNDIALI | P53: SCOOP ASER | Q53: LBA-011-ASR | R53: 569 | S53: 0 | T53: 15 | V53: 584 | Z53: =SUM(R53:U53) -> 584 | AA53: 48960 | AB53: 60 | AC53: 48376 | AD53: =IF(OR(AE53="",AB53=""),"",AE53-AB53) -> 48316 | AE53: 48376 | AF53: 48376 | AK53: =IF(COUNTA(AH53:AJ53)=0,"",SUM(AH53:AJ53)) | AO53: =IF(COUNTA(AL53:AN53)=0,"",SUM(AL53:AN53)) | AP53: =IF(COUNTA(AL53:AN53)<3,"",(AL53+0.5*(AM53+AN53))*0.17637) | AQ53: =IF(AO53="","",AO53*0.17637) | AR53: =IF(COUNTA(AJ53,AH53,AL53:AN53)=0,"",(AJ53+AH53+AL53+AM53+AN53)*0.17637) | AS53: =IF(AO53="","",AO53/1000) | AT53: =IF(COUNTA(AH53,AJ53,AL53:AN53)=0,"",SUM(AH53,AJ53,AL53:AN53)/1000) | AU53: 10.6 | AV53: 173 | BA53: =IF(COUNTA(AX53:AZ53)=0,"",SUM(AX53:AZ53)) | BE53: =IF(COUNTA(BB53:BD53)=0,"",SUM(BB53:BD53)) | BF53: =IF(COUNTA(BB53:BD53)<3,"",(BB53+0.5*(BC53+BD53))*0.17637) | BG53: =IF(BE53="","",BE53*0.17637) | BH53: =IF(COUNTA(AZ53,AX53,BB53:BD53)=0,"",(AZ53+AX53+BB53+BC53+BD53)*0.17637) | BI53: =IF(BE53="","",BE53/1000) | BJ53: =IF(COUNTA(AX53,AZ53,BB53:BD53)=0,"",SUM(AX53,AZ53,BB53:BD53)/1000) | BK53: 10.6 | BL53: 173
A54: RCV-BKE-2026-0053 | B54: 53 | C54: BKE-001 | F54: LOT-BKE-2026-0053 | G54: INSIDE | H54: 304 | I54: 18783 | J54: 953LU01 | K54: 46146 | L54: 04-May | M54: 46147 | N54: 05-May | O54: KATIOLA | P54: SCOOPS AH AL NOUR | Q54: LBA-016-NOU | R54: 475 | S54: 0 | T54: 10 | V54: 485 | Z54: =SUM(R54:U54) -> 485 | AA54: 41820 | AB54: 40 | AC54: 41335 | AD54: =IF(OR(AE54="",AB54=""),"",AE54-AB54) -> 41295 | AE54: 41335 | AF54: 41335 | AK54: =IF(COUNTA(AH54:AJ54)=0,"",SUM(AH54:AJ54)) | AO54: =IF(COUNTA(AL54:AN54)=0,"",SUM(AL54:AN54)) | AP54: =IF(COUNTA(AL54:AN54)<3,"",(AL54+0.5*(AM54+AN54))*0.17637) | AQ54: =IF(AO54="","",AO54*0.17637) | AR54: =IF(COUNTA(AJ54,AH54,AL54:AN54)=0,"",(AJ54+AH54+AL54+AM54+AN54)*0.17637) | AS54: =IF(AO54="","",AO54/1000) | AT54: =IF(COUNTA(AH54,AJ54,AL54:AN54)=0,"",SUM(AH54,AJ54,AL54:AN54)/1000) | AU54: 9.6 | AV54: 162 | BA54: =IF(COUNTA(AX54:AZ54)=0,"",SUM(AX54:AZ54)) | BE54: =IF(COUNTA(BB54:BD54)=0,"",SUM(BB54:BD54)) | BF54: =IF(COUNTA(BB54:BD54)<3,"",(BB54+0.5*(BC54+BD54))*0.17637) | BG54: =IF(BE54="","",BE54*0.17637) | BH54: =IF(COUNTA(AZ54,AX54,BB54:BD54)=0,"",(AZ54+AX54+BB54+BC54+BD54)*0.17637) | BI54: =IF(BE54="","",BE54/1000) | BJ54: =IF(COUNTA(AX54,AZ54,BB54:BD54)=0,"",SUM(AX54,AZ54,BB54:BD54)/1000) | BK54: 9.6 | BL54: 162
A55: RCV-BKE-2026-0054 | B55: 54 | C55: BKE-001 | D55: BKE-001-BIN-023 | F55: LOT-BKE-2026-0054 | G55: INSIDE | H55: 305 | I55: 31994 | J55: 9611CV03 | K55: 46146 | L55: 04-May | M55: 46147 | N55: 05-May | O55: KORHOGO | P55: SCOOPS-OUMI/KONE SIDY | Q55: LBA-015-OUM | R55: 567 | S55: 20 | T55: 0 | V55: 587 | Z55: =SUM(R55:U55) -> 587 | AA55: 49100 | AB55: 160 | AC55: 48513 | AD55: =IF(OR(AE55="",AB55=""),"",AE55-AB55) -> 48353 | AE55: 48513 | AF55: 48513 | AK55: =IF(COUNTA(AH55:AJ55)=0,"",SUM(AH55:AJ55)) | AO55: =IF(COUNTA(AL55:AN55)=0,"",SUM(AL55:AN55)) | AP55: =IF(COUNTA(AL55:AN55)<3,"",(AL55+0.5*(AM55+AN55))*0.17637) | AQ55: =IF(AO55="","",AO55*0.17637) | AR55: =IF(COUNTA(AJ55,AH55,AL55:AN55)=0,"",(AJ55+AH55+AL55+AM55+AN55)*0.17637) | AS55: =IF(AO55="","",AO55/1000) | AT55: =IF(COUNTA(AH55,AJ55,AL55:AN55)=0,"",SUM(AH55,AJ55,AL55:AN55)/1000) | AU55: 11 | AV55: 181 | BA55: =IF(COUNTA(AX55:AZ55)=0,"",SUM(AX55:AZ55)) | BE55: =IF(COUNTA(BB55:BD55)=0,"",SUM(BB55:BD55)) | BF55: =IF(COUNTA(BB55:BD55)<3,"",(BB55+0.5*(BC55+BD55))*0.17637) | BG55: =IF(BE55="","",BE55*0.17637) | BH55: =IF(COUNTA(AZ55,AX55,BB55:BD55)=0,"",(AZ55+AX55+BB55+BC55+BD55)*0.17637) | BI55: =IF(BE55="","",BE55/1000) | BJ55: =IF(COUNTA(AX55,AZ55,BB55:BD55)=0,"",SUM(AX55,AZ55,BB55:BD55)/1000) | BK55: 11 | BL55: 181
A56: RCV-BKE-2026-0055 | B56: 55 | C56: BKE-001 | F56: LOT-BKE-2026-0055 | G56: INSIDE | H56: 306 | I56: 13117 | J56: 5012HJ01 | K56: 46146 | L56: 04-May | M56: 46147 | N56: 05-May | O56: BOUAKE | P56: SCOOP IMANE | Q56: LBA-006-IMA | R56: 568 | S56: 0 | T56: 8 | V56: 576 | Z56: =SUM(R56:U56) -> 576 | AA56: 45540 | AB56: 32 | AC56: 44964 | AD56: =IF(OR(AE56="",AB56=""),"",AE56-AB56) -> 44932 | AE56: 44964 | AF56: 44964 | AK56: =IF(COUNTA(AH56:AJ56)=0,"",SUM(AH56:AJ56)) | AO56: =IF(COUNTA(AL56:AN56)=0,"",SUM(AL56:AN56)) | AP56: =IF(COUNTA(AL56:AN56)<3,"",(AL56+0.5*(AM56+AN56))*0.17637) | AQ56: =IF(AO56="","",AO56*0.17637) | AR56: =IF(COUNTA(AJ56,AH56,AL56:AN56)=0,"",(AJ56+AH56+AL56+AM56+AN56)*0.17637) | AS56: =IF(AO56="","",AO56/1000) | AT56: =IF(COUNTA(AH56,AJ56,AL56:AN56)=0,"",SUM(AH56,AJ56,AL56:AN56)/1000) | AU56: 8 | AV56: 177 | BA56: =IF(COUNTA(AX56:AZ56)=0,"",SUM(AX56:AZ56)) | BE56: =IF(COUNTA(BB56:BD56)=0,"",SUM(BB56:BD56)) | BF56: =IF(COUNTA(BB56:BD56)<3,"",(BB56+0.5*(BC56+BD56))*0.17637) | BG56: =IF(BE56="","",BE56*0.17637) | BH56: =IF(COUNTA(AZ56,AX56,BB56:BD56)=0,"",(AZ56+AX56+BB56+BC56+BD56)*0.17637) | BI56: =IF(BE56="","",BE56/1000) | BJ56: =IF(COUNTA(AX56,AZ56,BB56:BD56)=0,"",SUM(AX56,AZ56,BB56:BD56)/1000) | BK56: 8 | BL56: 177
A57: RCV-BKE-2026-0056 | B57: 56 | F57: LOT-BKE-2026-0056 | G57: INSIDE | H57: 429 | I57: 18946 | J57: 4981JR04 | K57: 46146 | L57: 04-May | M57: 46147 | N57: 05-May | O57: DABAKALA | P57: SCOOPS WEBE | Q57: LBA-004-WEB | R57: 448 | S57: 55 | T57: 0 | V57: 503 | Z57: =SUM(R57:U57) -> 503 | AA57: 41510 | AB57: 440 | AC57: 41007 | AD57: =IF(OR(AE57="",AB57=""),"",AE57-AB57) -> 40567 | AE57: 41007 | AF57: 41007 | AK57: =IF(COUNTA(AH57:AJ57)=0,"",SUM(AH57:AJ57)) | AO57: =IF(COUNTA(AL57:AN57)=0,"",SUM(AL57:AN57)) | AP57: =IF(COUNTA(AL57:AN57)<3,"",(AL57+0.5*(AM57+AN57))*0.17637) | AQ57: =IF(AO57="","",AO57*0.17637) | AR57: =IF(COUNTA(AJ57,AH57,AL57:AN57)=0,"",(AJ57+AH57+AL57+AM57+AN57)*0.17637) | AS57: =IF(AO57="","",AO57/1000) | AT57: =IF(COUNTA(AH57,AJ57,AL57:AN57)=0,"",SUM(AH57,AJ57,AL57:AN57)/1000) | AU57: 12.6 | AV57: 173 | BA57: =IF(COUNTA(AX57:AZ57)=0,"",SUM(AX57:AZ57)) | BE57: =IF(COUNTA(BB57:BD57)=0,"",SUM(BB57:BD57)) | BF57: =IF(COUNTA(BB57:BD57)<3,"",(BB57+0.5*(BC57+BD57))*0.17637) | BG57: =IF(BE57="","",BE57*0.17637) | BH57: =IF(COUNTA(AZ57,AX57,BB57:BD57)=0,"",(AZ57+AX57+BB57+BC57+BD57)*0.17637) | BI57: =IF(BE57="","",BE57/1000) | BJ57: =IF(COUNTA(AX57,AZ57,BB57:BD57)=0,"",SUM(AX57,AZ57,BB57:BD57)/1000) | BK57: 12.6 | BL57: 173
A58: RCV-BKE-2026-0057 | B58: 57 | F58: LOT-BKE-2026-0057 | G58: INSIDE | H58: 441 | I58: 89077 | J58: 8188KU03 | K58: 46146 | L58: 04-May | M58: 46150 | N58: 08-May | O58: SAMATIGUILA | P58: SANOGO SINDOU | Q58: LBA-021-SAN | R58: 580 | S58: 0 | T58: 10 | V58: 590 | Z58: =SUM(R58:U58) -> 590 | AA58: 47800 | AB58: 40 | AC58: 47210 | AD58: =IF(OR(AE58="",AB58=""),"",AE58-AB58) -> 47170 | AE58: 47210 | AF58: 47210 | AK58: =IF(COUNTA(AH58:AJ58)=0,"",SUM(AH58:AJ58)) | AO58: =IF(COUNTA(AL58:AN58)=0,"",SUM(AL58:AN58)) | AP58: =IF(COUNTA(AL58:AN58)<3,"",(AL58+0.5*(AM58+AN58))*0.17637) | AQ58: =IF(AO58="","",AO58*0.17637) | AR58: =IF(COUNTA(AJ58,AH58,AL58:AN58)=0,"",(AJ58+AH58+AL58+AM58+AN58)*0.17637) | AS58: =IF(AO58="","",AO58/1000) | AT58: =IF(COUNTA(AH58,AJ58,AL58:AN58)=0,"",SUM(AH58,AJ58,AL58:AN58)/1000) | AU58: 8.5 | AV58: 183 | BA58: =IF(COUNTA(AX58:AZ58)=0,"",SUM(AX58:AZ58)) | BE58: =IF(COUNTA(BB58:BD58)=0,"",SUM(BB58:BD58)) | BF58: =IF(COUNTA(BB58:BD58)<3,"",(BB58+0.5*(BC58+BD58))*0.17637) | BG58: =IF(BE58="","",BE58*0.17637) | BH58: =IF(COUNTA(AZ58,AX58,BB58:BD58)=0,"",(AZ58+AX58+BB58+BC58+BD58)*0.17637) | BI58: =IF(BE58="","",BE58/1000) | BJ58: =IF(COUNTA(AX58,AZ58,BB58:BD58)=0,"",SUM(AX58,AZ58,BB58:BD58)/1000) | BK58: 8.5 | BL58: 183
A59: RCV-BKE-2026-0058 | B59: 58 | F59: LOT-BKE-2026-0058 | G59: INSIDE | H59: 442 | I59: 78898 | J59: 5116HF01 | K59: 46149 | L59: 07-May | M59: 46150 | N59: 08-May | O59: VAVOUA | P59: SCAAMT COOP CA | Q59: LBA-002-SCA | R59: 514 | S59: 0 | T59: 14 | V59: 524 | Z59: =SUM(R59:U59) -> 528 | AA59: 41140 | AB59: 56 | AC59: 40616 | AD59: =IF(OR(AE59="",AB59=""),"",AE59-AB59) -> 40560 | AE59: 40616 | AF59: 40616 | AK59: =IF(COUNTA(AH59:AJ59)=0,"",SUM(AH59:AJ59)) | AO59: =IF(COUNTA(AL59:AN59)=0,"",SUM(AL59:AN59)) | AP59: =IF(COUNTA(AL59:AN59)<3,"",(AL59+0.5*(AM59+AN59))*0.17637) | AQ59: =IF(AO59="","",AO59*0.17637) | AR59: =IF(COUNTA(AJ59,AH59,AL59:AN59)=0,"",(AJ59+AH59+AL59+AM59+AN59)*0.17637) | AS59: =IF(AO59="","",AO59/1000) | AT59: =IF(COUNTA(AH59,AJ59,AL59:AN59)=0,"",SUM(AH59,AJ59,AL59:AN59)/1000) | AU59: 9.8 | AV59: 180 | BA59: =IF(COUNTA(AX59:AZ59)=0,"",SUM(AX59:AZ59)) | BE59: =IF(COUNTA(BB59:BD59)=0,"",SUM(BB59:BD59)) | BF59: =IF(COUNTA(BB59:BD59)<3,"",(BB59+0.5*(BC59+BD59))*0.17637) | BG59: =IF(BE59="","",BE59*0.17637) | BH59: =IF(COUNTA(AZ59,AX59,BB59:BD59)=0,"",(AZ59+AX59+BB59+BC59+BD59)*0.17637) | BI59: =IF(BE59="","",BE59/1000) | BJ59: =IF(COUNTA(AX59,AZ59,BB59:BD59)=0,"",SUM(AX59,AZ59,BB59:BD59)/1000) | BK59: 9.8 | BL59: 180

Sheet Drying
A1: Row ID | B1: No | C1: Drying Date | D1: Warehouse | E1: Source Bin | F1: Destination Bin | G1: Lot No | H1: Lot No | I1: Warehouse Receipt No | J1: Fiche No | K1: Origin | L1: Supplier Name | M1: Supplier Code | N1: CCAK Supplier Code | O1: Status | P1: Dry Type | Q1: Destination | R1: Issued Gross Weight with Bags & Pallets (kg) | S1: Issued Pallet Weight (kg) | T1: Issued Gross Weight with Bags (kg) | U1: Issued Bags | V1: Issued Net Weight (kg) | W1: Received Gross Weight with Bags & Pallets (kg) | X1: Received Pallet Weight (kg) | Y1: Received Gross Weight with Bags (kg) | Z1: Received Bags | AA1: Received Net Weight (kg) | AB1: Input Moisture (%) | AC1: Input Nut Count | AD1: Input KOR | AE1: Output Moisture (%) | AF1: Output Nut Count | AG1: Output KOR | AH1: Oil (g) | AI1: Rejection (g) | AJ1: Good Kernel (g) | AK1: Immature (g) | AL1: Spotted (g) | AM1: Shell (g) | AN1: Void (g) | AO1: Drying Loss (kg) | AP1: Triage Loss (kg) | AQ1: Damaged Nuts (kg) | AR1: Input Bags for Drying | AS1: Output Bags After Drying | AT1: Drying or Picking | AU1: Remarks | AV1: Issued to Production | AW1: Re-drying Date | AX1: Moisture After First Re-dry (%) | AY1: Moisture After Second Dry (%) | AZ1: Historical Output KOR | BA1: KOR Variance
A2: DRY-YAK-2026-001 | B2: 1 | C2: 46142 | D2: ANAGROCI-01 | E2: BIN-013 | F2: ANA-01-DRY | G2: LOT-YAK-2026-0193 | H2: 193 | J2: 773 | O2: OK | P2: Supplier | Q2: ANA-01-DRY | R2: 43680 | S2: 0 | T2: 43680 | U2: 531 | V2: 43149 | W2: 44299 | X2: 1955 | Y2: 42344 | Z2: 572 | AA2: 41772 | AB2: 11.8 | AC2: 185 | AD2: 43.03 | AE2: 9.6 | AF2: 183 | AG2: =IF(COUNTA(AJ2:AL2)<3,AZ2,(AJ2+0.5*(AK2+AL2))*0.17637) -> 42.3288 | AH2: 0 | AI2: 49 | AJ2: 227 | AK2: 10 | AL2: 16 | AM2: 675 | AN2: 17 | AO2: =IF(OR(V2="",AA2=""),"",V2-AA2) -> 1377 | AR2: 540 | AS2: 572 | AT2: Dryied | AU2: Scaled | AV2: Empilage in Production Area | AZ2: 43.32 | BA2: =IF(OR(AG2="",AZ2=""),"",AG2-AZ2) -> -0.9912
A3: DRY-YAK-2026-002 | B3: 2 | C3: 46142 | D3: ANAGROCI-01 | E3: BIN-013 | F3: ANA-01-DRY | G3: LOT-YAK-2026-0197 | H3: 197 | J3: 14643 | O3: Direct offload for dry | P3: Supplier | Q3: ANA-01-DRY | R3: 40480 | S3: 0 | T3: 40480 | U3: 453 | V3: 40027 | W3: 40602 | X3: 1650 | Y3: 38952 | Z3: 536 | AA3: 38416 | AB3: 11.8 | AC3: 160 | AD3: 43.12 | AE3: 10.4 | AF3: 164 | AG3: =IF(COUNTA(AJ3:AL3)<3,AZ3,(AJ3+0.5*(AK3+AL3))*0.17637) -> 43.21065 | AH3: 4 | AI3: 20 | AJ3: 230 | AK3: 12 | AL3: 18 | AM3: 675 | AN3: 36 | AO3: =IF(OR(V3="",AA3=""),"",V3-AA3) -> 1611 | AR3: 465 | AS3: 536 | AT3: Dryied | AU3: Scaled | AV3: Empilage in Production Area | AZ3: 43.21 | BA3: =IF(OR(AG3="",AZ3=""),"",AG3-AZ3) -> 0.00065
A4: DRY-YAK-2026-003 | B4: 3 | C4: 46145 | D4: ANAGROCI-01 | E4: BIN-001 | F4: ANA-02-DRY | G4: LOT-YAK-2026-0160 | H4: 160 | J4: 82124 | O4: OK | P4: BOUAKE | Q4: ANA-02-DRY | R4: 54180 | S4: 0 | T4: 54180 | U4: 646 | V4: 53534 | W4: 55082 | X4: 2044 | Y4: 53038 | Z4: 701 | AA4: 52337 | AB4: 15.4 | AC4: 158 | AD4: 43.56 | AE4: 10.5 | AF4: 170 | AG4: =IF(COUNTA(AJ4:AL4)<3,AZ4,(AJ4+0.5*(AK4+AL4))*0.17637) -> 44.26887 | AH4: 0 | AI4: 27 | AJ4: 244 | AK4: 10 | AL4: 4 | AM4: 674 | AN4: 37 | AO4: =IF(OR(V4="",AA4=""),"",V4-AA4) -> 1197 | AR4: 631 | AS4: 701 | AT4: Dryied | AU4: Scaled | AV4: BIN | AZ4: 44.26 | BA4: =IF(OR(AG4="",AZ4=""),"",AG4-AZ4) -> 0.00887
A5: DRY-YAK-2026-004 | B5: 4 | C5: 46146 | D5: ANAGROCI-01 | E5: BIN-013 | F5: ANA-01-DRY | G5: LOT-YAK-2026-0179 | H5: 179 | J5: 66919 | P5: BOUAKE | Q5: ANA-01-DRY | R5: 42480 | S5: 0 | T5: 42480 | U5: 577 | V5: 41903 | W5: 42599 | X5: 1633 | Y5: 40966 | Z5: 547 | AA5: 40419 | AB5: 10.5 | AC5: 184 | AD5: 42.41 | AE5: 8.5 | AF5: 188 | AG5: =IF(COUNTA(AJ5:AL5)<3,AZ5,(AJ5+0.5*(AK5+AL5))*0.17637) -> 43.21065 | AH5: 2 | AI5: 22 | AJ5: 234 | AK5: 12 | AL5: 10 | AM5: 681 | AN5: 34 | AO5: =IF(OR(V5="",AA5=""),"",V5-AA5) -> 1484 | AR5: 599 | AS5: 547 | AT5: Dryied | AU5: Scaled | AV5: Empilage in Production Area | AZ5: 43.03 | BA5: =IF(OR(AG5="",AZ5=""),"",AG5-AZ5) -> 0.18065
A6: DRY-YAK-2026-005 | B6: 5 | C6: 46164 | D6: ANAGROCI-01 | E6: BIN-03B | F6: ANA-01-DRY | G6: LOT-YAK-2026-BIN-03B | H6: BIN-03B | J6: 51237 | O6: OK | P6: BIN-03B | Q6: ANA-01-DRY | R6: 46553 | S6: 5930 | T6: 40623 | U6: 540 | V6: 40083 | W6: 41509 | X6: 1590 | Y6: 39919 | Z6: 535 | AA6: 39384 | AB6: 10.8 | AC6: 178 | AD6: 42.24 | AE6: 8.8 | AF6: 172 | AG6: =IF(COUNTA(AJ6:AL6)<3,AZ6,(AJ6+0.5*(AK6+AL6))*0.17637) -> 42.769725 | AH6: 0 | AI6: 40 | AJ6: 230 | AK6: 11 | AL6: 14 | AM6: 687 | AN6: 13 | AO6: =IF(OR(V6="",AA6=""),"",V6-AA6) -> 699 | AR6: 540 | AS6: 535 | AT6: Dryied | AU6: Scaled | AV6: Issued to Production | AZ6: 42.76 | BA6: =IF(OR(AG6="",AZ6=""),"",AG6-AZ6) -> 0.009725
A7: DRY-YAK-2026-006 | B7: 6 | C7: 46167 | D7: ANAGROCI-01 | E7: BIN-03B | F7: ANA-01-DRY | G7: LOT-YAK-2026-BIN-03B | H7: BIN-03B | J7: 82120 | O7: OK | P7: BIN-03B | Q7: ANA-01-DRY | R7: 78459 | S7: 2490 | T7: 75969 | U7: 1001 | V7: 74968 | W7: 77183 | X7: 2902 | Y7: 74281 | Z7: 998 | AA7: 73283 | AB7: 10.5 | AC7: 174 | AD7: 42.24 | AE7: 8.8 | AF7: 171 | AG7: =IF(COUNTA(AJ7:AL7)<3,AZ7,(AJ7+0.5*(AK7+AL7))*0.17637) -> 42.593355 | AH7: 3 | AI7: 30 | AJ7: 227 | AK7: 19 | AL7: 10 | AM7: 670 | AN7: 36 | AO7: =IF(OR(V7="",AA7=""),"",V7-AA7) -> 1685 | AR7: 1001 | AS7: 998 | AT7: Dryied | AU7: Scaled | AV7: Issued To Production | AZ7: 42.59 | BA7: =IF(OR(AG7="",AZ7=""),"",AG7-AZ7) -> 0.003355
A8: DRY-YAK-2026-007 | B8: 7 | C8: 46168 | D8: ANAGROCI-01 | E8: BIN-03B | F8: ANA-01-DRY | G8: LOT-YAK-2026-BIN-03B | H8: BIN-03B | J8: 82869 | O8: OK | P8: BIN-03B | Q8: ANA-01-DRY | R8: 32489 | S8: 1016 | T8: 31473 | U8: 414 | V8: 31059 | W8: 32297 | X8: 1394 | Y8: 30903 | Z8: 414 | AA8: 30489 | AB8: 10.1 | AC8: 174 | AD8: 42.15 | AE8: 8.7 | AF8: 175 | AG8: =IF(COUNTA(AJ8:AL8)<3,AZ8,(AJ8+0.5*(AK8+AL8))*0.17637) -> 42.50517 | AH8: 0 | AI8: 36 | AJ8: 223 | AK8: 17 | AL8: 19 | AM8: 659 | AN8: 41 | AO8: =IF(OR(V8="",AA8=""),"",V8-AA8) -> 570 | AR8: 414 | AS8: 414 | AT8: Dryied | AU8: Scaled | AV8: Issued To Production | AZ8: 42.5 | BA8: =IF(OR(AG8="",AZ8=""),"",AG8-AZ8) -> 0.00517
A9: DRY-YAK-2026-008 | B9: 8 | C9: 46169 | D9: ANAGROCI-01 | E9: BIN-03B | F9: ANA-01-DRY | G9: LOT-YAK-2026-BIN-03B | H9: BIN-03B | J9: 82153 | O9: OK | P9: BIN-03B | Q9: ANA-01-DRY | R9: 50394 | S9: 1523.9 | T9: 48870.1 | U9: 638 | V9: 48232.1 | W9: 49948 | X9: 1966 | Y9: 47982 | Z9: 645 | AA9: 47337 | AB9: 10.5 | AC9: 177 | AD9: 42.24 | AE9: 8.8 | AF9: 174 | AG9: =IF(COUNTA(AJ9:AL9)<3,AZ9,(AJ9+0.5*(AK9+AL9))*0.17637) -> 42.416985 | AH9: 0 | AI9: 37 | AJ9: 226 | AK9: 14 | AL9: 15 | AM9: 671 | AN9: 32 | AO9: =IF(OR(V9="",AA9=""),"",V9-AA9) -> 895.1 | AR9: 638 | AS9: 645 | AT9: Dryied | AU9: Scaled | AV9: Issued To Production | AZ9: 42.41 | BA9: =IF(OR(AG9="",AZ9=""),"",AG9-AZ9) -> 0.006985
A10: DRY-YAK-2026-009 | B10: 9 | C10: 46170 | D10: ANAGROCI-01 | E10: BIN-013 | F10: ANA-03B-DRY | G10: LOT-YAK-2026-87036 | H10: 87036 | J10: 87036 | O10: OK | P10: Supplier | Q10: ANA-03B-DRY | R10: 55860 | S10: 0 | T10: 55860 | U10: 690 | V10: 55170 | W10: 56876 | X10: 2215 | Y10: 54661 | Z10: 751 | AA10: 53910 | AB10: 10.4 | AC10: 175 | AD10: 41.88 | AE10: 8.9 | AF10: 183 | AG10: =IF(COUNTA(AJ10:AL10)<3,AZ10,(AJ10+0.5*(AK10+AL10))*0.17637) -> 41.09421 | AH10: 0 | AI10: 49 | AJ10: 220 | AK10: 12 | AL10: 14 | AM10: 682 | AN10: 17 | AO10: =IF(OR(V10="",AA10=""),"",V10-AA10) -> 1260 | AR10: 734 | AS10: 751 | AT10: Dried | AU10: Scaled | AV10: BIN IN CALIBRATION AREA | AZ10: 41.09 | BA10: =IF(OR(AG10="",AZ10=""),"",AG10-AZ10) -> 0.00421
A11: DRY-YAK-2026-010 | B11: 10 | C11: 46171 | D11: ANAGROCI-01 | E11: BIN-03B | F11: ANA-03B-DRY | G11: LOT-YAK-2026-BIN-03B | H11: BIN-03B | J11: BIN-03B | O11: OK | P11: BIN-03B | Q11: ANA-03B-DRY | R11: 69877 | S11: 2206 | T11: 67671 | U11: 893 | V11: 66778 | W11: 68376 | X11: 2668 | Y11: 65708 | Z11: 912 | AA11: 64796 | AB11: 10.2 | AC11: 174 | AD11: 42.65 | AE11: 8.6 | AF11: 170 | AG11: =IF(COUNTA(AJ11:AL11)<3,AZ11,(AJ11+0.5*(AK11+AL11))*0.17637) -> 43.03428 | AH11: 2 | AI11: 28 | AJ11: 230 | AK11: 18 | AL11: 10 | AM11: 678 | AN11: 26 | AO11: =IF(OR(V11="",AA11=""),"",V11-AA11) -> 1982 | AR11: 893 | AS11: 912 | AT11: Dried | AU11: Scaled | AV11: BIN IN CALIBRATION AREA | AZ11: 43.03 | BA11: =IF(OR(AG11="",AZ11=""),"",AG11-AZ11) -> 0.00428
A12: DRY-YAK-2026-011 | B12: 11 | C12: 46172 | D12: ANAGROCI-01 | E12: BIN-03B | F12: ANA-01-DRY | G12: LOT-YAK-2026-BIN-03B | H12: BIN-03B | J12: BIN-03B | O12: OK | P12: BIN-03B | Q12: ANA-01-DRY | R12: 69809 | S12: 2206 | T12: 67603 | U12: 898 | V12: 66705 | W12: 69008 | X12: 2666 | Y12: 66342 | Z12: 890 | AA12: 65452 | AB12: 10.7 | AC12: 175 | AD12: 42.06 | AE12: 8.3 | AF12: 177 | AG12: =IF(COUNTA(AJ12:AL12)<3,AZ12,(AJ12+0.5*(AK12+AL12))*0.17637) -> 41.535135 | AH12: 2 | AI12: 40 | AJ12: 217 | AK12: 17 | AL12: 20 | AM12: 665 | AN12: 35 | AO12: =IF(OR(V12="",AA12=""),"",V12-AA12) -> 1253 | AR12: 898 | AS12: 890 | AT12: Dried | AU12: Scaled | AV12: Issued To Production | AZ12: 41.53 | BA12: =IF(OR(AG12="",AZ12=""),"",AG12-AZ12) -> 0.005135
A13: DRY-YAK-2026-012 | B13: 12 | C13: 46174 | D13: ANAGROCI-01 | E13: BIN-03B | F13: ANA-03B-DRY | G13: LOT-YAK-2026-BIN-03B | H13: BIN-03B | J13: BIN-03B | O13: OK | P13: BIN-03B | Q13: ANA-03B-DRY | R13: 52187 | S13: 1671 | T13: 50516 | U13: 660 | V13: 49856 | W13: 50641.7 | X13: 1969 | Y13: 48672.7 | Z13: 740 | AA13: 47932.7 | AB13: 11.2 | AC13: 170 | AD13: 41.27 | AE13: 8.7 | AF13: 170 | AG13: =IF(COUNTA(AJ13:AL13)<3,AZ13,(AJ13+0.5*(AK13+AL13))*0.17637) -> 41.27058 | AH13: 0 | AI13: 48 | AJ13: 222 | AK13: 10 | AL13: 14 | AM13: 678 | AN13: 23 | AO13: =IF(OR(V13="",AA13=""),"",V13-AA13) -> 1923.3 | AR13: 660 | AS13: 740 | AT13: Dried | AU13: Scaled | AV13: BIN IN CALIBRATION AREA | AZ13: 41.27 | BA13: =IF(OR(AG13="",AZ13=""),"",AG13-AZ13) -> 0.00058
A14: DRY-YAK-2026-013 | B14: 13 | C14: 46175 | D14: ANAGROCI-01 | E14: BIN-015 | F14: ANA-03B-DRY | G14: LOT-YAK-2026-BIN-015 | H14: BIN-015 | J14: 87130 | O14: Direct offload for dry | P14: Supplier | Q14: ANA-03B-DRY | R14: 56200 | S14: 0 | T14: 56200 | U14: 724 | V14: 55476 | W14: 57460 | X14: 2240 | Y14: 55220 | Z14: 772 | AA14: 54448 | AB14: 10.4 | AC14: 164 | AD14: 41.88 | AE14: 8.9 | AF14: 174 | AG14: =IF(COUNTA(AJ14:AL14)<3,AZ14,(AJ14+0.5*(AK14+AL14))*0.17637) -> 41.97606 | AH14: 0 | AI14: 39 | AJ14: 219 | AK14: 21 | AL14: 17 | AM14: 688 | AN14: 15 | AO14: =IF(OR(V14="",AA14=""),"",V14-AA14) -> 1028 | AR14: 740 | AS14: 772 | AT14: Dried | AU14: Scaled | AV14: BIN IN CALIBRATION AREA | AZ14: 41.97 | BA14: =IF(OR(AG14="",AZ14=""),"",AG14-AZ14) -> 0.00606
A15: DRY-YAK-2026-014 | B15: 14 | C15: 46176 | D15: ANAGROCI-01 | E15: BIN-03B | F15: ANA-03B-DRY | G15: LOT-YAK-2026-BIN-03B | H15: BIN-03B | J15: BIN-03B | O15: OK | P15: BIN-03B | Q15: ANA-03B-DRY | R15: 57551 | S15: 1801 | T15: 55750 | U15: 750 | V15: 55000 | W15: 57075 | X15: 2285 | Y15: 54790 | Z15: 749 | AA15: 54041 | AB15: 10.2 | AC15: 175 | AD15: 40.65 | AE15: 8.8 | AF15: 180 | AG15: =IF(COUNTA(AJ15:AL15)<3,AZ15,(AJ15+0.5*(AK15+AL15))*0.17637) -> 40.829655 | AH15: 0 | AI15: 42 | AJ15: 214 | AK15: 19 | AL15: 16 | AM15: 686 | AN15: 18 | AO15: =IF(OR(V15="",AA15=""),"",V15-AA15) -> 959 | AR15: 750 | AS15: 749 | AT15: Dried | AU15: Scaled | AV15: BIN IN CALIBRATION AREA | AZ15: 40.82 | BA15: =IF(OR(AG15="",AZ15=""),"",AG15-AZ15) -> 0.009655
A16: DRY-YAK-2026-015 | B16: 15 | C16: 46178 | D16: ANAGROCI-01 | E16: BIN-005 | F16: ANA-05A-DRY | G16: LOT-YAK-2026-BIN-005 | H16: BIN-005 | J16: BIN-005 | P16: BIN-005 | Q16: ANA-05A-DRY | R16: 61767 | S16: 2475 | T16: 59292 | U16: 780 | V16: 58512 | W16: 60785.2 | X16: 2349.2 | Y16: 58436 | Z16: 785 | AA16: 57651 | AB16: 9.8 | AC16: 180 | AD16: 42.24 | AE16: 8.5 | AF16: 187 | AG16: =IF(COUNTA(AJ16:AL16)<3,AZ16,(AJ16+0.5*(AK16+AL16))*0.17637) -> 42.769725 | AH16: 2 | AI16: 36 | AJ16: 226 | AK16: 14 | AL16: 19 | AM16: 677 | AN16: 20 | AO16: =IF(OR(V16="",AA16=""),"",V16-AA16) -> 861 | AR16: 780 | AS16: 785 | AT16: Dried | AU16: Scaled | AV16: BIN IN CALIBRATION AREA | AZ16: 42.76 | BA16: =IF(OR(AG16="",AZ16=""),"",AG16-AZ16) -> 0.009725
A17: DRY-YAK-2026-016 | B17: 16 | C17: 46179 | D17: ANAGROCI-01 | E17: BIN-005 | F17: ANA-05A-DRY | G17: LOT-YAK-2026-BIN-005 | H17: BIN-005 | J17: BIN-005 | P17: BIN-005 | Q17: ANA-05A-DRY | R17: 51163 | S17: 1651 | T17: 49512 | U17: 660 | V17: 48852 | W17: 50909.8 | X17: 2032.6 | Y17: 48877.2 | Z17: 656 | AA17: 48221.2 | AB17: 9.8 | AC17: 181 | AD17: 43.47 | AE17: 7.9 | AF17: 177 | AG17: =IF(COUNTA(AJ17:AL17)<3,AZ17,(AJ17+0.5*(AK17+AL17))*0.17637) -> 43.73976 | AH17: 0 | AI17: 34 | AJ17: 233 | AK17: 13 | AL17: 17 | AM17: 689 | AN17: 9 | AO17: =IF(OR(V17="",AA17=""),"",V17-AA17) -> 630.8 | AR17: 660 | AS17: 656 | AT17: Dried | AU17: Scaled | AV17: BIN IN CALIBRATION AREA | AZ17: 43.73 | BA17: =IF(OR(AG17="",AZ17=""),"",AG17-AZ17) -> 0.00976
A18: DRY-YAK-2026-017 | B18: 17 | C18: 46181 | D18: ANAGROCI-01 | E18: BIN-005 | F18: ANA-05A-DRY | G18: LOT-YAK-2026-BIN-005 | H18: BIN-005 | J18: BIN-005 | P18: BIN-005 | Q18: ANA-05A-DRY | R18: 56895 | S18: 1876 | T18: 55019 | U18: 750 | V18: 54269 | W18: 54217 | X18: 0 | Y18: 54217 | Z18: 641 | AA18: 53576 | AB18: 8.9 | AC18: 186 | AD18: 42.32 | AE18: 8.2 | AF18: 184 | AG18: =IF(COUNTA(AJ18:AL18)<3,AZ18,(AJ18+0.5*(AK18+AL18))*0.17637) -> 42.593355 | AH18: 2 | AI18: 30 | AJ18: 227 | AK18: 16 | AL18: 13 | AM18: 675 | AN18: 32 | AO18: =IF(OR(V18="",AA18=""),"",V18-AA18) -> 693 | AR18: 750 | AS18: 641 | AT18: Dried | AU18: Scaled | AV18: ISSUE TO CALIBRATION | AZ18: 42.59 | BA18: =IF(OR(AG18="",AZ18=""),"",AG18-AZ18) -> 0.003355
A19: DRY-YAK-2026-018 | B19: 18 | C19: 46182 | D19: ANAGROCI-01 | E19: BIN-005 | F19: ANA-05A-DRY | G19: LOT-YAK-2026-BIN-005 | H19: BIN-005 | J19: BIN-005 | P19: BIN-005 | Q19: ANA-05A-DRY | R19: 67330.3 | S19: 2267 | T19: 65063.3 | U19: 930 | V19: 64133.3 | W19: 66705 | X19: 2568 | Y19: 64137 | Z19: 943 | AA19: 63194 | AB19: 8.5 | AC19: 188 | AD19: 42.68 | AE19: 7.8 | AF19: 182 | AG19: =IF(COUNTA(AJ19:AL19)<3,AZ19,(AJ19+0.5*(AK19+AL19))*0.17637) -> 43.651575 | AH19: 2 | AI19: 36 | AJ19: 237 | AK19: 9 | AL19: 12 | AM19: 686 | AN19: 13 | AO19: =IF(OR(V19="",AA19=""),"",V19-AA19) -> 939.3 | AR19: 930 | AS19: 395 | AT19: Dried | AU19: Scaled | AV19: ISSUE TO CALIBRATION | AZ19: 43.65 | BA19: =IF(OR(AG19="",AZ19=""),"",AG19-AZ19) -> 0.001575
A20: DRY-YAK-2026-019 | B20: 19 | C20: 46183 | D20: ANAGROCI-01 | E20: BIN-005 | F20: ANA-05A-DRY | G20: LOT-YAK-2026-BIN-005 | H20: BIN-005 | J20: BIN-005 | P20: BIN-005 | Q20: ANA-05A-DRY | R20: 28436.4 | S20: 935 | T20: 27501.4 | U20: 390 | V20: 27111.4 | W20: 27973 | X20: 1077 | Y20: 26896 | Z20: 395 | AA20: 26501 | AB20: 8.5 | AC20: 188 | AD20: 42.68 | AE20: 7.8 | AF20: 182 | AG20: =IF(COUNTA(AJ20:AL20)<3,AZ20,(AJ20+0.5*(AK20+AL20))*0.17637) -> 43.651575 | AH20: 2 | AI20: 36 | AJ20: 237 | AK20: 9 | AL20: 12 | AM20: 686 | AN20: 13 | AO20: =IF(OR(V20="",AA20=""),"",V20-AA20) -> 610.4 | AR20: 390 | AS20: 943 | AU20: Scaled | AZ20: 43.65 | BA20: =IF(OR(AG20="",AZ20=""),"",AG20-AZ20) -> 0.001575
A21: DRY-YAK-2026-020 | B21: 20 | C21: 46184 | D21: ANAGROCI-01 | E21: BIN-005 | F21: ANA-05A-DRY | G21: LOT-YAK-2026-BIN-005 | H21: BIN-005 | J21: BIN-005 | P21: BIN-005 | Q21: ANA-05A-DRY | R21: 67576.5 | S21: 2047 | T21: 65529.5 | U21: 870 | V21: 64659.5 | W21: 68016 | X21: 2648 | Y21: 65368 | Z21: 884 | AA21: 64484 | AB21: 9.8 | AC21: 187 | AD21: 43.56 | AE21: 7.9 | AF21: 190 | AG21: =IF(COUNTA(AJ21:AL21)<3,AZ21,(AJ21+0.5*(AK21+AL21))*0.17637) -> 43.21065 | AH21: 2 | AI21: 34 | AJ21: 230 | AK21: 15 | AL21: 15 | AM21: 660 | AN21: 34 | AO21: =IF(OR(V21="",AA21=""),"",V21-AA21) -> 175.5 | AR21: 870 | AS21: 884 | AT21: Dried | AU21: Scaled | AV21: Issued to Production | AZ21: 43.21 | BA21: =IF(OR(AG21="",AZ21=""),"",AG21-AZ21) -> 0.00065
A22: DRY-YAK-2026-021 | B22: 21 | C22: 46185 | D22: ANAGROCI-01 | E22: BIN-005 | F22: ANA-05A-DRY | G22: LOT-YAK-2026-BIN-005 | H22: BIN-005 | J22: BIN-005 | P22: BIN-005 | Q22: ANA-05A-DRY | R22: 74750 | S22: 2353 | T22: 72397 | U22: 990 | V22: 71407 | W22: 73569 | X22: 2853 | Y22: 70716 | Z22: 966 | AA22: 69750 | AB22: 9.6 | AC22: 173 | AD22: 43.47 | AE22: 7.3 | AF22: 179 | AG22: =IF(COUNTA(AJ22:AL22)<3,AZ22,(AJ22+0.5*(AK22+AL22))*0.17637) -> 44.004315 | AH22: 0 | AI22: 30 | AJ22: 235 | AK22: 15 | AL22: 14 | AM22: 658 | AN22: 38 | AO22: =IF(OR(V22="",AA22=""),"",V22-AA22) -> 1657 | AR22: 990 | AS22: 966 | AT22: Dried | AU22: scaled | AZ22: 44 | BA22: =IF(OR(AG22="",AZ22=""),"",AG22-AZ22) -> 0.004315
A23: DRY-YAK-2026-022 | B23: 22 | C23: 46186 | D23: ANAGROCI-01 | E23: BIN-005 | F23: ANA-05A-DRY | G23: LOT-YAK-2026-BIN-005 | H23: BIN-005 | J23: BIN-005 | P23: BIN-005 | Q23: ANA-05A-DRY | R23: 101655 | S23: 3208 | T23: 98447 | U23: 1322 | V23: 97125 | W23: 101548 | X23: 3740 | Y23: 97808 | Z23: 1325 | AA23: 96483 | AB23: 9 | AC23: 175 | AD23: 43.21 | AE23: 8.1 | AF23: 182 | AG23: =IF(COUNTA(AJ23:AL23)<3,AZ23,(AJ23+0.5*(AK23+AL23))*0.17637) -> 44.357055 | AH23: 3 | AI23: 20 | AJ23: 238 | AK23: 17 | AL23: 10 | AM23: 673 | AN23: 24 | AO23: =IF(OR(V23="",AA23=""),"",V23-AA23) -> 642 | AR23: 1322 | AS23: 1325 | AT23: Dried | AU23: Scaled | AZ23: 44.35 | BA23: =IF(OR(AG23="",AZ23=""),"",AG23-AZ23) -> 0.007055
A24: DRY-YAK-2026-023 | B24: 23 | C24: 46187 | D24: ANAGROCI-01 | E24: BIN-016 | F24: ANA-016-DRY | G24: LOT-YAK-2026-BIN-016 | H24: BIN-016 | J24: 30581 | O24: Direct offload for dry | P24: BIN-016 | Q24: ANA-016-DRY | R24: 37730 | S24: 0 | T24: 37730 | U24: 513 | V24: 37217 | W24: 38195 | X24: 1323 | Y24: 36872 | Z24: 531 | AA24: 36341 | AB24: 10 | AC24: 183 | AD24: 39.85 | AE24: 9 | AF24: 185 | AG24: =IF(COUNTA(AJ24:AL24)<3,AZ24,(AJ24+0.5*(AK24+AL24))*0.17637) -> 39.85962 | AH24: 0 | AI24: 46 | AJ24: 210 | AK24: 15 | AL24: 17 | AM24: 675 | AN24: 29 | AO24: =IF(OR(V24="",AA24=""),"",V24-AA24) -> 876 | AR24: 531 | AS24: 531 | AT24: Dried | AU24: Scaled | AZ24: 39.85 | BA24: =IF(OR(AG24="",AZ24=""),"",AG24-AZ24) -> 0.00962
A25: DRY-YAK-2026-024 | B25: 24 | C25: 46188 | D25: ANAGROCI-01 | E25: BIN-005 | F25: ANA-05A-DRY | G25: LOT-YAK-2026-BIN-005 | H25: BIN-005 | J25: BIN-005 | P25: BIN-005 | Q25: ANA-05A-DRY | R25: 106477.4 | S25: 3234 | T25: 103243.4 | U25: 1353 | V25: 101890.4 | W25: 105951 | X25: 4281 | Y25: 101670 | Z25: 1428 | AA25: 100242 | AB25: 9.5 | AC25: 180 | AD25: 43.47 | AE25: 7.8 | AF25: 177 | AG25: =IF(COUNTA(AJ25:AL25)<3,AZ25,(AJ25+0.5*(AK25+AL25))*0.17637) -> 43.298835 | AH25: 4 | AI25: 31 | AJ25: 231 | AK25: 16 | AL25: 13 | AM25: 688 | AN25: 12 | AO25: =IF(OR(V25="",AA25=""),"",V25-AA25) -> 1648.4 | AR25: 1353 | AS25: 1428 | AT25: Dried | AU25: Scaled | AZ25: 43.29 | BA25: =IF(OR(AG25="",AZ25=""),"",AG25-AZ25) -> 0.008835
A26: DRY-YAK-2026-025 | B26: 25 | C26: 46192 | D26: ANAGROCI-01 | E26: BIN-007 | F26: ANA-07A-DRY | G26: LOT-YAK-2026-BIN-007 | H26: BIN-007 | J26: BIN-007 | P26: BIN-007 | Q26: ANA-07A-DRY | R26: 25319.2 | S26: 698 | T26: 24621.2 | U26: 300 | V26: 24321.2 | W26: 24929.2 | X26: 988.4 | Y26: 23940.8 | Z26: 331 | AA26: 23609.8 | AB26: 10.7 | AC26: 175 | AD26: 39.68 | AE26: 9.4 | AF26: 176 | AG26: =IF(COUNTA(AJ26:AL26)<3,AZ26,(AJ26+0.5*(AK26+AL26))*0.17637) -> 40.5651 | AH26: 2 | AI26: 41 | AJ26: 216 | AK26: 16 | AL26: 12 | AM26: 674 | AN26: 33 | AO26: =IF(OR(V26="",AA26=""),"",V26-AA26) -> 711.4 | AR26: 300 | AS26: 331 | AT26: Dried | AU26: scaled | AZ26: 40.56 | BA26: =IF(OR(AG26="",AZ26=""),"",AG26-AZ26) -> 0.0051
A27: DRY-YAK-2026-026 | B27: 26 | C27: 46193 | D27: ANAGROCI-01 | E27: BIN-007 | F27: ANA-07A-DRY | G27: LOT-YAK-2026-BIN-007 | H27: BIN-007 | J27: BIN-007 | P27: BIN-007 | Q27: ANA-07A-DRY | R27: 24780 | S27: 737.8 | T27: 24042.2 | U27: 300 | V27: 23742.2 | W27: 24704.4 | X27: 1002.6 | Y27: 23701.8 | Z27: 308 | AA27: 23393.8 | AB27: 10.7 | AC27: 175 | AD27: 39.68 | AE27: 9.4 | AF27: 176 | AG27: =IF(COUNTA(AJ27:AL27)<3,AZ27,(AJ27+0.5*(AK27+AL27))*0.17637) -> 40.5651 | AH27: 2 | AI27: 41 | AJ27: 216 | AK27: 16 | AL27: 12 | AM27: 674 | AN27: 33 | AO27: =IF(OR(V27="",AA27=""),"",V27-AA27) -> 348.4 | AR27: 300 | AS27: 308 | AT27: Dried | AU27: scaled | AZ27: 40.56 | BA27: =IF(OR(AG27="",AZ27=""),"",AG27-AZ27) -> 0.0051
A28: DRY-YAK-2026-027 | B28: 27 | C28: 46197 | D28: ANAGROCI-01 | E28: BIN-007 | F28: ANA-07A-DRY | G28: LOT-YAK-2026-BIN-007 | H28: BIN-007 | J28: BIN-007 | P28: BIN-007 | Q28: ANA-07A-DRY | R28: 35380.4 | S28: 1537.2 | T28: 33843.2 | U28: 471 | V28: 33372.2 | W28: 34799.6 | X28: 1442.4 | Y28: 33357.2 | Z28: 449 | AA28: 32908.2 | AB28: 10 | AC28: 176 | AD28: 43.38 | AE28: 8.4 | AF28: 177 | AG28: =IF(COUNTA(AJ28:AL28)<3,AZ28,(AJ28+0.5*(AK28+AL28))*0.17637) -> 43.122465 | AH28: 0 | AI28: 27 | AJ28: 226 | AK28: 15 | AL28: 22 | AM28: 685 | AN28: 17 | AO28: =IF(OR(V28="",AA28=""),"",V28-AA28) -> 464 | AR28: 471 | AS28: 449 | AT28: Dried | AU28: scaled | AZ28: 43.12 | BA28: =IF(OR(AG28="",AZ28=""),"",AG28-AZ28) -> 0.002465
A29: DRY-YAK-2026-028 | B29: 28 | C29: 46198 | D29: ANAGROCI-01 | E29: BIN-007 | F29: ANA-07A-DRY | G29: LOT-YAK-2026-BIN-007 | H29: BIN-007 | J29: BIN-007 | P29: BIN-007 | Q29: ANA-07A-DRY | R29: 70200.8 | S29: 2453.6 | T29: 67747.2 | U29: 897 | V29: 66850.2 | W29: 68894.7 | X29: 2743.4 | Y29: 66151.3 | Z29: 898 | AA29: 65253.3 | AB29: 11.2 | AC29: 173 | AD29: 41.97 | AE29: 9.4 | AF29: 176 | AG29: =IF(COUNTA(AJ29:AL29)<3,AZ29,(AJ29+0.5*(AK29+AL29))*0.17637) -> 42.3288 | AH29: 2 | AI29: 35 | AJ29: 226 | AK29: 16 | AL29: 12 | AM29: 686 | AN29: 27 | AO29: =IF(OR(V29="",AA29=""),"",V29-AA29) -> 1596.9 | AR29: 897 | AS29: 872 | AT29: Dried | AU29: scaled | AZ29: 42.32 | BA29: =IF(OR(AG29="",AZ29=""),"",AG29-AZ29) -> 0.0088
A30: DRY-YAK-2026-029 | B30: 29 | C30: 46199 | D30: ANAGROCI-01 | E30: BIN-007 | F30: ANA-07A-DRY | G30: LOT-YAK-2026-BIN-007 | H30: BIN-007 | J30: BIN-007 | P30: BIN-007 | Q30: ANA-07A-DRY | R30: 35604 | S30: 1090.6 | T30: 34513.4 | U30: 450 | V30: 34063.4 | W30: 35340 | X30: 1256.4 | Y30: 34083.6 | Z30: 459 | AA30: 33624.6 | AB30: 10.4 | AC30: 179 | AD30: 42.94 | AE30: 8.1 | AF30: 180 | AG30: =IF(COUNTA(AJ30:AL30)<3,AZ30,(AJ30+0.5*(AK30+AL30))*0.17637) -> 42.946095 | AH30: 0 | AI30: 33 | AJ30: 230 | AK30: 15 | AL30: 12 | AM30: 676 | AN30: 29 | AO30: =IF(OR(V30="",AA30=""),"",V30-AA30) -> 438.8 | AR30: 450 | AS30: 459 | AT30: Dried | AU30: scaled | AZ30: 42.95 | BA30: =IF(OR(AG30="",AZ30=""),"",AG30-AZ30) -> -0.003905
A31: DRY-YAK-2026-030 | B31: 30 | C31: 46200 | D31: ANAGROCI-01 | E31: BIN-007 | F31: ANA-07A-DRY | G31: LOT-YAK-2026-BIN-007 | H31: BIN-007 | J31: BIN-007 | P31: BIN-007 | Q31: ANA-07A-DRY | R31: 61590 | S31: 1839.4 | T31: 59750.6 | U31: 750 | V31: 59000.6 | W31: 61125.2 | X31: 2548.4 | Y31: 58576.8 | Z31: 787 | AA31: 57789.8 | AB31: 9.8 | AC31: 179 | AD31: 42.86 | AE31: 8 | AF31: 176 | AG31: =IF(COUNTA(AJ31:AL31)<3,AZ31,(AJ31+0.5*(AK31+AL31))*0.17637) -> 42.85791 | AH31: 0 | AI31: 33 | AJ31: 226 | AK31: 18 | AL31: 16 | AM31: 679 | AN31: 22 | AO31: =IF(OR(V31="",AA31=""),"",V31-AA31) -> 1210.8 | AR31: 750 | AS31: 787 | AT31: Dried | AU31: scaled | AZ31: 42.85 | BA31: =IF(OR(AG31="",AZ31=""),"",AG31-AZ31) -> 0.00791

Sheet Drying & Sorting
A1: Row ID | B1: No | C1: Date | D1: Warehouse | E1: Unloading Bin | F1: After Drying Bin | G1: Lot No | H1: Warehouse Receipt No | I1: Origin | J1: Supplier Name | K1: Supplier Code (Anagroci) | L1: Supplier Code (CCAK) | M1: Issued Net Weight, GRN (kg) | N1: Received Net Weight After Drying (kg) | O1: Input Moisture (%) | P1: Input Nut Count | Q1: Input KOR | R1: Output Moisture (%) | S1: Output Nut Count | T1: Output KOR | U1: Drying Loss (kg) | V1: Damaged Nuts, Triage (kg) | W1: Input Bags for Drying | X1: Output Bags After Drying | Y1: Drying or Picking | Z1: Remarks
A2: DS-BKE-2026-001 | B2: 1 | C2: 46073 | D2: BKE-002 | E2: BKE-002-BIN-003 | F2: BKE-002-BIN-003- DRIED | G2: 13 | H2: 813, 805 | I2: KOUNAHIRI/ MANKONO | J2: DAGNOGO KARIM/SCOPPAS SCOOPS | K2: LBA-013-DAG/ LBA-009-SCO | L2: 0525-0068/ 0426-0203 | M2: 33917 | N2: 33408.245 | O2: 11 | P2: 161/ 180 | Q2: 47.61 | R2: 9.5 | S2: 176 | T2: 47.26 | U2: =IF(OR(M2="",N2=""),"",M2-N2) -> 508.755 | W2: 406 | X2: 434 | Y2: DRYING
A3: DS-BKE-2026-002 | B3: 2 | C3: 46074 | D3: BKE-002 | E3: BKE-002-BIN-004 | F3: BKE-002-BIN-004-DRIED | G3: 8 | H3: 807, 809 | I3: NIAKARA/ NIAKARA | J3: DAGNOGO KARIM/SCOOPS HERE B | K3: LBA-013-DAG/ LBA-003-HER | L3: 0525-0068/ 0425-0187 | M3: 25265 | N3: 24835.495 | O3: 11.4 | P3: 160/ 162 | Q3: 46.39 | R3: 9.7 | S3: 171 | T3: 46.73 | U3: =IF(OR(M3="",N3=""),"",M3-N3) -> 429.505 | V3: 216 | W3: 290 | X3: 320 | Y3: DRYING+PICKING
A4: DS-BKE-2026-003 | B4: 3 | C4: 46076 | D4: BKE-002 | E4: BKE-002-BIN-003 | F4: BKE-002-BIN-003- DRIED | G4: 13 | H4: 813, 805 | I4: KOUNAHIRI/ MANKONO | J4: DAGNOGO KARIM/SCOPPAS SCOOPS | K4: LBA-013-DAG/ LBA-009-SCO | L4: 0525-0068/ 0426-0203 | M4: 29573 | N4: 29129.405 | O4: 11 | P4: 161/ 180 | Q4: 47.61 | R4: 9.5 | S4: 176 | T4: 47.26 | U4: =IF(OR(M4="",N4=""),"",M4-N4) -> 443.595 | W4: 354 | X4: 386 | Y4: DRYING
A5: DS-BKE-2026-004 | B5: 4 | C5: 46078 | D5: BKE-002 | E5: BKE-002-BIN-003 | F5: BKE-002-BIN-003- DRIED | G5: 13 | H5: 813, 805 | I5: KOUNAHIRI/ MANKONO | J5: DAGNOGO KARIM/SCOPPAS SCOOPS | K5: LBA-013-DAG/ LBA-009-SCO | L5: 0525-0068/ 0426-0203 | M5: 35276 | N5: 34746.86 | O5: 11 | P5: 161/ 180 | Q5: 47.61 | R5: 9.5 | S5: 176 | T5: 47.26 | U5: =IF(OR(M5="",N5=""),"",M5-N5) -> 529.14 | V5: 76 | W5: 416 | X5: 442 | Y5: DRYING+PICKING
A6: DS-BKE-2026-005 | B6: 5 | C6: 46079 | D6: BKE-002 | E6: BKE-002-BIN-004 | F6: BKE-002-BIN-004-DRIED | G6: 8 | H6: 807, 809 | I6: KOUNAHIRI/ MANKONO | J6: DAGNOGO KARIM/SCOOPS HERE B | K6: LBA-013-DAG/ LBA-003-HER | L6: 0525-0068/ 0425-0187 | M6: 21780 | N6: 21409.74 | O6: 11.4 | P6: 160/ 162 | Q6: 46.39 | R6: 9.7 | S6: 171 | T6: 46.73 | U6: =IF(OR(M6="",N6=""),"",M6-N6) -> 370.26 | V6: 43 | W6: 250 | X6: 259 | Y6: DRYING+PICKING
A7: DS-BKE-2026-006 | B7: 6 | C7: 46080 | D7: BKE-002 | E7: BKE-002-BIN-004 | F7: BKE-002-BIN-004-DRIED | G7: 8 | H7: 807, 809 | I7: KOUNAHIRI/ MANKONO | J7: DAGNOGO KARIM/SCOOPS HERE B | K7: LBA-013-DAG/ LBA-003-HER | L7: 0525-0068/ 0425-0187 | M7: 26224 | N7: 25778.192 | O7: 11.4 | P7: 160/ 162 | Q7: 46.39 | R7: 9.7 | S7: 171 | T7: 46.73 | U7: =IF(OR(M7="",N7=""),"",M7-N7) -> 445.808 | V7: 64 | W7: 301 | X7: 335 | Y7: DRYING+PICKING
A8: DS-BKE-2026-007 | B8: 7 | C8: 46084 | D8: BKE-002 | E8: BKE-002-BIN-004 | F8: BKE-002-BIN-004-DRIED | G8: 8 | H8: 807, 809 | I8: KOUNAHIRI/ MANKONO | J8: DAGNOGO KARIM/SCOOPS HERE B | K8: LBA-013-DAG/ LBA-003-HER | L8: 0525-0068/ 0425-0187 | M8: 12198 | N8: 11990.634 | O8: 11.4 | P8: 160/ 162 | Q8: 46.39 | R8: 9.7 | S8: 171 | T8: 46.73 | U8: =IF(OR(M8="",N8=""),"",M8-N8) -> 207.366 | V8: 42 | W8: 140 | X8: 126 | Y8: DRYING+PICKING
A9: DS-BKE-2026-008 | B9: 8 | C9: 46084 | D9: BKE-001 | E9: BKE-001-BIN-007 | F9: BKE-001-BIN-007-DRIED | G9: 112 | H9: 1214 | I9: FERKE | J9: SCOOPS ASER | K9: LBA-011-ASR | L9: 0426-0340 | M9: 12102 | N9: 11859.96 | O9: 11.7 | P9: 170 | Q9: 47.27 | R9: 9.7 | S9: 178 | T9: 47.44 | U9: =IF(OR(M9="",N9=""),"",M9-N9) -> 242.04 | V9: 53 | W9: 160 | X9: 139 | Y9: DRYING+PICKING
A10: DS-BKE-2026-009 | B10: 9 | C10: 46115 | D10: BKE-001 | E10: BKE-001-BIN-016 | F10: BKE-001-BIN-016-DRIED | G10: 113 | H10: 1215 | I10: BOTRO | J10: SCOOPASS | K10: DIS-007-SPA | M10: 22371 | N10: 22057.806 | O10: 10.5 | P10: 177 | Q10: 47.27 | R10: 9.1 | S10: 180 | T10: 47.61 | U10: =IF(OR(M10="",N10=""),"",M10-N10) -> 313.194 | W10: 257 | X10: 285 | Y10: DRYING
A11: DS-BKE-2026-010 | B11: 10 | C11: 46145 | D11: BKE-002 | E11: BKE-002-BIN-014 | F11: BKE-002-BIN-014-DRIED | G11: 58 | H11: 760 | I11: PRIKRO | J11: CAPCD SCOOPS | K11: LBA-010-CAP | L11: 0431-0277 | M11: 33414 | N11: 33046.446 | O11: 10.3 | P11: 183 | Q11: 48.15 | R11: 9.2 | S11: 185 | T11: 48.32 | U11: =IF(OR(M11="",N11=""),"",M11-N11) -> 367.554 | W11: 384 | X11: 127 | Y11: DRYING | Z11: RAIN
A12: DS-BKE-2026-011 | B12: 11 | C12: 46176 | D12: BKE-002 | E12: BKE-002-BIN-014 | F12: BKE-002-BIN-014-DRIED | G12: 58 | H12: 760 | I12: PRIKRO | J12: CAPCD SCOOPS | K12: LBA-010-CAP | L12: 0431-0277 | M12: 22363 | N12: 22117.007 | O12: 10.3 | P12: 183 | Q12: 48.15 | R12: 9.2 | S12: 185 | T12: 48.32 | U12: =IF(OR(M12="",N12=""),"",M12-N12) -> 245.993 | W12: 257 | X12: 295 | Y12: REDRYING
A13: DS-BKE-2026-012 | B13: 12 | C13: 46090 | D13: BKE-001 | E13: BKE-001-BIN-007 | F13: BKE-001-BIN-007-DRIED | G13: 112 | H13: 1214 | I13: FERKE | J13: SCOOPS ASER | K13: LBA-011-ASR | L13: 0426-0340 | M13: 10060 | N13: 9858.8 | O13: 11.7 | P13: 170 | Q13: 47.27 | R13: 9.7 | S13: 178 | T13: 47.44 | U13: =IF(OR(M13="",N13=""),"",M13-N13) -> 201.2 | V13: 263 | W13: 133 | X13: 135 | Y13: DRYING+PICKING
A14: DS-BKE-2026-013 | B14: 13 | C14: 46090 | D14: BKE-002 | E14: BKE-002-BIN-014 | F14: BKE-002-BIN-014-DRIED | G14: 58 | H14: 760 | I14: PRIKRO | J14: CAPCD SCOOPS | K14: LBA-010-CAP | L14: 0431-0277 | M14: 8267 | N14: 8176.063 | O14: 10.3 | P14: 183 | Q14: 48.15 | R14: 9.2 | S14: 185 | T14: 48.32 | U14: =IF(OR(M14="",N14=""),"",M14-N14) -> 90.937 | W14: 95 | X14: 127 | Y14: DRYING
A15: DS-BKE-2026-014 | B15: 14 | C15: 46091 | D15: BKE-001 | E15: BKE-001-BIN-007 | F15: BKE-001-BIN-007-DRIED | G15: 112 | H15: 1214 | I15: FERKE | J15: SCOOPS ASER | K15: LBA-011-ASR | L15: 0426-0340 | M15: 20498 | N15: 20088.04 | O15: 11.7 | P15: 170 | Q15: 47.27 | R15: 9.7 | S15: 178 | T15: 47.44 | U15: =IF(OR(M15="",N15=""),"",M15-N15) -> 409.96 | V15: 207 | W15: 271 | X15: 262 | Y15: DRYING+PICKING
A16: DS-BKE-2026-015 | B16: 15 | C16: 46097 | D16: BKE-001 | E16: BKE-001-BIN-015 | F16: BKE-001-BIN-015-DRIED | G16: 206 | H16: 108 | I16: DABAKALA | J16: SCOOPS HERE B | K16: LBA-003-HER | L16: 0425-0187 | M16: 39325 | N16: 38459.85 | O16: 12.2 | P16: 189 | Q16: 45.15 | R16: 10 | S16: 185 | T16: 45.32 | U16: =IF(OR(M16="",N16=""),"",M16-N16) -> 865.15 | V16: 120 | W16: 475 | X16: 474 | Y16: DRYING+PICKING
A17: DS-BKE-2026-016 | B17: 16 | C17: 46098 | D17: BKE-001 | E17: BKE-001-BIN-016 | F17: BKE-001-BIN-016-DRIED | G17: 207 | H17: 109 | I17: KATIOLA | J17: SCOOPS AH AL NOUR | K17: LBA-016-NOU | L17: 0425-0055 | M17: 43088 | N17: 42441.68 | O17: 11 | P17: 164 | Q17: 46.03 | R17: 9.5 | S17: 171 | T17: 46.56 | U17: =IF(OR(M17="",N17=""),"",M17-N17) -> 646.32 | V17: 163 | W17: 512 | X17: 523 | Y17: DRYING+PICKING
A18: DS-BKE-2026-017 | B18: 17 | C18: 46108 | D18: BKE-002 | E18: BKE-002-BIN-006 | F18: BKE-002-BIN-006-DRIED | G18: 12 | H18: 809, 790 | I18: DIANRA/ NIAKARA | J18: CAPCD SCOOPS/ SCOOPS HERE B | K18: LBA-010-CAP/ LBA-003-HER | L18: 0431-0277/ 0425-0187 | M18: 30456 | N18: 29877.336 | O18: 11.2 | P18: 168/ 161 | Q18: 48.19 | R18: 9.3 | S18: 177 | T18: 47.97 | U18: =IF(OR(M18="",N18=""),"",M18-N18) -> 578.664 | W18: 376 | X18: 381 | Y18: DRYING
A19: DS-BKE-2026-018 | B19: 18 | C19: 46111 | D19: BKE-002 | E19: BKE-002-BIN-006 | F19: BKE-002-BIN-006-DRIED | G19: 12 | H19: 809, 790 | I19: DIANRA/ NIAKARA | J19: CAPCD SCOOPS/ SCOOPS HERE B | K19: LBA-010-CAP/ LBA-003-HER | L19: 0431-0277/ 0425-0187 | M19: 20331 | N19: 19944.711 | O19: 11.2 | P19: 168/ 161 | Q19: 48.19 | R19: 9.3 | S19: 177 | T19: 47.97 | U19: =IF(OR(M19="",N19=""),"",M19-N19) -> 386.289 | W19: 251 | X19: 268 | Y19: DRYING
A20: DS-BKE-2026-019 | B20: 19 | C20: 46112 | D20: BKE-002 | E20: BKE-002-BIN-006 | F20: BKE-002-BIN-006-DRIED | G20: 12 | H20: 809, 790 | I20: DIANRA/ NIAKARA | J20: CAPCD SCOOPS/ SCOOPS HERE B | K20: LBA-010-CAP/ LBA-003-HER | L20: 0431-0277/ 0425-0187 | M20: 30780 | N20: 30195.18 | O20: 11.2 | P20: 168/ 161 | Q20: 48.19 | R20: 9.3 | S20: 177 | T20: 47.97 | U20: =IF(OR(M20="",N20=""),"",M20-N20) -> 584.82 | W20: 380 | X20: 413 | Y20: DRYING
A21: DS-BKE-2026-020 | B21: 20 | C21: 46116 | D21: BKE-001 | E21: BKE-001-BIN-021 | F21: BKE-001-BIN-021-DRIED | G21: 262 | H21: 1164 | I21: DUEKOUE | J21: SCOOPS ASER | K21: LBA-011-ASR | L21: 0426-0340 | M21: 32006 | N21: 31301.868 | O21: 11.6 | P21: 168 | Q21: 44.97 | R21: 9.4 | S21: 174 | T21: 45.15 | U21: =IF(OR(M21="",N21=""),"",M21-N21) -> 704.132 | V21: 275 | W21: 319 | X21: 312 | Y21: DRYING+PICKING
A22: DS-BKE-2026-021 | B22: 21 | C22: 46116 | D22: BKE-001 | E22: BKE-001-BIN-018 | F22: BKE-001-BIN-018-DRIED | G22: 246253 | H22: 1481155 | I22: DUEKOUE, KOUNAHIRI | J22: SCOOPS ASER/ SCOOPS COBAN | K22: LBA-011-ASR/ LBA-008-COB | L22: 0426-0340/ 0410-0149 | M22: 35827 | N22: 35325.422 | O22: 11 | P22: 173, 163 | Q22: 44.09 | R22: 9.6 | S22: 174 | T22: 44.35 | U22: =IF(OR(M22="",N22=""),"",M22-N22) -> 501.578 | V22: 291 | W22: 423 | X22: 433 | Y22: DRYING+PICKING
A23: DS-BKE-2026-022 | B23: 22 | C23: 46119 | D23: BKE-001 | E23: BKE-001-BIN-018 | F23: BKE-001-BIN-018-DRIED | G23: 246253 | H23: 1481155 | I23: DUEKOUE, KOUNAHIRI | J23: SCOOPS ASER/ SCOOPS COBAN | K23: LBA-011-ASR/ LBA-008-COB | L23: 0426-0340/ 0420-0149 | M23: 24223 | N23: 23883.878 | O23: 11 | P23: 173, 163 | Q23: 44.09 | R23: 9.6 | S23: 174 | T23: 44.35 | U23: =IF(OR(M23="",N23=""),"",M23-N23) -> 339.122 | V23: 398 | W23: 286 | X23: 292 | Y23: DRYING+PICKING
A24: DS-BKE-2026-023 | B24: 23 | C24: 46121 | D24: BKE-001 | E24: BKE-001-BIN-018 | F24: BKE-001-BIN-018-DRIED | G24: 246253 | H24: 1481155 | I24: DUEKOUE, KOUNAHIRI | J24: SCOOPS ASER/ SCOOPS COBAN | K24: LBA-011-ASR/ LBA-008-COB | L24: 0426-0340/ 0420-0149 | M24: 44466 | N24: 43843.476 | O24: 11 | P24: 173, 163 | Q24: 44.09 | R24: 9.6 | S24: 174 | T24: 44.35 | U24: =IF(OR(M24="",N24=""),"",M24-N24) -> 622.524 | V24: 177 | W24: 525 | X24: 518 | Y24: DRYING+PICKING
A25: DS-BKE-2026-024 | B25: 24 | C25: 46125 | D25: BKE-002 | E25: BKE-002-BIN-028 | F25: BKE-002-BIN-028-DRIED | G25: 315 | H25: 1117 | J25: SCOOPS BAY SCOOPS | K25: LBA-014-BAY | L25: 0426-0194 | M25: 19100 | N25: 18507.9 | O25: 13.3 | P25: 161 | Q25: 42.51 | R25: 10.2 | S25: 169 | T25: 42.15 | U25: =IF(OR(M25="",N25=""),"",M25-N25) -> 592.1 | V25: 543 | W25: 232 | X25: 228 | Y25: DRYING+PICKING
A26: DS-BKE-2026-025 | B26: 25 | C26: 46141 | D26: BKE-001 | E26: BKE-001-BIN-024 | F26: BKE-001-BIN-024-DRIED | G26: 415 | H26: 367 | I26: ZOUKOUGBOU | J26: CAPCD SCOOPS | K26: LBA-010-CAP | L26: 0431-0277 | M26: 32868 | N26: 31914.828 | O26: 12.3 | P26: 163 | Q26: 42.50517 | R26: 9.4 | S26: 174 | T26: 43.03 | U26: =IF(OR(M26="",N26=""),"",M26-N26) -> 953.172 | V26: 87 | W26: 432 | X26: 439 | Y26: DRYING+PICKING
A27: DS-BKE-2026-026 | B27: 26 | C27: 46142 | D27: BKE-001 | E27: BKE-001-BIN-023 | F27: BKE-001-BIN-023-DRIED | G27: 429 | H27: 381 | I27: KORHOGO | J27: SCOOPS COOPRAKA | K27: LBA-018-COP | L27: 0425-0001 | M27: 22180 | N27: 21558 | O27: 11.6 | P27: 162 | Q27: 41.27 | R27: 10.4 | S27: 168 | T27: 41.79 | U27: =IF(OR(M27="",N27=""),"",M27-N27) -> 622 | V27: 127 | W27: 250 | X27: 276 | Y27: DRYING+PICKING
A28: DS-BKE-2026-027 | B28: 27 | C28: 46146 | D28: BKE-002 | E28: BKE-002-BIN-028 | F28: BKE-002-BIN-028-DRIED | G28: 407 | H28: 359 | I28: MBAHIAKRO | J28: SCOOPS BAY SCOOPS | K28: LBA-014-BAY | L28: 0426-0194 | M28: 16214 | N28: 15889 | O28: 11.6 | P28: 175 | Q28: 42.15 | R28: 10 | S28: 179 | T28: 42.5 | U28: =IF(OR(M28="",N28=""),"",M28-N28) -> 325 | V28: 115 | W28: 210 | X28: 221 | Y28: DRYING+PICKING
A29: DS-BKE-2026-028 | B29: 28 | C29: 46147 | D29: BKE-001 | E29: BKE-001-BIN-023 | F29: BKE-001-BIN-023-DRIED | G29: 387 | H29: 289353 | I29: DIANRA | J29: CASP-S SCOOPS, SCOOPS DIENE | K29: LBA-007-CAS | L29: 0429-0040 | M29: 27370 | N29: 26540 | O29: 11.9 | P29: 166 | Q29: 41.09 | R29: 9.7 | S29: 169 | T29: 42.06 | U29: =IF(OR(M29="",N29=""),"",M29-N29) -> 830 | V29: 122 | W29: 322 | X29: 319 | Y29: DRYING+PICKING
A30: DS-BKE-2026-029 | B30: 29 | C30: 46148 | D30: BKE-001 | E30: BKE-001-BIN-023 | F30: BKE-001-BIN-023-DRIED | G30: 453 | H30: 305 | I30: BOUAKE | J30: SCOOPS OUMI | K30: LBA-015-OUM | L30: 0426-0347 | M30: 27572 | N30: 26883 | O30: 14 | P30: 181 | Q30: 42.15 | R30: 12.1 | U30: =IF(OR(M30="",N30=""),"",M30-N30) -> 689 | V30: 146 | W30: 335 | X30: 351 | Y30: DRYING+PICKING
A31: DS-BKE-2026-030 | B31: 30 | C31: 46150 | D31: BKE-001 | E31: BKE-001-BIN-023 | F31: BKE-001-BIN-023-DRIED | G31: 453 | H31: 305 | I31: BOUAKE | J31: SCOOPS OUMI | K31: LBA-015-OUM | L31: 0426-0347 | M31: 26470 | N31: 25862 | O31: 12.1 | P31: 181 | Q31: 42.15 | R31: 9.8 | S31: 185 | T31: 43.21 | U31: =IF(OR(M31="",N31=""),"",M31-N31) -> 608 | W31: 351 | X31: 352 | Y31: DRYING

Sheet Dispatch
A1: Row ID | B1: No | C1: Loading Date | D1: Voyage Number | E1: Remarks | F1: Scale Location | G1: Warehouse | H1: Warehouse or Direct | I1: Bin | J1: Origin | K1: Truck No | L1: Transporter | M1: Driver | N1: Phone | O1: Warehouse Receipt No | P1: Fiche CCA No | Q1: Bags Loaded (This Bin) | R1: Total Bags | S1: Gross Weight (kg) | T1: Net Weight (kg) | U1: Status | V1: Unloading Status | W1: Rejection (g) | X1: Void (g) | Y1: Oil (g) | Z1: Total Defect (g) | AA1: Good Kernel (g) | AB1: Immature (g) | AC1: Spotted (g) | AD1: Total Kernels (g) | AE1: KOR | AF1: Shot | AG1: FOT | AH1: Useful Kernels Yield (%) | AI1: Total Yield (%) | AJ1: Moisture (%) | AK1: Nut Count | AL1: Shell (g) | AM1: Historical KOR | AN1: KOR Variance
A2: DSP-BKE-2026-001 | B2: 1 | C2: 46098 | D2: BKT001 | F2: INSIDE | G2: BKE-002 | H2: WH | I2: BKE-002-BIN-012 | J2: BOUAKE | K2: 1796GC01/3922BB04 | L2: SONEL TRANS | M2: TRAOREBAKARY | N2: 715347075 | O2: 951 | P2: 51505 | Q2: 951 | R2: 590 | S2: 48880 | T2: 48290 | U2: REACHED | V2: UNLOADED | W2: 20 | X2: 53 | Y2: 4 | Z2: =IF(COUNTA(W2:Y2)=0,"",SUM(W2:Y2)) -> 77 | AA2: 243 | AB2: 4 | AC2: 22 | AD2: =IF(COUNTA(AA2:AC2)=0,"",SUM(AA2:AC2)) -> 269 | AE2: =IF(COUNTA(AA2:AC2)<3,"",(AA2+0.5*(AB2+AC2))*0.17637) -> 45.15072 | AF2: =IF(AD2="","",AD2*0.17637) -> 47.44353 | AG2: =IF(COUNTA(Y2,W2,AA2:AC2)=0,"",(Y2+W2+AA2+AB2+AC2)*0.17637) -> 51.67641 | AH2: =IF(AD2="","",AD2/1000) -> 0.269 | AI2: =IF(COUNTA(W2,Y2,AA2:AC2)=0,"",SUM(W2,Y2,AA2:AC2)/1000) -> 0.293 | AJ2: 8.8 | AK2: 172 | AL2: 647 | AM2: 45.15072 | AN2: =IF(OR(AE2="",AM2=""),"",AE2-AM2) -> 0
A3: DSP-BKE-2026-002 | B3: 2 | C3: 46098 | D3: BKT002 | F3: INSIDE | G3: BKE-002 | H3: WH | I3: BKE-002-BIN-012 | J3: BOUAKE | K3: 7957-GN-01/3599-KV-01 | L3: CAMARA MAGAH | M3: DOSSOADAMA | N3: 504367884 | O3: 952 | P3: 51506 | Q3: 952 | R3: 590 | S3: 48680 | T3: 48090 | U3: REACHED | V3: UNLOADED | W3: 12 | X3: 62 | Y3: 0 | Z3: =IF(COUNTA(W3:Y3)=0,"",SUM(W3:Y3)) -> 74 | AA3: 247 | AB3: 4 | AC3: 20 | AD3: =IF(COUNTA(AA3:AC3)=0,"",SUM(AA3:AC3)) -> 271 | AE3: =IF(COUNTA(AA3:AC3)<3,"",(AA3+0.5*(AB3+AC3))*0.17637) -> 45.67983 | AF3: =IF(AD3="","",AD3*0.17637) -> 47.79627 | AG3: =IF(COUNTA(Y3,W3,AA3:AC3)=0,"",(Y3+W3+AA3+AB3+AC3)*0.17637) -> 49.91271 | AH3: =IF(AD3="","",AD3/1000) -> 0.271 | AI3: =IF(COUNTA(W3,Y3,AA3:AC3)=0,"",SUM(W3,Y3,AA3:AC3)/1000) -> 0.283 | AJ3: 9.2 | AK3: 171 | AL3: 648 | AM3: 45.67983 | AN3: =IF(OR(AE3="",AM3=""),"",AE3-AM3) -> 0
A4: DSP-BKE-2026-003 | B4: 3 | C4: 46098 | D4: BKT003 | F4: INSIDE | G4: BKE-002 | H4: WH | I4: BKE-001-BIN-016 | J4: BOUAKE | K4: 3334-FN-01 | L4: CAMARA MAGAH | M4: DIABYMAMOUDOU | N4: 709456630 | O4: 953 | P4: 51507 | Q4: 953 | R4: 523 | S4: 42140 | T4: 41617 | U4: REACHED | V4: UNLOADED | W4: 18 | X4: 48 | Y4: 0 | Z4: =IF(COUNTA(W4:Y4)=0,"",SUM(W4:Y4)) -> 66 | AA4: 252 | AB4: 4 | AC4: 24 | AD4: =IF(COUNTA(AA4:AC4)=0,"",SUM(AA4:AC4)) -> 280 | AE4: =IF(COUNTA(AA4:AC4)<3,"",(AA4+0.5*(AB4+AC4))*0.17637) -> 46.91442 | AF4: =IF(AD4="","",AD4*0.17637) -> 49.3836 | AG4: =IF(COUNTA(Y4,W4,AA4:AC4)=0,"",(Y4+W4+AA4+AB4+AC4)*0.17637) -> 52.55826 | AH4: =IF(AD4="","",AD4/1000) -> 0.28 | AI4: =IF(COUNTA(W4,Y4,AA4:AC4)=0,"",SUM(W4,Y4,AA4:AC4)/1000) -> 0.298 | AJ4: 9.3 | AK4: 177 | AL4: 649 | AM4: 46.91442 | AN4: =IF(OR(AE4="",AM4=""),"",AE4-AM4) -> 0
A5: DSP-BKE-2026-004 | B5: 4 | C5: 46099 | D5: BKT004 | F5: INSIDE | G5: BKE-002 | H5: WH | I5: BKE-002-BIN-012 | J5: BOUAKE | K5: 847HH04/850HH04 | L5: CAMARA MAGAH | M5: KONEZAKARIDJA | N5: 586985450 | O5: 954 | P5: 51508 | Q5: 954 | R5: 526 | S5: 41420 | T5: 40894 | U5: REACHED | V5: UNLOADED | W5: 12 | X5: 57 | Y5: 6 | Z5: =IF(COUNTA(W5:Y5)=0,"",SUM(W5:Y5)) -> 75 | AA5: 248 | AB5: 4 | AC5: 16 | AD5: =IF(COUNTA(AA5:AC5)=0,"",SUM(AA5:AC5)) -> 268 | AE5: =IF(COUNTA(AA5:AC5)<3,"",(AA5+0.5*(AB5+AC5))*0.17637) -> 45.50346 | AF5: =IF(AD5="","",AD5*0.17637) -> 47.26716 | AG5: =IF(COUNTA(Y5,W5,AA5:AC5)=0,"",(Y5+W5+AA5+AB5+AC5)*0.17637) -> 50.44182 | AH5: =IF(AD5="","",AD5/1000) -> 0.268 | AI5: =IF(COUNTA(W5,Y5,AA5:AC5)=0,"",SUM(W5,Y5,AA5:AC5)/1000) -> 0.286 | AJ5: 8 | AK5: 171 | AL5: 653 | AM5: 45.50346 | AN5: =IF(OR(AE5="",AM5=""),"",AE5-AM5) -> 0
A6: DSP-BKE-2026-005 | B6: 5 | C6: 46099 | D6: BKT005 | F6: INSIDE | G6: DIRECT-001 | H6: DIRECT | I6: DIRECT-001 | J6: BOUAKE | K6: 9008JH04/9011JH04 | L6: CAMARA MAGAH | M6: SANOGOOUMAR | N6: 171714514 | O6: 955 | P6: 52047 | Q6: 955 | R6: 592 | S6: 50760 | T6: 50168 | U6: REACHED | V6: UNLOADED | W6: 11 | X6: 59 | Y6: 0 | Z6: =IF(COUNTA(W6:Y6)=0,"",SUM(W6:Y6)) -> 70 | AA6: 251 | AB6: 2 | AC6: 18 | AD6: =IF(COUNTA(AA6:AC6)=0,"",SUM(AA6:AC6)) -> 271 | AE6: =IF(COUNTA(AA6:AC6)<3,"",(AA6+0.5*(AB6+AC6))*0.17637) -> 46.03257 | AF6: =IF(AD6="","",AD6*0.17637) -> 47.79627 | AG6: =IF(COUNTA(Y6,W6,AA6:AC6)=0,"",(Y6+W6+AA6+AB6+AC6)*0.17637) -> 49.73634 | AH6: =IF(AD6="","",AD6/1000) -> 0.271 | AI6: =IF(COUNTA(W6,Y6,AA6:AC6)=0,"",SUM(W6,Y6,AA6:AC6)/1000) -> 0.282 | AJ6: 12 | AK6: 155 | AL6: 653 | AM6: 46.03257 | AN6: =IF(OR(AE6="",AM6=""),"",AE6-AM6) -> 0
A7: DSP-BKE-2026-006 | B7: 6 | C7: 46104 | D7: BKT006 | F7: INSIDE | G7: DIRECT-002 | H7: DIRECT | I7: DIRECT-002 | J7: BOUAKE | K7: AA244BT03/3762BN01 | L7: CAMARA MAGAH | M7: SYLLAYACOUBA | N7: 715464786 | O7: 956 | P7: 51515 | Q7: 956 | R7: 678 | S7: 54940 | T7: 54262 | U7: REACHED | V7: UNLOADED | W7: 10 | X7: 78 | Y7: 0 | Z7: =IF(COUNTA(W7:Y7)=0,"",SUM(W7:Y7)) -> 88 | AA7: 241 | AB7: 6 | AC7: 28 | AD7: =IF(COUNTA(AA7:AC7)=0,"",SUM(AA7:AC7)) -> 275 | AE7: =IF(COUNTA(AA7:AC7)<3,"",(AA7+0.5*(AB7+AC7))*0.17637) -> 45.50346 | AF7: =IF(AD7="","",AD7*0.17637) -> 48.50175 | AG7: =IF(COUNTA(Y7,W7,AA7:AC7)=0,"",(Y7+W7+AA7+AB7+AC7)*0.17637) -> 50.26545 | AH7: =IF(AD7="","",AD7/1000) -> 0.275 | AI7: =IF(COUNTA(W7,Y7,AA7:AC7)=0,"",SUM(W7,Y7,AA7:AC7)/1000) -> 0.285 | AJ7: 10.7 | AK7: 183 | AL7: 633 | AM7: 45.50346 | AN7: =IF(OR(AE7="",AM7=""),"",AE7-AM7) -> 0
A8: DSP-BKE-2026-007 | B8: 7 | C8: 46104 | D8: BKT007 | E8: MULTI-BIN / MULTI-LINE LOAD | F8: INSIDE | G8: BKE-002 | H8: WH | I8: BKE-002-BIN-012 | J8: BOUAKE | K8: 997JY01/4285CH04 | L8: CAMARA MAGAH | M8: BERTHEADAMA | N8: 531130081 | O8: 957 | P8: 51514 | Q8: 344 | R8: 494 | S8: 27990 | T8: 27646 | U8: REACHED | V8: UNLOADED | W8: 11 | X8: 75 | Y8: 0 | Z8: =IF(COUNTA(W8:Y8)=0,"",SUM(W8:Y8)) -> 86 | AA8: 243 | AB8: 8 | AC8: 16 | AD8: =IF(COUNTA(AA8:AC8)=0,"",SUM(AA8:AC8)) -> 267 | AE8: =IF(COUNTA(AA8:AC8)<3,"",(AA8+0.5*(AB8+AC8))*0.17637) -> 44.97435 | AF8: =IF(AD8="","",AD8*0.17637) -> 47.09079 | AG8: =IF(COUNTA(Y8,W8,AA8:AC8)=0,"",(Y8+W8+AA8+AB8+AC8)*0.17637) -> 49.03086 | AH8: =IF(AD8="","",AD8/1000) -> 0.267 | AI8: =IF(COUNTA(W8,Y8,AA8:AC8)=0,"",SUM(W8,Y8,AA8:AC8)/1000) -> 0.278 | AJ8: 9.8 | AK8: 177 | AL8: 642 | AM8: 44.97435 | AN8: =IF(OR(AE8="",AM8=""),"",AE8-AM8) -> 0
A9: DSP-BKE-2026-008 | B9: 8 | C9: 46104 | D9: BKT007 | E9: MULTI-BIN / MULTI-LINE LOAD | G9: BKE-001 | H9: WH | I9: BKE-001-BIN-008 | J9: BOUAKE | K9: 997JY01/4285CH04 | L9: CAMARA MAGAH | M9: BERTHEADAMA | N9: 531130081 | O9: 957 | P9: 51514 | Q9: 150 | R9: 0 | S9: 12210 | T9: 12060 | Z9: =IF(COUNTA(W9:Y9)=0,"",SUM(W9:Y9)) | AD9: =IF(COUNTA(AA9:AC9)=0,"",SUM(AA9:AC9)) | AE9: =IF(COUNTA(AA9:AC9)<3,"",(AA9+0.5*(AB9+AC9))*0.17637) | AF9: =IF(AD9="","",AD9*0.17637) | AG9: =IF(COUNTA(Y9,W9,AA9:AC9)=0,"",(Y9+W9+AA9+AB9+AC9)*0.17637) | AH9: =IF(AD9="","",AD9/1000) | AI9: =IF(COUNTA(W9,Y9,AA9:AC9)=0,"",SUM(W9,Y9,AA9:AC9)/1000) | AN9: =IF(OR(AE9="",AM9=""),"",AE9-AM9)
A10: DSP-BKE-2026-009 | B10: 9 | C10: 46104 | D10: BKT008 | F10: INSIDE | G10: DIRECT-003 | H10: DIRECT | I10: DIRECT-003 | J10: BOUAKE | K10: 827KT01/57AY01 | L10: CAMARA MAGAH | M10: COULIBALYKARIGA | N10: 748503977 | O10: 958 | P10: 51510 | Q10: 958 | R10: 511 | S10: 40280 | T10: 39769 | U10: REACHED | V10: UNLOADED | W10: 12 | X10: 74 | Y10: 0 | Z10: =IF(COUNTA(W10:Y10)=0,"",SUM(W10:Y10)) -> 86 | AA10: 250 | AB10: 6 | AC10: 14 | AD10: =IF(COUNTA(AA10:AC10)=0,"",SUM(AA10:AC10)) -> 270 | AE10: =IF(COUNTA(AA10:AC10)<3,"",(AA10+0.5*(AB10+AC10))*0.17637) -> 45.8562 | AF10: =IF(AD10="","",AD10*0.17637) -> 47.6199 | AG10: =IF(COUNTA(Y10,W10,AA10:AC10)=0,"",(Y10+W10+AA10+AB10+AC10)*0.17637) -> 49.73634 | AH10: =IF(AD10="","",AD10/1000) -> 0.27 | AI10: =IF(COUNTA(W10,Y10,AA10:AC10)=0,"",SUM(W10,Y10,AA10:AC10)/1000) -> 0.282 | AJ10: 9.7 | AK10: 173 | AL10: 643 | AM10: 45.8562 | AN10: =IF(OR(AE10="",AM10=""),"",AE10-AM10) -> 0
A11: DSP-BKE-2026-010 | B11: 10 | C11: 46104 | D11: BKT009 | F11: INSIDE | G11: BKE-001 | H11: WH | I11: BKE-001-BIN-017 | J11: BOUAKE | K11: 6477GX01/5949GZ01 | L11: CAMARA MAGAH | M11: DIABATESOUTRAILA | N11: 150501306 | O11: 959 | P11: 51511 | Q11: 959 | R11: 505 | S11: 40660 | T11: 40155 | U11: REACHED | V11: UNLOADED | W11: 13 | X11: 71 | Y11: 0 | Z11: =IF(COUNTA(W11:Y11)=0,"",SUM(W11:Y11)) -> 84 | AA11: 238 | AB11: 8 | AC11: 26 | AD11: =IF(COUNTA(AA11:AC11)=0,"",SUM(AA11:AC11)) -> 272 | AE11: =IF(COUNTA(AA11:AC11)<3,"",(AA11+0.5*(AB11+AC11))*0.17637) -> 44.97435 | AF11: =IF(AD11="","",AD11*0.17637) -> 47.97264 | AG11: =IF(COUNTA(Y11,W11,AA11:AC11)=0,"",(Y11+W11+AA11+AB11+AC11)*0.17637) -> 50.26545 | AH11: =IF(AD11="","",AD11/1000) -> 0.272 | AI11: =IF(COUNTA(W11,Y11,AA11:AC11)=0,"",SUM(W11,Y11,AA11:AC11)/1000) -> 0.285 | AJ11: 9.1 | AK11: 177 | AL11: 636 | AM11: 44.97435 | AN11: =IF(OR(AE11="",AM11=""),"",AE11-AM11) -> 0
A12: DSP-BKE-2026-011 | B12: 11 | C12: 46104 | D12: BKT010 | F12: INSIDE | G12: BKE-002 | H12: WH | I12: BKE-002-BIN-012 | J12: BOUAKE | K12: 7668KL04/6826KU04 | L12: CAMARA MAGAH | M12: SANGAREBRAHIMA | N12: 707391719 | O12: 960 | P12: 51516 | Q12: 960 | R12: 504 | S12: 40500 | T12: 39996 | U12: REACHED | V12: UNLOADED | W12: 13 | X12: 64 | Y12: 5 | Z12: =IF(COUNTA(W12:Y12)=0,"",SUM(W12:Y12)) -> 82 | AA12: 243 | AB12: 4 | AC12: 22 | AD12: =IF(COUNTA(AA12:AC12)=0,"",SUM(AA12:AC12)) -> 269 | AE12: =IF(COUNTA(AA12:AC12)<3,"",(AA12+0.5*(AB12+AC12))*0.17637) -> 45.15072 | AF12: =IF(AD12="","",AD12*0.17637) -> 47.44353 | AG12: =IF(COUNTA(Y12,W12,AA12:AC12)=0,"",(Y12+W12+AA12+AB12+AC12)*0.17637) -> 50.61819 | AH12: =IF(AD12="","",AD12/1000) -> 0.269 | AI12: =IF(COUNTA(W12,Y12,AA12:AC12)=0,"",SUM(W12,Y12,AA12:AC12)/1000) -> 0.287 | AJ12: 8.9 | AK12: 179 | AL12: 644 | AM12: 45.15072 | AN12: =IF(OR(AE12="",AM12=""),"",AE12-AM12) -> 0
A13: DSP-BKE-2026-012 | B13: 12 | C13: 46104 | D13: BKT011 | F13: INSIDE | G13: DIRECT-004 | H13: DIRECT | I13: DIRECT-004 | J13: BOUAKE | K13: 1011JP01/1602JE03 | L13: CAMARA MAGAH | M13: TRAOREZAKARIA | N13: 709267406 | O13: 961 | P13: 51513 | Q13: 961 | R13: 457 | S13: 40140 | T13: 39683 | U13: REACHED | V13: UNLOADED | W13: 12 | X13: 79 | Y13: 0 | Z13: =IF(COUNTA(W13:Y13)=0,"",SUM(W13:Y13)) -> 91 | AA13: 240 | AB13: 4 | AC13: 20 | AD13: =IF(COUNTA(AA13:AC13)=0,"",SUM(AA13:AC13)) -> 264 | AE13: =IF(COUNTA(AA13:AC13)<3,"",(AA13+0.5*(AB13+AC13))*0.17637) -> 44.44524 | AF13: =IF(AD13="","",AD13*0.17637) -> 46.56168 | AG13: =IF(COUNTA(Y13,W13,AA13:AC13)=0,"",(Y13+W13+AA13+AB13+AC13)*0.17637) -> 48.67812 | AH13: =IF(AD13="","",AD13/1000) -> 0.264 | AI13: =IF(COUNTA(W13,Y13,AA13:AC13)=0,"",SUM(W13,Y13,AA13:AC13)/1000) -> 0.276 | AJ13: 9.9 | AK13: 167 | AL13: 638 | AM13: 44.44524 | AN13: =IF(OR(AE13="",AM13=""),"",AE13-AM13) -> 0
A14: DSP-BKE-2026-013 | B14: 13 | C14: 46104 | D14: BKT012 | F14: INSIDE | G14: BKE-001 | H14: WH | I14: BKE-001-BIN-017 | J14: BOUAKE | K14: 9584GX03/4742BB04 | L14: SONEL TRANS | M14: DIALLOSIKKOU | N14: 778920896 | O14: 962 | P14: 51517 | Q14: 962 | R14: 472 | S14: 39060 | T14: 38588 | U14: REACHED | V14: UNLOADED | Z14: =IF(COUNTA(W14:Y14)=0,"",SUM(W14:Y14)) | AD14: =IF(COUNTA(AA14:AC14)=0,"",SUM(AA14:AC14)) | AE14: =IF(COUNTA(AA14:AC14)<3,"",(AA14+0.5*(AB14+AC14))*0.17637) | AF14: =IF(AD14="","",AD14*0.17637) | AG14: =IF(COUNTA(Y14,W14,AA14:AC14)=0,"",(Y14+W14+AA14+AB14+AC14)*0.17637) | AH14: =IF(AD14="","",AD14/1000) | AI14: =IF(COUNTA(W14,Y14,AA14:AC14)=0,"",SUM(W14,Y14,AA14:AC14)/1000) | AM14: 0 | AN14: =IF(OR(AE14="",AM14=""),"",AE14-AM14)
A15: DSP-BKE-2026-014 | B15: 14 | C15: 46105 | D15: BKT013 | F15: INSIDE | G15: DIRECT005 | H15: DIRECT | I15: DIRECT-005 | J15: BOUAKE | K15: 1447JT01/7010EJ04 | L15: CAMARA MAGAH | M15: SANGAREKARIM | N15: 501241889 | O15: 963 | P15: 51512 | Q15: 963 | R15: 526 | S15: 38520 | T15: 37994 | U15: REACHED | V15: UNLOADED | W15: 13 | X15: 74 | Y15: 3 | Z15: =IF(COUNTA(W15:Y15)=0,"",SUM(W15:Y15)) -> 90 | AA15: 237 | AB15: 6 | AC15: 22 | AD15: =IF(COUNTA(AA15:AC15)=0,"",SUM(AA15:AC15)) -> 265 | AE15: =IF(COUNTA(AA15:AC15)<3,"",(AA15+0.5*(AB15+AC15))*0.17637) -> 44.26887 | AF15: =IF(AD15="","",AD15*0.17637) -> 46.73805 | AG15: =IF(COUNTA(Y15,W15,AA15:AC15)=0,"",(Y15+W15+AA15+AB15+AC15)*0.17637) -> 49.55997 | AH15: =IF(AD15="","",AD15/1000) -> 0.265 | AI15: =IF(COUNTA(W15,Y15,AA15:AC15)=0,"",SUM(W15,Y15,AA15:AC15)/1000) -> 0.281 | AJ15: 11.7 | AK15: 169 | AL15: 641 | AM15: 44.26887 | AN15: =IF(OR(AE15="",AM15=""),"",AE15-AM15) -> 0
A16: DSP-BKE-2026-015 | B16: 15 | C16: 46105 | D16: BKT014 | F16: INSIDE | G16: BKE002 | H16: WH | I16: BKE-003-BIN-021 | J16: BOUAKE | K16: 7650HB07/2995CX04 | L16: CAMARA MAGAH | M16: RAHIMIABASI | N16: 789993743 | O16: 964 | P16: 51519 | Q16: 964 | R16: 474 | S16: 38820 | T16: 38346 | U16: REACHED | V16: UNLOADED | W16: 13 | X16: 74 | Y16: 3 | Z16: =IF(COUNTA(W16:Y16)=0,"",SUM(W16:Y16)) -> 90 | AA16: 237 | AB16: 6 | AC16: 22 | AD16: =IF(COUNTA(AA16:AC16)=0,"",SUM(AA16:AC16)) -> 265 | AE16: =IF(COUNTA(AA16:AC16)<3,"",(AA16+0.5*(AB16+AC16))*0.17637) -> 44.26887 | AF16: =IF(AD16="","",AD16*0.17637) -> 46.73805 | AG16: =IF(COUNTA(Y16,W16,AA16:AC16)=0,"",(Y16+W16+AA16+AB16+AC16)*0.17637) -> 49.55997 | AH16: =IF(AD16="","",AD16/1000) -> 0.265 | AI16: =IF(COUNTA(W16,Y16,AA16:AC16)=0,"",SUM(W16,Y16,AA16:AC16)/1000) -> 0.281 | AJ16: 11.7 | AK16: 169 | AL16: 641 | AM16: 44.26887 | AN16: =IF(OR(AE16="",AM16=""),"",AE16-AM16) -> 0
A17: DSP-BKE-2026-016 | B17: 16 | C17: 46105 | D17: BKT015 | F17: INSIDE | G17: BKE001 | H17: WH | I17: BKE-001-BIN-017 | J17: BOUAKE | K17: 9828JC03/4903AJ04 | L17: SONEL TRANS | M17: KONATEMEFOUNGO | N17: 554351133 | O17: 965 | P17: 51520 | Q17: 965 | R17: 496 | S17: 40120 | T17: 39624 | U17: REACHED | V17: UNLOADED | W17: 12 | X17: 81 | Y17: 3 | Z17: =IF(COUNTA(W17:Y17)=0,"",SUM(W17:Y17)) -> 96 | AA17: 240 | AB17: 4 | AC17: 20 | AD17: =IF(COUNTA(AA17:AC17)=0,"",SUM(AA17:AC17)) -> 264 | AE17: =IF(COUNTA(AA17:AC17)<3,"",(AA17+0.5*(AB17+AC17))*0.17637) -> 44.44524 | AF17: =IF(AD17="","",AD17*0.17637) -> 46.56168 | AG17: =IF(COUNTA(Y17,W17,AA17:AC17)=0,"",(Y17+W17+AA17+AB17+AC17)*0.17637) -> 49.20723 | AH17: =IF(AD17="","",AD17/1000) -> 0.264 | AI17: =IF(COUNTA(W17,Y17,AA17:AC17)=0,"",SUM(W17,Y17,AA17:AC17)/1000) -> 0.279 | AJ17: 10 | AK17: 172 | AL17: 636 | AM17: 44.44524 | AN17: =IF(OR(AE17="",AM17=""),"",AE17-AM17) -> 0
A18: DSP-BKE-2026-017 | B18: 17 | C18: 46105 | D18: BKT016 | F18: INSIDE | G18: BKE002 | H18: WH | I18: BKE-002-BIN-021 | J18: BOUAKE | K18: AA562FZ01/6302CS04 | L18: SONEL TRANS | M18: COULIBALYSOUMAILA | N18: 460080257 | O18: 966 | P18: 51518 | Q18: 966 | R18: 514 | S18: 41460 | T18: 40946 | U18: REACHED | V18: UNLOADED | W18: 14 | X18: 78 | Y18: 6 | Z18: =IF(COUNTA(W18:Y18)=0,"",SUM(W18:Y18)) -> 98 | AA18: 235 | AB18: 6 | AC18: 28 | AD18: =IF(COUNTA(AA18:AC18)=0,"",SUM(AA18:AC18)) -> 269 | AE18: =IF(COUNTA(AA18:AC18)<3,"",(AA18+0.5*(AB18+AC18))*0.17637) -> 44.44524 | AF18: =IF(AD18="","",AD18*0.17637) -> 47.44353 | AG18: =IF(COUNTA(Y18,W18,AA18:AC18)=0,"",(Y18+W18+AA18+AB18+AC18)*0.17637) -> 50.97093 | AH18: =IF(AD18="","",AD18/1000) -> 0.269 | AI18: =IF(COUNTA(W18,Y18,AA18:AC18)=0,"",SUM(W18,Y18,AA18:AC18)/1000) -> 0.289 | AJ18: 9.4 | AK18: 184 | AL18: 629 | AM18: 44.44524 | AN18: =IF(OR(AE18="",AM18=""),"",AE18-AM18) -> 0
A19: DSP-BKE-2026-018 | B19: 18 | C19: 46105 | D19: BKT017 | F19: INSIDE | G19: BKE001 | H19: WH | I19: BKE-001-BIN-017 | J19: BOUAKE | K19: AA087XL03/2469EK03 | L19: CAMARA MAGAH | M19: KAREMBEMALICK | N19: 502921980 | O19: 967 | P19: 51521 | Q19: 967 | R19: 504 | S19: 41100 | T19: 40596 | U19: REACHED | V19: UNLOADED | W19: 8 | X19: 71 | Y19: 0 | Z19: =IF(COUNTA(W19:Y19)=0,"",SUM(W19:Y19)) -> 79 | AA19: 238 | AB19: 8 | AC19: 24 | AD19: =IF(COUNTA(AA19:AC19)=0,"",SUM(AA19:AC19)) -> 270 | AE19: =IF(COUNTA(AA19:AC19)<3,"",(AA19+0.5*(AB19+AC19))*0.17637) -> 44.79798 | AF19: =IF(AD19="","",AD19*0.17637) -> 47.6199 | AG19: =IF(COUNTA(Y19,W19,AA19:AC19)=0,"",(Y19+W19+AA19+AB19+AC19)*0.17637) -> 49.03086 | AH19: =IF(AD19="","",AD19/1000) -> 0.27 | AI19: =IF(COUNTA(W19,Y19,AA19:AC19)=0,"",SUM(W19,Y19,AA19:AC19)/1000) -> 0.278 | AJ19: 10.5 | AK19: 169 | AL19: 648 | AM19: 44.79798 | AN19: =IF(OR(AE19="",AM19=""),"",AE19-AM19) -> 0
A20: DSP-BKE-2026-019 | B20: 19 | C20: 46105 | D20: BKT018 | F20: INSIDE | G20: BKE001 | H20: WH | I20: BKE-001-BIN-009 | J20: BOUAKE | K20: 9652HR01/8325GN01 | L20: CAMARA MAGAH | M20: POUDIOGABOUREHIMA | N20: 708099465 | O20: 968 | P20: 51522 | Q20: 968 | R20: 424 | S20: 36540 | T20: 36116 | U20: REACHED | V20: UNLOADED | W20: 16 | X20: 64 | Y20: 0 | Z20: =IF(COUNTA(W20:Y20)=0,"",SUM(W20:Y20)) -> 80 | AA20: 245 | AB20: 2 | AC20: 24 | AD20: =IF(COUNTA(AA20:AC20)=0,"",SUM(AA20:AC20)) -> 271 | AE20: =IF(COUNTA(AA20:AC20)<3,"",(AA20+0.5*(AB20+AC20))*0.17637) -> 45.50346 | AF20: =IF(AD20="","",AD20*0.17637) -> 47.79627 | AG20: =IF(COUNTA(Y20,W20,AA20:AC20)=0,"",(Y20+W20+AA20+AB20+AC20)*0.17637) -> 50.61819 | AH20: =IF(AD20="","",AD20/1000) -> 0.271 | AI20: =IF(COUNTA(W20,Y20,AA20:AC20)=0,"",SUM(W20,Y20,AA20:AC20)/1000) -> 0.287 | AJ20: 8.4 | AK20: 175 | AL20: 644 | AM20: 45.50346 | AN20: =IF(OR(AE20="",AM20=""),"",AE20-AM20) -> 0
A21: DSP-BKE-2026-020 | B21: 20 | C21: 46105 | D21: BKT019 | F21: INSIDE | G21: BKE001 | H21: WH | I21: BKE-001-BIN-009 | J21: BOUAKE | K21: AA350AM01/9546JL01 | L21: CAMARA MAGAH | M21: KONEKARIM | N21: 779774848 | O21: 969 | P21: 51523 | Q21: 969 | R21: 454 | S21: 39440 | T21: 38986 | U21: REACHED | V21: UNLOADED | W21: 16 | X21: 64 | Y21: 0 | Z21: =IF(COUNTA(W21:Y21)=0,"",SUM(W21:Y21)) -> 80 | AA21: 245 | AB21: 2 | AC21: 24 | AD21: =IF(COUNTA(AA21:AC21)=0,"",SUM(AA21:AC21)) -> 271 | AE21: =IF(COUNTA(AA21:AC21)<3,"",(AA21+0.5*(AB21+AC21))*0.17637) -> 45.50346 | AF21: =IF(AD21="","",AD21*0.17637) -> 47.79627 | AG21: =IF(COUNTA(Y21,W21,AA21:AC21)=0,"",(Y21+W21+AA21+AB21+AC21)*0.17637) -> 50.61819 | AH21: =IF(AD21="","",AD21/1000) -> 0.271 | AI21: =IF(COUNTA(W21,Y21,AA21:AC21)=0,"",SUM(W21,Y21,AA21:AC21)/1000) -> 0.287 | AJ21: 8.4 | AK21: 175 | AL21: 644 | AM21: 45.50346 | AN21: =IF(OR(AE21="",AM21=""),"",AE21-AM21) -> 0
A22: DSP-BKE-2026-021 | B22: 21 | C22: 46105 | D22: BKT020 | F22: INSIDE | G22: BKE002 | H22: WH | I22: BKE-002-BIN-020 | J22: BOUAKE | K22: 6964KV01/9943JP01 | L22: CAMARA MAGAH | M22: DISSAYAYA | N22: 594908022 | O22: 970 | P22: 51525 | Q22: 970 | R22: 480 | S22: 38900 | T22: 38420 | U22: REACHED | V22: UNLOADED | W22: 12 | X22: 69 | Y22: 0 | Z22: =IF(COUNTA(W22:Y22)=0,"",SUM(W22:Y22)) -> 81 | AA22: 245 | AB22: 6 | AC22: 18 | AD22: =IF(COUNTA(AA22:AC22)=0,"",SUM(AA22:AC22)) -> 269 | AE22: =IF(COUNTA(AA22:AC22)<3,"",(AA22+0.5*(AB22+AC22))*0.17637) -> 45.32709 | AF22: =IF(AD22="","",AD22*0.17637) -> 47.44353 | AG22: =IF(COUNTA(Y22,W22,AA22:AC22)=0,"",(Y22+W22+AA22+AB22+AC22)*0.17637) -> 49.55997 | AH22: =IF(AD22="","",AD22/1000) -> 0.269 | AI22: =IF(COUNTA(W22,Y22,AA22:AC22)=0,"",SUM(W22,Y22,AA22:AC22)/1000) -> 0.281 | AJ22: 8 | AK22: 167 | AL22: 646 | AM22: 45.32709 | AN22: =IF(OR(AE22="",AM22=""),"",AE22-AM22) -> 0
A23: DSP-BKE-2026-022 | B23: 22 | C23: 46105 | D23: BKT021 | E23: MULTI-BIN / MULTI-LINE LOAD | F23: INSIDE | G23: BKE001 | H23: WH | I23: BKE-001-BIN-009 | J23: BOUAKE | K23: 4974FC01/8694BA01 | L23: CAMARA MAGAH | M23: KONEMOUSSA | N23: 564720109 | O23: 971 | P23: 51524 | Q23: 185 | R23: 496 | S23: 14240 | T23: 14055 | U23: REACHED | V23: UNLOADED | W23: 18 | X23: 81 | Y23: 7 | Z23: =IF(COUNTA(W23:Y23)=0,"",SUM(W23:Y23)) -> 106 | AA23: 236 | AB23: 6 | AC23: 22 | AD23: =IF(COUNTA(AA23:AC23)=0,"",SUM(AA23:AC23)) -> 264 | AE23: =IF(COUNTA(AA23:AC23)<3,"",(AA23+0.5*(AB23+AC23))*0.17637) -> 44.0925 | AF23: =IF(AD23="","",AD23*0.17637) -> 46.56168 | AG23: =IF(COUNTA(Y23,W23,AA23:AC23)=0,"",(Y23+W23+AA23+AB23+AC23)*0.17637) -> 50.97093 | AH23: =IF(AD23="","",AD23/1000) -> 0.264 | AI23: =IF(COUNTA(W23,Y23,AA23:AC23)=0,"",SUM(W23,Y23,AA23:AC23)/1000) -> 0.289 | AJ23: 9.4 | AK23: 176 | AL23: 625 | AM23: 44.0925 | AN23: =IF(OR(AE23="",AM23=""),"",AE23-AM23) -> 0
A24: DSP-BKE-2026-023 | B24: 23 | C24: 46105 | D24: BKT021 | E24: MULTI-BIN / MULTI-LINE LOAD | G24: BKE001 | H24: WH | I24: BKE-001-BIN-011 | J24: BOUAKE | K24: 4974FC01/8694BA01 | L24: CAMARA MAGAH | M24: KONEMOUSSA | N24: 564720109 | O24: 971 | P24: 51524 | Q24: 311 | R24: 0 | S24: 23940 | T24: 23629 | W24: 13 | X24: 67 | Y24: 0 | Z24: =IF(COUNTA(W24:Y24)=0,"",SUM(W24:Y24)) -> 80 | AA24: 246 | AB24: 8 | AC24: 16 | AD24: =IF(COUNTA(AA24:AC24)=0,"",SUM(AA24:AC24)) -> 270 | AE24: =IF(COUNTA(AA24:AC24)<3,"",(AA24+0.5*(AB24+AC24))*0.17637) -> 45.50346 | AF24: =IF(AD24="","",AD24*0.17637) -> 47.6199 | AG24: =IF(COUNTA(Y24,W24,AA24:AC24)=0,"",(Y24+W24+AA24+AB24+AC24)*0.17637) -> 49.91271 | AH24: =IF(AD24="","",AD24/1000) -> 0.27 | AI24: =IF(COUNTA(W24,Y24,AA24:AC24)=0,"",SUM(W24,Y24,AA24:AC24)/1000) -> 0.283 | AJ24: 8.3 | AK24: 172 | AL24: 643 | AM24: 45.50346 | AN24: =IF(OR(AE24="",AM24=""),"",AE24-AM24) -> 0
A25: DSP-BKE-2026-024 | B25: 24 | C25: 46123 | D25: BKT-097 | F25: MARCHE DEGRO/ INSIDE | G25: BKE-001 | H25: DIRECT | I25: DIRECT-022 | J25: BOUAKE | K25: 4170LJ03/8364GS01 | L25: SONEL TRANS | M25: DIARRASSOUBA | N25: 500946080 | O25: 147 | P25: 51579 | R25: 446 | S25: 41800 | T25: 41354 | U25: REACHED | V25: UNLOADED | W25: 23 | X25: 84 | Y25: 7 | Z25: =IF(COUNTA(W25:Y25)=0,"",SUM(W25:Y25)) -> 114 | AA25: 215 | AB25: 10 | AC25: 26 | AD25: =IF(COUNTA(AA25:AC25)=0,"",SUM(AA25:AC25)) -> 251 | AE25: =IF(COUNTA(AA25:AC25)<3,"",(AA25+0.5*(AB25+AC25))*0.17637) -> 41.09421 | AF25: =IF(AD25="","",AD25*0.17637) -> 44.26887 | AG25: =IF(COUNTA(Y25,W25,AA25:AC25)=0,"",(Y25+W25+AA25+AB25+AC25)*0.17637) -> 49.55997 | AH25: =IF(AD25="","",AD25/1000) -> 0.251 | AI25: =IF(COUNTA(W25,Y25,AA25:AC25)=0,"",SUM(W25,Y25,AA25:AC25)/1000) -> 0.281 | AJ25: 12.4 | AK25: 156 | AL25: 630 | AM25: 41.09421 | AN25: =IF(OR(AE25="",AM25=""),"",AE25-AM25) -> 0
A26: DSP-BKE-2026-025 | B26: 25 | C26: 46140 | D26: BKT173 | F26: MARCHE DEGRO/ INSIDE | G26: BKE-001 | H26: DIRECT, WH | I26: DIRECT-085, BKE-001-BIN23 | J26: BOUAKE | K26: AA517ZT01/2496CB04 | L26: CAMARA MAGAH | M26: KONE LASSINA JUNIOR | N26: 767211670 | O26: 628 | P26: 51651 | R26: 619 | S26: 53300 | T26: 52681 | U26: REACHED | V26: UNLOADED | W26: 19 | X26: 88 | Y26: 0 | Z26: =IF(COUNTA(W26:Y26)=0,"",SUM(W26:Y26)) -> 107 | AA26: 218 | AB26: 10 | AC26: 28 | AD26: =IF(COUNTA(AA26:AC26)=0,"",SUM(AA26:AC26)) -> 256 | AE26: =IF(COUNTA(AA26:AC26)<3,"",(AA26+0.5*(AB26+AC26))*0.17637) -> 41.79969 | AF26: =IF(AD26="","",AD26*0.17637) -> 45.15072 | AG26: =IF(COUNTA(Y26,W26,AA26:AC26)=0,"",(Y26+W26+AA26+AB26+AC26)*0.17637) -> 48.50175 | AH26: =IF(AD26="","",AD26/1000) -> 0.256 | AI26: =IF(COUNTA(W26,Y26,AA26:AC26)=0,"",SUM(W26,Y26,AA26:AC26)/1000) -> 0.275 | AJ26: 12.8 | AK26: 160 | AL26: 631 | AM26: 41.79969 | AN26: =IF(OR(AE26="",AM26=""),"",AE26-AM26) -> 0
A27: DSP-BKE-2026-026 | B27: 26 | C27: 46230 | D27: BKT-250 | F27: MARCHE DEGROS/ INSIDE | G27: BKE-001 | H27: WH | I27: BKE-001-BIN-015, BKE-001-BIN-008 | J27: BOUAKE | K27: 10FK03/6498BC04 | L27: SONEL TRANS | M27: ZON HASSIMI | N27: 709344480 | O27: 475 | P27: 51733 | R27: 571 | S27: 47000 | T27: 46429 | U27: IN TRANSIT | V27: IN TRANSIT | W27: 16 | X27: 29 | Y27: 4 | Z27: =IF(COUNTA(W27:Y27)=0,"",SUM(W27:Y27)) -> 49 | AA27: 255 | AB27: 4 | AC27: 14 | AD27: =IF(COUNTA(AA27:AC27)=0,"",SUM(AA27:AC27)) -> 273 | AE27: =IF(COUNTA(AA27:AC27)<3,"",(AA27+0.5*(AB27+AC27))*0.17637) -> 46.56168 | AF27: =IF(AD27="","",AD27*0.17637) -> 48.14901 | AG27: =IF(COUNTA(Y27,W27,AA27:AC27)=0,"",(Y27+W27+AA27+AB27+AC27)*0.17637) -> 51.67641 | AH27: =IF(AD27="","",AD27/1000) -> 0.273 | AI27: =IF(COUNTA(W27,Y27,AA27:AC27)=0,"",SUM(W27,Y27,AA27:AC27)/1000) -> 0.293 | AJ27: 7.8 | AK27: 171 | AL27: 675 | AM27: 46.56168 | AN27: =IF(OR(AE27="",AM27=""),"",AE27-AM27) -> 0
A28: DSP-BKE-2026-027 | B28: 27 | C28: 46251 | D28: BKT-326 | F28: MARCHE DEGROS/ INSIDE | G28: BKE-003 | H28: WH | I28: BKE-003-BIN-001 | J28: BOUAKE | K28: 5019FE04/2606JT01 | L28: SONEL TRANS | M28: KONATE YACOU | N28: 706616964 | O28: 1201 | P28: 52948 | R28: 490 | S28: 40980 | T28: 40490 | U28: IN TRANSIT | V28: IN TRANSIT | W28: 7 | X28: 20 | Y28: 0 | Z28: =IF(COUNTA(W28:Y28)=0,"",SUM(W28:Y28)) -> 27 | AA28: 272 | AB28: 2 | AC28: 10 | AD28: =IF(COUNTA(AA28:AC28)=0,"",SUM(AA28:AC28)) -> 284 | AE28: =IF(COUNTA(AA28:AC28)<3,"",(AA28+0.5*(AB28+AC28))*0.17637) -> 49.03086 | AF28: =IF(AD28="","",AD28*0.17637) -> 50.08908 | AG28: =IF(COUNTA(Y28,W28,AA28:AC28)=0,"",(Y28+W28+AA28+AB28+AC28)*0.17637) -> 51.32367 | AH28: =IF(AD28="","",AD28/1000) -> 0.284 | AI28: =IF(COUNTA(W28,Y28,AA28:AC28)=0,"",SUM(W28,Y28,AA28:AC28)/1000) -> 0.291 | AJ28: 7.4 | AK28: 176 | AL28: 683 | AM28: 49.03086 | AN28: =IF(OR(AE28="",AM28=""),"",AE28-AM28) -> 0

Sheet Stock Transfers
A1: Row ID | B1: No | C1: Date | D1: Month | E1: Dry or Undry | F1: Transfer ID | G1: Truck Registration | H1: Lot No | I1: Lot Dry | J1: Fiche No | K1: CCA Fiche No | L1: Bin No | M1: From Warehouse | N1: To Warehouse | O1: Origin | P1: Bags Dispatched | Q1: Bags Received | R1: Damaged Bags | S1: New Jute Bags Used | T1: Reconditioned Bags | U1: Laissez-Passer (Entry) | V1: Loaded Truck Weight (kg) | W1: Empty Truck Weight (kg) | X1: Gross Weight Received (kg) | Y1: Net Weight at Arrival (kg) | Z1: Net Weight Dispatched (kg) | AA1: KOR Received | AB1: KOR Dispatched | AC1: Moisture Received (%) | AD1: Moisture Dispatched (%) | AE1: Nut Count at Arrival | AF1: Comment | AG1: Transfer Status | AH1: Receipt Date | AI1: Bag Variance | AJ1: Weight Variance (kg)
A2: TRF-BKE-2026-001 | B2: 1 | C2: 46098 | D2: =IF(C2="","",TEXT(C2,"mmm-yyyy")) -> Mar-2026 | F2: BKT001 | G2: 1796GC01/3922BB04 | H2: LOT-YAK-2026-0002 | J2: 951 | K2: 51505 | L2: BKE-002-BIN-012 | M2: BKE-002 | N2: YAKRO FACTORY | O2: BOUAKE | P2: 590 | Q2: 574 | U2: 151 | V2: 48880 | X2: 48820 | Y2: 48246 | Z2: 48290 | AA2: 45.15 | AB2: 45.15072 | AC2: 8.8 | AD2: 8.8 | AE2: 172 | AG2: =IF(Q2="","IN TRANSIT",IF(OR(AI2<>0,AJ2<>0),"DISCREPANCY","CLOSED")) -> DISCREPANCY | AH2: 46099 | AI2: =IF(OR(P2="",Q2=""),"",Q2-P2) -> -16 | AJ2: =IF(OR(Z2="",Y2=""),"",Y2-Z2) -> -44
A3: TRF-BKE-2026-002 | B3: 2 | C3: 46098 | D3: =IF(C3="","",TEXT(C3,"mmm-yyyy")) -> Mar-2026 | F3: BKT002 | G3: 7957-GN-01/3599-KV-01 | H3: LOT-YAK-2026-0003 | J3: 952 | K3: 51506 | L3: BKE-002-BIN-012 | M3: BKE-002 | N3: YAKRO FACTORY | O3: BOUAKE | P3: 590 | Q3: 618 | U3: 153 | V3: 48680 | X3: 48620 | Y3: 48002 | Z3: 48090 | AA3: 44.94 | AB3: 45.67983 | AC3: 9.5 | AD3: 9.2 | AE3: 184 | AG3: =IF(Q3="","IN TRANSIT",IF(OR(AI3<>0,AJ3<>0),"DISCREPANCY","CLOSED")) -> DISCREPANCY | AH3: 46099 | AI3: =IF(OR(P3="",Q3=""),"",Q3-P3) -> 28 | AJ3: =IF(OR(Z3="",Y3=""),"",Y3-Z3) -> -88
A4: TRF-BKE-2026-003 | B4: 3 | C4: 46098 | D4: =IF(C4="","",TEXT(C4,"mmm-yyyy")) -> Mar-2026 | F4: BKT003 | G4: 3334-FN-01 | J4: 953 | K4: 51507 | L4: BKE-001-BIN-016 | M4: BKE-002 | N4: YAKRO FACTORY | O4: BOUAKE | P4: 523 | V4: 42140 | Z4: 41617 | AB4: 46.91442 | AD4: 9.3 | AG4: =IF(Q4="","IN TRANSIT",IF(OR(AI4<>0,AJ4<>0),"DISCREPANCY","CLOSED")) -> IN TRANSIT | AI4: =IF(OR(P4="",Q4=""),"",Q4-P4) | AJ4: =IF(OR(Z4="",Y4=""),"",Y4-Z4)
A5: TRF-BKE-2026-004 | B5: 4 | C5: 46099 | D5: =IF(C5="","",TEXT(C5,"mmm-yyyy")) -> Mar-2026 | F5: BKT004 | G5: 847HH04/850HH04 | H5: LOT-YAK-2026-0004 | J5: 954 | K5: 51508 | L5: BKE-002-BIN-012 | M5: BKE-002 | N5: YAKRO FACTORY | O5: BOUAKE | P5: 526 | Q5: 521 | U5: 154 | V5: 41420 | X5: 41240 | Y5: 40719 | Z5: 40894 | AA5: 44.52 | AB5: 45.50346 | AC5: 8.9 | AD5: 8 | AE5: 192 | AG5: =IF(Q5="","IN TRANSIT",IF(OR(AI5<>0,AJ5<>0),"DISCREPANCY","CLOSED")) -> DISCREPANCY | AH5: 46104 | AI5: =IF(OR(P5="",Q5=""),"",Q5-P5) -> -5 | AJ5: =IF(OR(Z5="",Y5=""),"",Y5-Z5) -> -175
A6: TRF-BKE-2026-005 | B6: 5 | C6: 46099 | D6: =IF(C6="","",TEXT(C6,"mmm-yyyy")) -> Mar-2026 | F6: BKT005 | G6: 9008JH04/9011JH04 | H6: LOT-YAK-2026-0005 | J6: 955 | K6: 52047 | L6: DIRECT-001 | M6: DIRECT-001 | N6: YAKRO FACTORY | O6: BOUAKE | P6: 592 | Q6: 608 | U6: 155 | V6: 50760 | X6: 51840 | Y6: 51232 | Z6: 50168 | AA6: 45.49 | AB6: 46.03257 | AC6: 11.2 | AD6: 12 | AE6: 157 | AG6: =IF(Q6="","IN TRANSIT",IF(OR(AI6<>0,AJ6<>0),"DISCREPANCY","CLOSED")) -> DISCREPANCY | AH6: 46104 | AI6: =IF(OR(P6="",Q6=""),"",Q6-P6) -> 16 | AJ6: =IF(OR(Z6="",Y6=""),"",Y6-Z6) -> 1064
A7: TRF-BKE-2026-006 | B7: 6 | C7: 46104 | D7: =IF(C7="","",TEXT(C7,"mmm-yyyy")) -> Mar-2026 | F7: BKT006 | G7: AA244BT03/3762BN01 | J7: 956 | K7: 51515 | L7: DIRECT-002 | M7: DIRECT-002 | N7: YAKRO FACTORY | O7: BOUAKE | P7: 678 | V7: 54940 | Z7: 54262 | AB7: 45.50346 | AD7: 10.7 | AG7: =IF(Q7="","IN TRANSIT",IF(OR(AI7<>0,AJ7<>0),"DISCREPANCY","CLOSED")) -> IN TRANSIT | AI7: =IF(OR(P7="",Q7=""),"",Q7-P7) | AJ7: =IF(OR(Z7="",Y7=""),"",Y7-Z7)
A8: TRF-BKE-2026-007 | B8: 7 | C8: 46104 | D8: =IF(C8="","",TEXT(C8,"mmm-yyyy")) -> Mar-2026 | F8: BKT007 | G8: 997JY01/4285CH04 | H8: LOT-YAK-2026-0007 | J8: 957 | K8: 51514 | L8: BKE-002-BIN-012 / BKE-001-BIN-008 | M8: BKE-002 / BKE-001 | N8: YAKRO FACTORY | O8: BOUAKE | P8: 494 | Q8: 516 | U8: 160 | V8: 40200 | X8: 40300 | Y8: 39784 | Z8: 39706 | AA8: 44.17 | AB8: 44.97435 | AC8: 9.8 | AD8: 9.8 | AE8: 180 | AG8: =IF(Q8="","IN TRANSIT",IF(OR(AI8<>0,AJ8<>0),"DISCREPANCY","CLOSED")) -> DISCREPANCY | AH8: 46105 | AI8: =IF(OR(P8="",Q8=""),"",Q8-P8) -> 22 | AJ8: =IF(OR(Z8="",Y8=""),"",Y8-Z8) -> 78
A9: TRF-BKE-2026-008 | B9: 8 | C9: 46104 | D9: =IF(C9="","",TEXT(C9,"mmm-yyyy")) -> Mar-2026 | F9: BKT008 | G9: 827KT01/57AY01 | H9: LOT-YAK-2026-0010 | J9: 958 | K9: 51510 | L9: DIRECT-003 | M9: DIRECT-003 | N9: YAKRO FACTORY | O9: BOUAKE | P9: 511 | Q9: 434 | U9: 168 | V9: 40280 | X9: 40400 | Y9: 39966 | Z9: 39769 | AA9: 44.88 | AB9: 45.8562 | AC9: 8.9 | AD9: 9.7 | AE9: 184 | AG9: =IF(Q9="","IN TRANSIT",IF(OR(AI9<>0,AJ9<>0),"DISCREPANCY","CLOSED")) -> DISCREPANCY | AH9: 46107 | AI9: =IF(OR(P9="",Q9=""),"",Q9-P9) -> -77 | AJ9: =IF(OR(Z9="",Y9=""),"",Y9-Z9) -> 197
A10: TRF-BKE-2026-009 | B10: 9 | C10: 46104 | D10: =IF(C10="","",TEXT(C10,"mmm-yyyy")) -> Mar-2026 | F10: BKT009 | G10: 6477GX01/5949GZ01 | H10: LOT-YAK-2026-0012 | J10: 959 | K10: 51511 | L10: BKE-001-BIN-017 | M10: BKE-001 | N10: YAKRO FACTORY | O10: BOUAKE | P10: 505 | Q10: 519 | U10: 162 | V10: 40660 | X10: 40760 | Y10: 40241 | Z10: 40155 | AA10: 44.96 | AB10: 44.97435 | AC10: 8.6 | AD10: 9.1 | AE10: 178 | AG10: =IF(Q10="","IN TRANSIT",IF(OR(AI10<>0,AJ10<>0),"DISCREPANCY","CLOSED")) -> DISCREPANCY | AH10: 46105 | AI10: =IF(OR(P10="",Q10=""),"",Q10-P10) -> 14 | AJ10: =IF(OR(Z10="",Y10=""),"",Y10-Z10) -> 86
A11: TRF-BKE-2026-010 | B11: 10 | C11: 46104 | D11: =IF(C11="","",TEXT(C11,"mmm-yyyy")) -> Mar-2026 | F11: BKT010 | G11: 7668KL04/6826KU04 | H11: LOT-YAK-2026-0010 | J11: 960 | K11: 51516 | L11: BKE-002-BIN-012 | M11: BKE-002 | N11: YAKRO FACTORY | O11: BOUAKE | P11: 504 | Q11: 560 | U11: 158 | V11: 40500 | X11: 40740 | Y11: 40180 | Z11: 39996 | AA11: 44.7 | AB11: 45.15072 | AC11: 8.8 | AD11: 8.9 | AE11: 168 | AG11: =IF(Q11="","IN TRANSIT",IF(OR(AI11<>0,AJ11<>0),"DISCREPANCY","CLOSED")) -> DISCREPANCY | AH11: 46105 | AI11: =IF(OR(P11="",Q11=""),"",Q11-P11) -> 56 | AJ11: =IF(OR(Z11="",Y11=""),"",Y11-Z11) -> 184
A12: TRF-BKE-2026-011 | B12: 11 | C12: 46104 | D12: =IF(C12="","",TEXT(C12,"mmm-yyyy")) -> Mar-2026 | F12: BKT011 | G12: 1011JP01/1602JE03 | J12: 961 | K12: 51513 | L12: DIRECT-004 | M12: DIRECT-004 | N12: YAKRO FACTORY | O12: BOUAKE | P12: 457 | V12: 40140 | Z12: 39683 | AB12: 44.44524 | AD12: 9.9 | AG12: =IF(Q12="","IN TRANSIT",IF(OR(AI12<>0,AJ12<>0),"DISCREPANCY","CLOSED")) -> IN TRANSIT | AI12: =IF(OR(P12="",Q12=""),"",Q12-P12) | AJ12: =IF(OR(Z12="",Y12=""),"",Y12-Z12)
A13: TRF-BKE-2026-012 | B13: 12 | C13: 46104 | D13: =IF(C13="","",TEXT(C13,"mmm-yyyy")) -> Mar-2026 | F13: BKT012 | G13: 9584GX03/4742BB04 | H13: LOT-YAK-2026-0009 | J13: 962 | K13: 51517 | L13: BKE-001-BIN-017 | M13: BKE-001 | N13: YAKRO FACTORY | O13: BOUAKE | P13: 472 | Q13: 513 | U13: 157 | V13: 39060 | X13: 39120 | Y13: 38607 | Z13: 38588 | AA13: 45.05 | AB13: 0 | AC13: 9.7 | AE13: 168 | AG13: =IF(Q13="","IN TRANSIT",IF(OR(AI13<>0,AJ13<>0),"DISCREPANCY","CLOSED")) -> DISCREPANCY | AH13: 46105 | AI13: =IF(OR(P13="",Q13=""),"",Q13-P13) -> 41 | AJ13: =IF(OR(Z13="",Y13=""),"",Y13-Z13) -> 19
A14: TRF-BKE-2026-013 | B14: 13 | C14: 46105 | D14: =IF(C14="","",TEXT(C14,"mmm-yyyy")) -> Mar-2026 | F14: BKT013 | G14: 1447JT01/7010EJ04 | H14: LOT-YAK-2026-0020 | J14: 963 | K14: 51512 | L14: DIRECT-005 | M14: DIRECT005 | N14: YAKRO FACTORY | O14: BOUAKE | P14: 526 | Q14: 537 | U14: 176 | V14: 38520 | X14: 38380 | Y14: 37843 | Z14: 37994 | AA14: 44.26 | AB14: 44.26887 | AC14: 10.9 | AD14: 11.7 | AE14: 174 | AG14: =IF(Q14="","IN TRANSIT",IF(OR(AI14<>0,AJ14<>0),"DISCREPANCY","CLOSED")) -> DISCREPANCY | AH14: 46109 | AI14: =IF(OR(P14="",Q14=""),"",Q14-P14) -> 11 | AJ14: =IF(OR(Z14="",Y14=""),"",Y14-Z14) -> -151
A15: TRF-BKE-2026-014 | B15: 14 | C15: 46105 | D15: =IF(C15="","",TEXT(C15,"mmm-yyyy")) -> Mar-2026 | F15: BKT014 | G15: 7650HB07/2995CX04 | H15: LOT-YAK-2026-0014 | J15: 964 | K15: 51519 | L15: BKE-003-BIN-021 | M15: BKE002 | N15: YAKRO FACTORY | O15: BOUAKE | P15: 474 | Q15: 487 | U15: 166 | V15: 38820 | X15: 39040 | Y15: 38553 | Z15: 38346 | AA15: 44.52 | AB15: 44.26887 | AC15: 9.9 | AD15: 11.7 | AE15: 160 | AG15: =IF(Q15="","IN TRANSIT",IF(OR(AI15<>0,AJ15<>0),"DISCREPANCY","CLOSED")) -> DISCREPANCY | AH15: 46107 | AI15: =IF(OR(P15="",Q15=""),"",Q15-P15) -> 13 | AJ15: =IF(OR(Z15="",Y15=""),"",Y15-Z15) -> 207
A16: TRF-BKE-2026-015 | B16: 15 | C16: 46105 | D16: =IF(C16="","",TEXT(C16,"mmm-yyyy")) -> Mar-2026 | F16: BKT015 | G16: 9828JC03/4903AJ04 | J16: 965 | K16: 51520 | L16: BKE-001-BIN-017 | M16: BKE001 | N16: YAKRO FACTORY | O16: BOUAKE | P16: 496 | V16: 40120 | Z16: 39624 | AB16: 44.44524 | AD16: 10 | AG16: =IF(Q16="","IN TRANSIT",IF(OR(AI16<>0,AJ16<>0),"DISCREPANCY","CLOSED")) -> IN TRANSIT | AI16: =IF(OR(P16="",Q16=""),"",Q16-P16) | AJ16: =IF(OR(Z16="",Y16=""),"",Y16-Z16)
A17: TRF-BKE-2026-016 | B17: 16 | C17: 46105 | D17: =IF(C17="","",TEXT(C17,"mmm-yyyy")) -> Mar-2026 | F17: BKT016 | G17: AA562FZ01/6302CS04 | H17: LOT-YAK-2026-0013 | J17: 966 | K17: 51518 | L17: BKE-002-BIN-021 | M17: BKE002 | N17: YAKRO FACTORY | O17: BOUAKE | P17: 514 | Q17: 525 | U17: 167 | V17: 41460 | X17: 41560 | Y17: 41035 | Z17: 40946 | AA17: 44.35 | AB17: 44.44524 | AC17: 10.3 | AD17: 9.4 | AE17: 172 | AG17: =IF(Q17="","IN TRANSIT",IF(OR(AI17<>0,AJ17<>0),"DISCREPANCY","CLOSED")) -> DISCREPANCY | AH17: 46107 | AI17: =IF(OR(P17="",Q17=""),"",Q17-P17) -> 11 | AJ17: =IF(OR(Z17="",Y17=""),"",Y17-Z17) -> 89
A18: TRF-BKE-2026-017 | B18: 17 | C18: 46105 | D18: =IF(C18="","",TEXT(C18,"mmm-yyyy")) -> Mar-2026 | F18: BKT017 | G18: AA087XL03/2469EK03 | H18: LOT-YAK-2026-0018 | J18: 967 | K18: 51521 | L18: BKE-001-BIN-017 | M18: BKE001 | N18: YAKRO FACTORY | O18: BOUAKE | P18: 504 | Q18: 486 | U18: 159 | V18: 41100 | X18: 41160 | Y18: 40674 | Z18: 40596 | AA18: 44.52 | AB18: 44.79798 | AC18: 10 | AD18: 10.5 | AE18: 185 | AG18: =IF(Q18="","IN TRANSIT",IF(OR(AI18<>0,AJ18<>0),"DISCREPANCY","CLOSED")) -> DISCREPANCY | AH18: 46107 | AI18: =IF(OR(P18="",Q18=""),"",Q18-P18) -> -18 | AJ18: =IF(OR(Z18="",Y18=""),"",Y18-Z18) -> 78
A19: TRF-BKE-2026-018 | B19: 18 | C19: 46105 | D19: =IF(C19="","",TEXT(C19,"mmm-yyyy")) -> Mar-2026 | F19: BKT018 | G19: 9652HR01/8325GN01 | H19: LOT-YAK-2026-0021 | J19: 968 | K19: 51522 | L19: BKE-001-BIN-009 | M19: BKE001 | N19: YAKRO FACTORY | O19: BOUAKE | P19: 424 | Q19: 439 | U19: 172 | V19: 36540 | X19: 36500 | Y19: 36061 | Z19: 36116 | AA19: 45.23 | AB19: 45.50346 | AC19: 9.8 | AD19: 8.4 | AE19: 173 | AG19: =IF(Q19="","IN TRANSIT",IF(OR(AI19<>0,AJ19<>0),"DISCREPANCY","CLOSED")) -> DISCREPANCY | AH19: 46108 | AI19: =IF(OR(P19="",Q19=""),"",Q19-P19) -> 15 | AJ19: =IF(OR(Z19="",Y19=""),"",Y19-Z19) -> -55
A20: TRF-BKE-2026-019 | B20: 19 | C20: 46105 | D20: =IF(C20="","",TEXT(C20,"mmm-yyyy")) -> Mar-2026 | F20: BKT019 | G20: AA350AM01/9546JL01 | J20: 969 | K20: 51523 | L20: BKE-001-BIN-009 | M20: BKE001 | N20: YAKRO FACTORY | O20: BOUAKE | P20: 454 | V20: 39440 | Z20: 38986 | AB20: 45.50346 | AD20: 8.4 | AG20: =IF(Q20="","IN TRANSIT",IF(OR(AI20<>0,AJ20<>0),"DISCREPANCY","CLOSED")) -> IN TRANSIT | AI20: =IF(OR(P20="",Q20=""),"",Q20-P20) | AJ20: =IF(OR(Z20="",Y20=""),"",Y20-Z20)
A21: TRF-BKE-2026-020 | B21: 20 | C21: 46105 | D21: =IF(C21="","",TEXT(C21,"mmm-yyyy")) -> Mar-2026 | F21: BKT020 | G21: 6964KV01/9943JP01 | H21: LOT-YAK-2026-0017 | J21: 970 | K21: 51525 | L21: BKE-002-BIN-020 | M21: BKE002 | N21: YAKRO FACTORY | O21: BOUAKE | P21: 480 | Q21: 477 | U21: 163 | V21: 38900 | X21: 38600 | Y21: 38123 | Z21: 38420 | AA21: 43.82 | AB21: 45.32709 | AC21: 9.8 | AD21: 8 | AE21: 179 | AG21: =IF(Q21="","IN TRANSIT",IF(OR(AI21<>0,AJ21<>0),"DISCREPANCY","CLOSED")) -> DISCREPANCY | AH21: 46107 | AI21: =IF(OR(P21="",Q21=""),"",Q21-P21) -> -3 | AJ21: =IF(OR(Z21="",Y21=""),"",Y21-Z21) -> -297
A22: TRF-BKE-2026-021 | B22: 21 | C22: 46105 | D22: =IF(C22="","",TEXT(C22,"mmm-yyyy")) -> Mar-2026 | F22: BKT021 | G22: 4974FC01/8694BA01 | H22: LOT-YAK-2026-0016 | J22: 971 | K22: 51524 | L22: BKE-001-BIN-009 / BKE-001-BIN-011 | M22: BKE001 | N22: YAKRO FACTORY | O22: BOUAKE | P22: 496 | Q22: 505 | U22: 164 | V22: 38180 | X22: 38080 | Y22: 37575 | Z22: 37684 | AA22: 45.05 | AB22: 44.0925 | AC22: 9.4 | AD22: 9.4 | AE22: 178 | AG22: =IF(Q22="","IN TRANSIT",IF(OR(AI22<>0,AJ22<>0),"DISCREPANCY","CLOSED")) -> DISCREPANCY | AH22: 46107 | AI22: =IF(OR(P22="",Q22=""),"",Q22-P22) -> 9 | AJ22: =IF(OR(Z22="",Y22=""),"",Y22-Z22) -> -109
